Workbook

Sheet Read Me
A1: Anthropic (ANT) IPO Valuation — Hybrid Business Model
A2: Prepared by Mike Ye | mikeye.com | Version 1.3.1, October 26, 2026 | Reviewed over three rounds with an independent AI audit (Ella) and revised
A4: WHAT THIS IS
A5: A scenario valuation of Anthropic built from its public S-1. It values (1) the business as it exists today, pay-per-token plus subscriptions, and (2) a hybrid that adds a
A6: hypothetical third line where Anthropic takes a cut of measurable value Claude creates for partners. The question: can tokens and subscriptions alone support a $2T valuation?
A7: Reported facts, figures derived from the filing, and hypothetical assumptions are labeled separately.
A9: HOW TO USE IT
A10: Change yellow cells on Inputs and the model recalculates. Input checks at the bottom of Inputs reject invalid entries (negative costs, fractional depreciation lives,
A11: stock comp above personnel); loss-making scenarios are allowed and show 'Not meaningful' instead. The Summary shows the check result in cell A3.
A12: Color code: blue = typed in (reported or assumed); black = formula; green = link to another tab; yellow fill = assumption you can change.
A14: TABS
A15: Summary — results, linked limitations, value-share break-even tests, market check, $2T test, tax sensitivity. Change Log — v1.2 to v1.3 changes and verification table.
... A64: Anthropic has not reviewed or endorsed this model. Do your own research.

Sheet Summary
A1: Anthropic (ANT) — IPO valuation: core business vs. hybrid business model (v1.3.1)
A2: Prepared by Mike Ye, mikeye.com. $ billions except per share. Change yellow cells on Inputs. Not investment advice — see Read Me.
A3: =Inputs!C131 -> All input checks passed
A4: Valuation | B4: Bear | C4: Base | D4: Bull | E4: Weighted
A5: Value per share — hybrid | B5: =Bear!G189 -> 12.973183 | C5: =Base!G189 -> 87.834506 | D5: =Bull!G189 -> 347.32945 | E5: =IF(Inputs!$B$131>0,"check inputs",IF(COUNT(B5:D5)<3,"n/a",SUMPRODUCT(B5:D5,$B$13:$D$13))) -> 133.99291
A6: Value per share — core only (tokens + subscriptions) | B6: =Bear!F189 -> 14.541989 | C6: =Base!F189 -> 76.388093 | D6: =Bull!F189 -> 196.94872 | E6: =IF(Inputs!$B$131>0,"check inputs",IF(COUNT(B6:D6)<3,"n/a",SUMPRODUCT(B6:D6,$B$13:$D$13))) -> 91.066722
A7: Equity value — hybrid ($B) | B7: =IFERROR(Bear!G191/1000,"n/a") -> 232.25449 | C7: =IFERROR(Base!G191/1000,"n/a") -> 1572.4713 | D7: =IFERROR(Bull!G191/1000,"n/a") -> 6598.7198 | E7: =IF(Inputs!$B$131>0,"check inputs",IF(COUNT(B7:D7)<3,"n/a",SUMPRODUCT(B7:D7,$B$13:$D$13))) -> 2493.9792
A8: Equity value — core only ($B) | B8: =IFERROR(Bear!F191/1000,"n/a") -> 260.34029 | C8: =IFERROR(Base!F191/1000,"n/a") -> 1367.5501 | D8: =IFERROR(Bull!F191/1000,"n/a") -> 3668.3525 | E8: =IF(Inputs!$B$131>0,"check inputs",IF(COUNT(B8:D8)<3,"n/a",SUMPRODUCT(B8:D8,$B$13:$D$13))) -> 1665.9482
A9: Hybrid uplift vs. core | B9: =IFERROR(B7/B8-1,"n/a") -> -0.10788113 | C9: =IFERROR(C7/C8-1,"n/a") -> 0.14984552 | D9: =IFERROR(D7/D8-1,"n/a") -> 0.79882381 | E9: =IFERROR(E7/E8-1,"n/a") -> 0.49703285
A10: Funding status (hybrid) | B10: =Bear!G183 -> No raise needed | C10: =Base!G183 -> No raise needed | D10: =Bull!G183 -> No raise needed
A11: Public Benefit issuance steps (hybrid) | B11: =Bear!G188 -> 0 | C11: =Base!G188 -> 0 | D11: =Bull!G188 -> 3
A12: Exit value share of value — P/E / cash flow (hybrid) | B12: =TEXT(Bear!G172,"0%")&" / "&TEXT(Bear!G173,"0%") -> 93% / 88% | C12: =TEXT(Base!G172,"0%")&" / "&TEXT(Base!G173,"0%") -> 93% / 92% | D12: =TEXT(Bull!G172,"0%")&" / "&TEXT(Bull!G173,"0%") -> 94% / 93%
A13: Probability | B13: =Inputs!B93 -> 0.25 | C13: =Inputs!C93 -> 0.5 | D13: =Inputs!D93 -> 0.25 | E13: =SUM($B$13:$D$13) -> 1
A14: Bull case share of weighted hybrid value per share | E14: =IFERROR(D13*D5/E5,"n/a") -> 0.64803699
A16: Headline limitations (linked) | B16: Value
A17: Base hybrid value per share | B17: =C5 -> 87.834506
A18: Combined-stress (S6) hybrid value per share | B18: =S6!G189 -> unresolved
A19: Combined-stress funding status | B19: =S6!G183 -> Not meaningful: 2030 earnings or cash flow negative
A20: Flat-revenue stress (S1): cash at end 2030 and runway | B20: =TEXT(S1!G141/1000,"$0.0")&"B; "&IF(ISNUMBER(S1!G181),TEXT(S1!G181,"0.0")&" years of cash at 2030 burn","cash-positive") -> $12.4B; 0.2 years of cash at 2030 burn
A21: Base: exit value share of value (P/E method / cash flow method) | B21: =C12 -> 93% / 92%
A22: Bull share of weighted value | B22: =E14 -> 0.64803699
A23: Both valuation methods use the same forecasts, so blending them is not independent confirmation. Most value sits in the post-2030 exit value.
A24: ="Assumed, not disclosed: state tax on "&TEXT(Inputs!$B$46,"0%")&" of income at "&TEXT(Inputs!$B$47,"0.0%")&" gives a mature combined rate of "&TEXT(Inputs!$B$43+Inputs!$B$46*Inputs!$B$47*(1-Inputs!$B$43),"0.00%")&". Covenant: $5B minimum liquidity from Q4 2026 (cash used as proxy)." -> Assumed, not disclosed: state tax on 72% of income at 6.0% gives a mature combined rate of 24.41%. Covenant: $5B minimum liquidity from Q4 2026 (cash used as proxy).
A25: 2030 snapshot | B25: Bear | C25: Base | D25: Bull
A26: Core revenue ($B) | B26: =IFERROR(Bear!G5/1000,"n/a") -> 148.48005 | C26: =IFERROR(Base!G5/1000,"n/a") -> 283.68023 | D26: =IFERROR(Bull!G5/1000,"n/a") -> 521.49015
A27: Hybrid total revenue ($B) | B27: =IFERROR(Bear!G105/1000,"n/a") -> 147.73765 | C27: =IFERROR(Base!G105/1000,"n/a") -> 321.97706 | D27: =IFERROR(Bull!G105/1000,"n/a") -> 808.30973
A28: Value-share revenue, gross ($B) | B28: =IFERROR(Bear!G29/1000,"n/a") -> 2.969601 | C28: =IFERROR(Base!G29/1000,"n/a") -> 51.062441 | D28: =IFERROR(Bull!G29/1000,"n/a") -> 312.89409
A29: Core operating margin (after stock comp & depreciation) | B29: =Bear!G54 -> 0.094094487 | C29: =Base!G54 -> 0.30031884 | D29: =Bull!G54 -> 0.40821284
A30: Hybrid operating margin | B30: =Bear!G110 -> 0.07556148 | C30: =Base!G110 -> 0.31006794 | D30: =Bull!G110 -> 0.48419351
A31: Compute % of core revenue | B31: =Bear!G19 -> 0.51550418 | C31: =Base!G19 -> 0.3526967 | D31: =Bull!G19 -> 0.2872467
A32: Effective tax rate (hybrid) | B32: =Bear!G126 -> 0.244128 | C32: =Base!G126 -> 0.244128 | D32: =Bull!G126 -> 0.244128
A33: Value created for partners ($B) | B33: =IFERROR(Bear!G27/1000,"n/a") -> 29.69601 | C33: =IFERROR(Base!G27/1000,"n/a") -> 340.41627 | D33: =IFERROR(Bull!G27/1000,"n/a") -> 1564.4705
A34: Value created as % of $40T knowledge-work pool | B34: =Bear!G36 -> 0.00074240026 | C34: =Base!G36 -> 0.0085104067 | D34: =Bull!G36 -> 0.039111761
A36: Value-share break-even tests (per $1 of revenue moved, 2030 steady state) | B36: Bear | C36: Base | D36: Bull
A37: 1. Operating: contribution per $1 moved | B37: =Inputs!$B$101*Inputs!$B$102*(1-Inputs!$B$104-Inputs!$B$105-Inputs!$B$106)-Inputs!$B$103 -> -0.38 | C37: =Inputs!$C$101*Inputs!$C$102*(1-Inputs!$C$104-Inputs!$C$105-Inputs!$C$106)-Inputs!$C$103 -> 0.36 | D37: =Inputs!$D$101*Inputs!$D$102*(1-Inputs!$D$104-Inputs!$D$105-Inputs!$D$106)-Inputs!$D$103 -> 1.408
A38: 2. Cash: after tax, capex and its depreciation tax shield, per $1 moved (steady state) | B38: =(1-Bear!G126)*(Inputs!$B$101*Inputs!$B$102*(1-Inputs!$B$104-Inputs!$B$105-Inputs!$B$106)-Inputs!$B$103-CHOOSE(Inputs!$B$35,Inputs!$F$55*(Inputs!$B$101*Inputs!$B$102-Inputs!$B$103),Inputs!$B$36*Inputs!$B$101*Inputs!$B$102,0)) -> -0.283452 | C38: =(1-Base!G126)*(Inputs!$C$101*Inputs!$C$102*(1-Inputs!$C$104-Inputs!$C$105-Inputs!$C$106)-Inputs!$C$103-CHOOSE(Inputs!$B$35,Inputs!$F$55*(Inputs!$C$101*Inputs!$C$102-Inputs!$C$103),Inputs!$B$36*Inputs!$C$101*Inputs!$C$102,0)) -> 0.23809968 | D38: =(1-Bull!G126)*(Inputs!$D$101*Inputs!$D$102*(1-Inputs!$D$104-Inputs!$D$105-Inputs!$D$106)-Inputs!$D$103-CHOOSE(Inputs!$B$35,Inputs!$F$55*(Inputs!$D$101*Inputs!$D$102-Inputs!$D$103),Inputs!$B$36*Inputs!$D$101*Inputs!$D$102,0)) -> 0.98112186
A39: 3. Value: hybrid equity less core equity ($B) | B39: =IFERROR(Bear!G191/1000-Bear!F191/1000,"n/a") -> -28.085805 | C39: =IFERROR(Base!G191/1000-Base!F191/1000,"n/a") -> 204.92125 | D39: =IFERROR(Bull!G191/1000-Bull!F191/1000,"n/a") -> 2930.3673
A40: Minimum cut to pass operating test | B40: =IFERROR(Inputs!$B$103/(Inputs!$B$101*(1-Inputs!$B$104-Inputs!$B$105-Inputs!$B$106)),0) -> 0.41666667 | C40: =IFERROR(Inputs!$C$103/(Inputs!$C$101*(1-Inputs!$C$104-Inputs!$C$105-Inputs!$C$106)),0) -> 0.068181818 | D40: =IFERROR(Inputs!$D$103/(Inputs!$D$101*(1-Inputs!$D$104-Inputs!$D$105-Inputs!$D$106)),0) -> 0.024875622
A41: Minimum cut to pass cash test | B41: =IFERROR(CHOOSE(Inputs!$B$35,Inputs!$B$103*(1-Inputs!$F$55)/(Inputs!$B$101*((1-Inputs!$B$104-Inputs!$B$105-Inputs!$B$106)-Inputs!$F$55)),Inputs!$B$103/(Inputs!$B$101*((1-Inputs!$B$104-Inputs!$B$105-Inputs!$B$106)-Inputs!$B$36)),Inputs!$B$103/(Inputs!$B$101*(1-Inputs!$B$104-Inputs!$B$105-Inputs!$B$106))),"n/a") -> 0.475 | C41: =IFERROR(CHOOSE(Inputs!$B$35,Inputs!$C$103*(1-Inputs!$F$55)/(Inputs!$C$101*((1-Inputs!$C$104-Inputs!$C$105-Inputs!$C$106)-Inputs!$F$55)),Inputs!$C$103/(Inputs!$C$101*((1-Inputs!$C$104-Inputs!$C$105-Inputs!$C$106)-Inputs!$B$36)),Inputs!$C$103/(Inputs!$C$101*(1-Inputs!$C$104-Inputs!$C$105-Inputs!$C$106))),"n/a") -> 0.07125 | D41: =IFERROR(CHOOSE(Inputs!$B$35,Inputs!$D$103*(1-Inputs!$F$55)/(Inputs!$D$101*((1-Inputs!$D$104-Inputs!$D$105-Inputs!$D$106)-Inputs!$F$55)),Inputs!$D$103/(Inputs!$D$101*((1-Inputs!$D$104-Inputs!$D$105-Inputs!$D$106)-Inputs!$B$36)),Inputs!$D$103/(Inputs!$D$101*(1-Inputs!$D$104-Inputs!$D$105-Inputs!$D$106))),"n/a") -> 0.025537634
A42: Cut assumed | B42: =Inputs!$B$102 -> 0.1 | C42: =Inputs!$C$102 -> 0.15 | D42: =Inputs!$D$102 -> 0.2
A43: Test 2 assumes steady state, where depreciation equals capex, so the tax shield offsets tax on depreciation; the row below is the same test taken from the full 2030 build (includes growth timing and depreciation lags). Test 3 is the full model. All value-share inputs are hypothetical.
A44: 2b. Cash test from the full model: 2030 incremental economic cash flow per $1 moved | B44: =IFERROR((Bear!G132-Bear!G130-(Bear!G76-Bear!G74))/Bear!G25,"n/a") -> -0.28266682 | C44: =IFERROR((Base!G132-Base!G130-(Base!G76-Base!G74))/Base!G25,"n/a") -> 0.23100649 | D44: =IFERROR((Bull!G132-Bull!G130-(Bull!G76-Bull!G74))/Bull!G25,"n/a") -> 0.96375253
A45: Market check | B45: Reference | C45: Target
A46: Valuation ($B) | B46: =Inputs!$B$22/1000 -> 1500 | C46: =Inputs!$B$28/1000 -> 2000
A47: Implied price per share (economic shares, before Public Benefit steps) | B47: =IFERROR(B46*1000/Inputs!$B$18,0) -> 83.786431 | C47: =IFERROR(C46*1000/Inputs!$B$18,0) -> 111.71524
A48: Upside / (downside): weighted hybrid value | B48: =IFERROR($E$5/B47-1,"n/a") -> 0.5992197 | C48: =IFERROR($E$5/C47-1,"n/a") -> 0.19941478
A49: Upside / (downside): base hybrid value | B49: =IFERROR($C$5/B47-1,"n/a") -> 0.048314209 | C49: =IFERROR($C$5/C47-1,"n/a") -> -0.21376434
A50: Upside / (downside): base core-only value | B50: =IFERROR($C$6/B47-1,"n/a") -> -0.088299959 | C50: =IFERROR($C$6/C47-1,"n/a") -> -0.31622497
A52: Can the base case reach the target? | B52: Value
A53: Target valuation ($B) | B53: =C46 -> 2000
A54: Base hybrid equity value ($B) | B54: =C7 -> 1572.4713
A55: Gap to target ($B) | B55: =IFERROR(B53-B54,"n/a") -> 427.52869
A56: Value added by the value-share line, base case ($B) | B56: =IFERROR(C7-C8,"n/a") -> 204.92125
A57: Value-share adoption needed, as a multiple of base-case adoption | B57: =IF(NOT(ISNUMBER(B56)),"n/a",IF(B56<=0,"n/a",MAX(0,1+B55/B56))) -> 3.0863072
A58: Implied 2030 share of revenue base on value-share | B58: =IF(ISNUMBER(B57),Inputs!$C$100*B57,"n/a") -> 0.46294608
A59: Base-case 2030 share, for comparison | B59: =Inputs!$C$100 -> 0.15
A60: Solve is exact under current inputs? | B60: =IF(AND(Base!D67=0,Base!D123=0,Base!D62=0,Base!D118=0,Base!G90=0,Base!G146=0,Base!G109>0,Base!D53>0),"Yes","Approximate — verify") -> Yes
A61: Exact when tax losses are used up by end 2027 on both paths, no funding is needed and profits stay positive: value-share value then scales in proportion to adoption. Public Benefit steps affect per-share values only.
A63: Tax sensitivity: base case value per share | B63: Detailed (NOL + state) | C63: Flat 21% | D63: Flat 25% | E63: Flat 28%
A64: Hybrid | B64: =Base!G189 -> 87.834506 | C64: =T21!G189 -> 91.580799 | D64: =T25!G189 -> 87.082403 | E64: =T28!G189 -> 83.708605
A65: Core only | B65: =Base!F189 -> 76.388093 | C65: =T21!F189 -> 79.586102 | D65: =T25!F189 -> 75.730631 | E65: =T28!F189 -> 72.839027
A66: Flat rates ignore tax losses; they bracket the combined federal + state rate. The state allocation is an assumption, not company disclosure.
A68: Where the business is today (Q2 2026 actual) | B68: Value
A69: Quarterly revenue ($B) | B69: =Historicals!G5/1000 -> 11.555
A70: Operating margin | B70: =Historicals!G27 -> 0.084292514
A71: Operating margin before stock comp | B71: =Historicals!G28 -> 0.19342276
A72: Compute % of revenue | B72: =Historicals!G23 -> 0.48100389
A73: H1 2026 free cash flow margin (reported, before stock comp) | B73: =Historicals!F61 -> 0.21165418
A74: Revenue added in Q2 2026 vs Q1 ($B) | B74: =Historicals!G31/1000 -> 6.824
A75: Revenue added in Q3 2026 vs Q2 ($B, implied) | B75: =(Historicals!H5-Historicals!G5)/1000 -> 5.387

Sheet Change Log
A1: Change log: v1.2 to v1.3, plus the v1.3.1 patch
A2: v1.1 and v1.2 are preserved as separate files. Cell references point to the Base tab unless noted; the same rows exist on every case tab.
A4: v1.3.1 patch (narrow; no commercial assumptions changed) | B4: Where
A5: Start-of-year payments now discounted from the start of their year: removes a ~$21.4B overstatement of the $200B S7 prepayment's present value (once, in the shared cash flows) | B5: Base!F167:G167
A6: Funded-path interest now earned on the funded balance after start-of-year payments (S7 2027: zero, since the payment consumes opening cash plus proceeds); taxes reconciled | B6: Base!C154:G155
A7: Default shortfall threshold set to an assumed $5B operating cash buffer ($0 kept as a sensitivity row); the $5B covenant check stays separate | B7: Inputs!B29; Base!G147
A8: Summary title updated to v1.3.1 | B8: Summary!A1
A10: 1. Source corrections | B10: Where
A11: Q2 2026 stock comp: $1,261M from the non-GAAP reconciliation replaces the rounded $1.3B. Lowers the H2 2026 stock comp ratio and end-2026 cash by ~$0.1B | B11: Historicals!G19
A12: Broadcom equipment leases identified as finance leases (~$161.2B rent, 5 years, quarterly from ready-for-service); payment timing still incomplete | B12: Read Me method 4
A13: $5.0B minimum-liquidity covenant (A&R Credit Agreement, quarter-ends from Q4 2026) added as a separate check from the cash-shortfall threshold; definition not in the S-1 | B13: Inputs!B38; Base!C144:G144
A15: 2. Formula corrections | B15: Where
A16: Depreciation now by vintage: each year's capex is depreciated only within its useful life (fixes lives under 5 years) | B16: Base!C52:G52, C108:G108
A17: Funding need uses the lowest cash in each year, including start-of-year payments, not just year-end balances | B17: Base!C142:G146
... A30: No Bear, Base or Bull commercial assumption changed | B30: —
A32: Verification (LibreOffice recalculation) | B32: Expected | C32: Result | D32: Status
A33: S7 funded value per share, base discount (Ella: ~$83.97 at $0 buffer; ~$83.89 at the $5B buffer) | B33: ~$83.9 | C33: =S7!G185 -> 83.913807 | D33: =IF(AND(C33>83.5,C33<84.1),"Pass","Review") -> Pass
A34: S7 peak funding need with $5B buffer ($B) (Ella: ~$64.68B) | B34: ~64.68 | C34: =S7!G146/1000 -> 64.682089 | D34: =IF(ABS(C34-64.68)<0.05,"Pass","Review") -> Pass
A35: S7 peak need with $0 buffer ($B) (Ella: $59.68B) | B35: 59.68 | C35: =S7!G147/1000 -> 59.682089 | D35: =IF(ABS(C35-59.68)<0.05,"Pass","Review") -> Pass
A36: S7 2027 interest change on funded path ($B) | B36: 0 at $0 buffer | C36: =S7!D154/1000 -> 0.125 | D36: =IF(C36>=0,"Info","Review") -> Info
A37: Base hybrid value per share (v1.2: $87.84; change from Q2 stock comp only) | B37: ~$87.84 | C37: =Summary!C5 -> 87.834506 | D37: =IF(ABS(C37-87.84)<0.05,"Pass","Review") -> Pass
A38: Base core value per share (v1.2: $76.40) | B38: ~$76.40 | C38: =Summary!C6 -> 76.388093 | D38: =IF(ABS(C38-76.4)<0.05,"Pass","Review") -> Pass
A39: Weighted hybrid value per share (v1.2: $134.00) | B39: ~$134.00 | C39: =Summary!E5 -> 133.99291 | D39: =IF(ABS(C39-134)<0.1,"Pass","Review") -> Pass
A40: S2 hybrid value per share (Ella checkpoint $70.46) | B40: $70.46 | C40: =S2!G189 -> 70.455706 | D40: =IF(ABS(C40-70.46)<0.01,"Pass","Review") -> Pass
A41: S2 2030 compute vs Base | B41: +20.0% | C41: =S2!G10/Base!G10-1 -> 0.2 | D41: =IF(ABS(C41-0.2)<0.0001,"Pass","Review") -> Pass
A42: S2 2026 compute equals Base | B42: equal | C42: =S2!C10-Base!C10 -> 0 | D42: =IF(C42=0,"Pass","Review") -> Pass
A43: S7 peak need at start of 2027 = $200B less opening cash + $5B buffer ($B) | B43: ~64.7 | C43: =S7!G146/1000 -> 64.682089 | D43: =IF(ABS(C43-(205-S7!D136/1000))<0.01,"Pass","Review") -> Pass
A44: S7 funded path never below threshold | B44: Yes | C44: =COUNTIF(S7!C158:G158,"No") -> 0 | D44: =IF(C44=0,"Pass","Review") -> Pass
A45: S7 prepaid fully credited by 2030 (closing balance, $B) | B45: 0 | C45: =S7!G46/1000 -> 0 | D45: =IF(ABS(C45)<0.001,"Pass","Review") -> Pass
A46: S7 2028 credits capped at eligible compute ($B) | B46: equals 2028 compute | C46: =S7!E45/1000-S7!E44/1000 -> 0 | D46: =IF(ABS(C46)<0.001,"Pass","Review") -> Pass
A47: Zero value-share adoption: hybrid less core equity, Bear/Base/Bull ($B) | B47: 0 / 0 / 0 | C47: 0.0 / 0.0 / 0.0 | D47: Pass
A48: Vintage depreciation vs independent calculation, lives 1 / 2 / 3 / 5 (max difference) | B48: 0 | C48: 0e+00 / 0e+00 / 9e-13 / 1e-13 | D48: Pass
A49: Base hybrid per share at lives 1 / 2 / 3 / 5 | B49: — | C49: $85.9 / $86.34 / $86.78 / $87.83 | D49: Info
A50: Fractional depreciation life (2.5) | B50: warning | C50: CHECK INPUTS: results may be invalid | D50: Pass
A51: Negative cost ratio input | B51: warning; weighted blocked | C51: CHECK INPUTS: results may be invalid; check inputs | D51: Pass
A52: Stock comp above personnel | B52: warning | C52: CHECK INPUTS: results may be invalid | D52: Pass
A53: Legitimate loss scenario (2027 growth -30%) | B53: no warning; 'Not meaningful' | C53: All input checks passed; Not meaningful: 2030 earnings or cash flow negative | D53: Pass
A54: S7 funded value per share at 0% / 15% / 30% discount | B54: decreasing | C54: $84.54 / $83.91 / $83.04 | D54: Pass
A56: Static rows were measured by recalculating copies of v1.3 with the stated inputs; live rows recalculate with the workbook.
A57: S7 note: the raise is sized to the assumed $5B operating cash buffer, so the funded start-of-year low is $5B. The $5B covenant check remains separate because its liquidity definition may differ from cash.
A58: Outputs that changed: Base, Bear and Bull move by under $0.01 per share (Q2 stock comp correction only); S2 falls from $76.29 to $70.46 and S6 stays unresolved (true +20% compute); S7 need rises from $33.0B to $59.7B (start-of-year timing), with value $85.16 vs $85.47.

Sheet Historicals
A1: Historical financials from the S-1 ($ millions)
A2: Source: Anthropic, PBC Form S-1, filed Oct 26, 2026 (SEC EDGAR CIK 2130357). Blue = reported figure. Black = formula.
A4: Quarterly income statement | B4: Q1 2025 | C4: Q2 2025 | D4: Q3 2025 | E4: Q4 2025 | F4: Q1 2026 | G4: Q2 2026 | H4: Q3 2026 (implied)
A5: Revenue | B5: 376 | C5: 787 | D5: 1382 | E5: 2040 | F5: 4731 | G5: 11555 | H5: =B66*B67 -> 16942
A6: Compute and infrastructure | B6: 944 | C6: 1390 | D6: 2047 | E6: 2945 | F6: 3387 | G6: 5558
A7: Personnel (incl. stock comp) | B7: 218 | C7: 320 | D7: 489 | E7: 812 | F7: 1295 | G7: 1857
A8: Bartz settlement (one-time) | B8: 0 | C8: 0 | D8: 1500 | E8: 0 | F8: 0 | G8: 0
A9: Sales, marketing, and partnerships | B9: 24 | C9: 96 | D9: 202 | E9: 246 | F9: 1033 | G9: 2135
A10: Other operating and administrative | B10: 125 | C10: 181 | D10: 233 | E10: 873 | F10: 683 | G10: 1031
A11: Total operating expenses | B11: =SUM(B6:B10) -> 1311 | C11: =SUM(C6:C10) -> 1987 | D11: =SUM(D6:D10) -> 4471 | E11: =SUM(E6:E10) -> 4876 | F11: =SUM(F6:F10) -> 6398 | G11: =SUM(G6:G10) -> 10581
A12: Operating income (loss) | B12: =B5-B11 -> -935 | C12: =C5-C11 -> -1200 | D12: =D5-D11 -> -3089 | E12: =E5-E11 -> -2836 | F12: =F5-F11 -> -1667 | G12: =G5-G11 -> 974
A13: Interest income | B13: 51 | C13: 64 | D13: 124 | E13: 192 | F13: 349 | G13: 762
A14: Change in fair value of convertible notes etc. (non-cash) | B14: -5701 | C14: -5241 | D14: -9165 | E14: -14201 | F14: -12791 | G14: -59597
A15: Other income (expense), net | B15: 0 | C15: 0 | D15: -3 | E15: -5 | F15: -309 | G15: -8448
A16: Loss before income taxes | B16: =B12+B13+B14+B15 -> -6585 | C16: =C12+C13+C14+C15 -> -6377 | D16: =D12+D13+D14+D15 -> -12133 | E16: =E12+E13+E14+E15 -> -16850 | F16: =F12+F13+F14+F15 -> -14418 | G16: =G12+G13+G14+G15 -> -66309
A17: Provision for income taxes | B17: 7 | C17: 0 | D17: 5 | E17: 8 | F17: 21 | G17: 0
A18: Net income (loss) | B18: =B16-B17 -> -6592 | C18: =C16-C17 -> -6377 | D18: =D16-D17 -> -12138 | E18: =E16-E17 -> -16858 | F18: =F16-F17 -> -14439 | G18: =G16-G17 -> -66309
A19: Stock-based compensation (non-GAAP reconciliation) | B19: 105 | C19: 181 | D19: 305 | E19: 574 | F19: 924 | G19: 1261
A20: Operating income before stock comp | B20: =B12+B19 -> -830 | C20: =C12+C19 -> -1019 | D20: =D12+D19 -> -2784 | E20: =E12+E19 -> -2262 | F20: =F12+F19 -> -743 | G20: =G12+G19 -> 2235
A22: Quarterly ratios
A23: Compute % of revenue | B23: =IFERROR(B6/B5,0) -> 2.5106383 | C23: =IFERROR(C6/C5,0) -> 1.7662008 | D23: =IFERROR(D6/D5,0) -> 1.4811867 | E23: =IFERROR(E6/E5,0) -> 1.4436275 | F23: =IFERROR(F6/F5,0) -> 0.7159163 | G23: =IFERROR(G6/G5,0) -> 0.48100389
A24: Personnel % of revenue | B24: =IFERROR(B7/B5,0) -> 0.57978723 | C24: =IFERROR(C7/C5,0) -> 0.40660737 | D24: =IFERROR(D7/D5,0) -> 0.35383502 | E24: =IFERROR(E7/E5,0) -> 0.39803922 | F24: =IFERROR(F7/F5,0) -> 0.27372648 | G24: =IFERROR(G7/G5,0) -> 0.16070965
A25: Sales, marketing & partnerships % of revenue | B25: =IFERROR(B9/B5,0) -> 0.063829787 | C25: =IFERROR(C9/C5,0) -> 0.12198221 | D25: =IFERROR(D9/D5,0) -> 0.14616498 | E25: =IFERROR(E9/E5,0) -> 0.12058824 | F25: =IFERROR(F9/F5,0) -> 0.21834707 | G25: =IFERROR(G9/G5,0) -> 0.1847685
A26: Other opex % of revenue | B26: =IFERROR(B10/B5,0) -> 0.33244681 | C26: =IFERROR(C10/C5,0) -> 0.22998729 | D26: =IFERROR(D10/D5,0) -> 0.16859624 | E26: =IFERROR(E10/E5,0) -> 0.42794118 | F26: =IFERROR(F10/F5,0) -> 0.14436694 | G26: =IFERROR(G10/G5,0) -> 0.089225444
A27: Operating margin | B27: =IFERROR(B12/B5,0) -> -2.4867021 | C27: =IFERROR(C12/C5,0) -> -1.5247776 | D27: =IFERROR(D12/D5,0) -> -2.2351664 | E27: =IFERROR(E12/E5,0) -> -1.3901961 | F27: =IFERROR(F12/F5,0) -> -0.3523568 | G27: =IFERROR(G12/G5,0) -> 0.084292514
A28: Operating margin before stock comp | B28: =IFERROR(B20/B5,0) -> -2.2074468 | C28: =IFERROR(C20/C5,0) -> -1.2947903 | D28: =IFERROR(D20/D5,0) -> -2.0144718 | E28: =IFERROR(E20/E5,0) -> -1.1088235 | F28: =IFERROR(F20/F5,0) -> -0.15704925 | G28: =IFERROR(G20/G5,0) -> 0.19342276
A29: Stock comp % of revenue | B29: =IFERROR(B19/B5,0) -> 0.27925532 | C29: =IFERROR(C19/C5,0) -> 0.22998729 | D29: =IFERROR(D19/D5,0) -> 0.22069465 | E29: =IFERROR(E19/E5,0) -> 0.28137255 | F29: =IFERROR(F19/F5,0) -> 0.19530755 | G29: =IFERROR(G19/G5,0) -> 0.10913025
A30: Revenue growth vs prior quarter | C30: =IFERROR(C5/B5-1,0) -> 1.0930851 | D30: =IFERROR(D5/C5-1,0) -> 0.75603558 | E30: =IFERROR(E5/D5-1,0) -> 0.47612156 | F30: =IFERROR(F5/E5-1,0) -> 1.3191176 | G30: =IFERROR(G5/F5-1,0) -> 1.4424012 | H30: =IFERROR(H5/G5-1,0) -> 0.46620511
A31: Revenue added vs prior quarter ($mm) | C31: =C5-B5 -> 411 | D31: =D5-C5 -> 595 | E31: =E5-D5 -> 658 | F31: =F5-E5 -> 2691 | G31: =G5-F5 -> 6824 | H31: =H5-G5 -> 5387
A32: Check: Q1+Q2 2026 revenue less H1 2026 (should be 0) | G32: =F5+G5-F35 -> 0
A33: Check: 2025 quarters less 2025 revenue (should be 0) | G33: =B5+C5+D5+E5-D35 -> 0
A34: Annual & half-year income statement | B34: 2023 | C34: 2024 | D34: 2025 | E34: H1 2025 | F34: H1 2026
A35: Revenue | B35: 41 | C35: 386 | D35: 4585 | E35: 1163 | F35: 16286
A36: Compute and infrastructure | B36: 433 | C36: 2522 | D36: 7326 | E36: 2334 | F36: 8945
A37: Personnel (incl. stock comp) | B37: 95 | C37: 454 | D37: 1839 | E37: 538 | F37: 3152
A38: Bartz settlement (one-time) | B38: 0 | C38: 0 | D38: 1500 | E38: 0 | F38: 0
A39: Sales, marketing, and partnerships | B39: 2 | C39: 43 | D39: 568 | E39: 120 | F39: 3168
A40: Other operating and administrative | B40: 62 | C40: 347 | D40: 1412 | E40: 306 | F40: 1714
A41: Total operating expenses | B41: =SUM(B36:B40) -> 592 | C41: =SUM(C36:C40) -> 3366 | D41: =SUM(D36:D40) -> 12645 | E41: =SUM(E36:E40) -> 3298 | F41: =SUM(F36:F40) -> 16979
A42: Operating income (loss) | B42: =B35-B41 -> -551 | C42: =C35-C41 -> -2980 | D42: =D35-D41 -> -8060 | E42: =E35-E41 -> -2135 | F42: =F35-F41 -> -693
A43: Interest income | B43: 69 | C43: 106 | D43: 431 | E43: 115 | F43: 1111
A44: Change in fair value of convertible notes etc. (non-cash) | B44: -1045 | C44: -5434 | D44: -34308 | E44: -10942 | F44: -72388
A45: Other income (expense), net | B45: -2 | C45: 0 | D45: -8 | E45: 0 | F45: -8757
A46: Loss before income taxes | B46: =B42+B43+B44+B45 -> -1529 | C46: =C42+C43+C44+C45 -> -8308 | D46: =D42+D43+D44+D45 -> -41945 | E46: =E42+E43+E44+E45 -> -12962 | F46: =F42+F43+F44+F45 -> -80727
A47: Provision for income taxes | B47: 2 | C47: 1 | D47: 20 | E47: 7 | F47: 21
A48: Net income (loss) | B48: =B46-B47 -> -1531 | C48: =C46-C47 -> -8309 | D48: =D46-D47 -> -41965 | E48: =E46-E47 -> -12969 | F48: =F46-F47 -> -80748
A49: Stock-based compensation (cash flow statement) | B49: 29 | C49: 192 | D49: 1158 | E49: 279 | F49: 2185 | G49: Quarterly stock comp (row 19) is from the non-GAAP reconciliation; this row is from the cash flow statement. They differ slightly.
A50: Consumption-based revenue | B50: 39 | C50: 288 | D50: 3796 | E50: 983 | F50: 13064
A51: Subscription-based revenue | B51: 2 | C51: 98 | D51: 789 | E51: 180 | F51: 3222
A52: Check: revenue split ties (should be 0) | B52: =B50+B51-B35 -> 0 | C52: =C50+C51-C35 -> 0 | D52: =D50+D51-D35 -> 0 | E52: =E50+E51-E35 -> 0 | F52: =F50+F51-F35 -> 0
A53: United States revenue | B53: 34 | C53: 263 | D53: 3362 | E53: 820 | F53: 11763
A54: International revenue | B54: 7 | C54: 123 | D54: 1223 | E54: 343 | F54: 4523
A55: Cloud marketplace share of revenue | C55: 0.32 | D55: 0.47 | F55: 0.48
A57: Cash flow | B57: 2023 | C57: 2024 | D57: 2025 | E57: H1 2025 | F57: H1 2026
A58: Net cash from operating activities | B58: -1627 | C58: -5692 | D58: -2637 | E58: -1513 | F58: 3929
A59: Purchases of property & equipment | B59: -2 | C59: -15 | D59: -131 | E59: -18 | F59: -482
A60: Free cash flow (reported basis) | B60: =B58+B59 -> -1629 | C60: =C58+C59 -> -5707 | D60: =D58+D59 -> -2768 | E60: =E58+E59 -> -1531 | F60: =F58+F59 -> 3447
A61: Free cash flow margin (before stock comp) | B61: =IFERROR(B60/B35,0) -> -39.731707 | C61: =IFERROR(C60/C35,0) -> -14.784974 | D61: =IFERROR(D60/D35,0) -> -0.60370774 | E61: =IFERROR(E60/E35,0) -> -1.316423 | F61: =IFERROR(F60/F35,0) -> 0.21165418
A62: Free cash flow less stock comp | B62: =B60-B49 -> -1658 | C62: =C60-C49 -> -5899 | D62: =D60-D49 -> -3926 | E62: =E60-E49 -> -1810 | F62: =F60-F49 -> 1262
A64: Q3 2026 derivation
A66: Q4 2024 revenue ($mm) | B66: 197
A67: Q3 2026 revenue as multiple of Q4 2024 | B67: 86
A69: Cash, equivalents & short-term investments, Jun 30, 2026 | B69: 131651
A71: H1 2026 cash flow bridge ($mm) | B71: H1 2026 | C71: Source / note
A72: Operating income (loss) | B72: =F42 -> -693 | C72: Income statement
A73: + Interest income | B73: =F43 -> 1111 | C73: Income statement
A74: - Income taxes | B74: =-F47 -> -21 | C74: Income statement
A75: - Capital spending | B75: =F59 -> -482 | C75: Cash flow statement
A76: Subtotal: model comparator: earnings minus capex (after stock comp) | B76: =SUM(B72:B75) -> -85 | C76: Basis v1.1 used for the H2 2026 cash build
A77: + Stock-based compensation (non-cash) | B77: =F49 -> 2185 | C77: Cash flow statement
A78: + Donation-matching charge (non-cash, share-settled) | B78: 126 | C78: Cash flow statement: donation matching program liability
A79: Subtotal: model liquidity basis (no D&A, no working capital) | B79: =B76+B77+B78 -> 2226 | C79: Basis used for the H2 2026 cash roll-forward in v1.2
A80: + Depreciation & amortization | B80: 97 | C80: Cash flow statement
A81: + Other financial items, net of non-cash portion | B81: =F45+8720 -> -37 | C81: Other expense of $(8,757)M less $8,720M non-cash recognition of other financial instruments
A82: + Other operating adjustments | B82: -7 | C82: Cash flow statement
A83: + Working capital changes | B83: =-4982+2094+2679-3+1380 -> 1168 | C83: Receivables, prepaids, payables, leases, deferred revenue
A84: Total: free cash flow (reported basis) | B84: =SUM(B79:B83) -> 3447 | C84: Should equal Free cash flow above
A85: Check: bridge vs reported (should be 0) | B85: =B84-F60 -> 0
A86: Memo: free cash flow less stock comp | B86: =B84-B77 -> 1262 | C86: Reported free cash flow less stock comp; differs from row 76 by donation, D&A, other items and working capital

Sheet Inputs
A1: Assumptions
A2: Blue = input. Yellow = key assumption you can change. Green = link to another tab. Black = formula. Input checks are at the bottom of this tab.
A4: Shared settings | B4: Value | C4: Note
A5: Q3 2026 revenue (implied, $mm) | B5: =Historicals!H5 -> 16942 | C5: S-1: Q3 2026 revenue was 86x Q4 2024 ($197M). Company separately told investors $16.8B
A6: Cash, equivalents & short-term investments, Jun 30, 2026 ($mm) | B6: =Historicals!B69 -> 131651 | C6: S-1 balance sheet
A7: Initial Public Benefit Fund issuance (shares) | B7: 846840960 | C7: S-1: 846,840,960 Class N shares contributed to the Anthropic Public Benefit Fund (Oct 2026)
A8: Issuance as % of June 30 fully diluted shares | B8: 0.05 | C8: S-1: 5% of fully diluted shares as of June 30, 2026, assuming full conversion of the Amazon notes
A9: June 30, 2026 fully diluted shares (mm) | B9: =B7/B8/1000000 -> 16936.819 | C9: Derived. Assumes this count includes options and RSUs outstanding at June 30 (definition not stated in the S-1). Excludes the Fund issuance
A10: Count the Fund issuance in economic shares? (1 = yes) | B10: 1 | C10: Held by a wholly owned subsidiary, so not outstanding for accounting; may be donated or sold, so counted as economic dilution
A11: RSUs granted after June 30, 2026 (mm) | B11: 91 | C11: S-1 Note 17: ~91M RSUs, grant-date fair value $5.8B, vest over 4 years; performance condition met at IPO
A12: Count post-June RSUs in economic shares? (1 = yes) | B12: 1 | C12: Counted as granted awards. Partial overlap: their future expense is also inside forecast stock comp
A13: October 2026 donation-matching shares (mm) | B13: 28 | C13: S-1 Note 17: ~28.0M Class N shares issued to settle the Q3 2026 donation-matching obligation
A14: RSU shares withheld for taxes at IPO (mm) | B14: 0 | C14: Blank in S-1. Net settlement reduces shares but costs cash (see next rows)
A15: Primary IPO proceeds to company ($mm) | B15: 0 | C15: Blank in S-1. Update from price-range amendment
A16: New shares issued in IPO (mm) | B16: 0 | C16: Blank in S-1. Update from price-range amendment
A17: Cash paid for RSU tax withholding at IPO ($mm) | B17: 0 | C17: Blank in S-1. Paid from IPO proceeds per S-1 use of proceeds; separate from the tax deduction
A18: Economic shares at valuation date (mm) | B18: =B9+B10*B7/1000000+B12*B11+B13-B14+B16 -> 17902.66 | C18: June fully diluted + Fund issuance + post-June RSUs + donation shares - shares withheld + IPO shares
A19: Discount rate | B19: 0.12 | C19: Annual return required on the equity
A20: Interest yield on cash | B20: 0.025 | C20: Q2 2026 actual ~2.3% a year. Applied to opening cash each year; no interest on a negative balance
A21: Weight on P/E method (rest on cash flow method) | B21: 0.5 | C21: Both methods use the same forecasts, so the blend is not independent confirmation
A22: Reference IPO valuation ($mm) | B22: 1500000 | C22: Low end of reported $1.5T-$2T range; sets the Public Benefit step starting price
A23: Reference IPO price per share | B23: =B22/B18 -> 83.786431 | C23: Derived on economic shares
A24: Board issues maximum Public Benefit shares? (1 = yes) | B24: 1 | C24: S-1: discretionary. Model assumes maximum issuance (conservative)
A25: Public Benefit issuance per step (% of shares) | B25: 0.02 | C25: S-1: up to an additional 2% each time the price rises 50% above the prior step
A26: Share price rise per step | B26: 0.5 | C26: S-1: a step requires a close above the threshold on 90 of 120 trading days and a 10-day average above it
A27: Global knowledge-work value pool ($mm) | B27: 40000000 | C27: S-1: knowledge work was more than $40 trillion of economic value in 2025. Sanity check only
A28: Target valuation for the $2T test ($mm) | B28: 2000000 | C28: Used on Summary
A29: Operating cash buffer (shortfall threshold, $mm) | B29: 5000 | C29: Assumed buffer; cash below it is a shortfall. Separate from the $5B liquidity covenant, whose definition may differ from cash. $0 shown as a sensitivity
A30: Equity issuance discount if funding is needed | B30: 0.15 | C30: Illustrative modeling assumption, not observed terms. 0% and 30% shown alongside
A31: Equity issuance fees | B31: 0.03 | C31: Illustrative
A32: Depreciation life of owned capacity (years) | B32: 5 | C32: Straight-line depreciation on capital spending from 2027
A33: Working capital change, % of revenue increase | B33: 0 | C33: H1 2026 working capital was a $1.17B inflow; default 0
A34: Value-share days to collect | B34: 0 | C34: Default 0 reproduces v1.1. Raising it delays value-share cash
A35: Value-share capex basis (1, 2 or 3) | B35: 1 | C35: 1 = company capex rate x net new revenue (v1.1 method); 2 = % of gross value-share revenue; 3 = none (capacity bought via extra-compute charge)
... A40: Years over which prepaid credits are scheduled (from 2028) | B40: 3 | C40: Scheduled credits accumulate; actual credits are capped by eligible charges and the remaining balance
A42: Taxes | B42: Value | C42: Note
A43: Federal tax rate | B43: 0.21 | C43: US federal statutory rate
A44: Federal NOL carryforward at Dec 31, 2025 ($mm) | B44: 8200 | C44: S-1 income tax note: $8.2B, does not expire
A45: Federal NOL usage limit (% of taxable income) | B45: 0.8 | C45: Post-2017 federal NOLs offset up to 80% of taxable income
A46: Share of taxable income subject to state tax | B46: 0.72 | C46: Assumption. Proxy: US share of H1 2026 revenue (72%). Not company disclosure
A47: Blended state tax rate on that income | B47: 0.06 | C47: Assumption, not company disclosure. California's 8.84% is not applied to all income
A48: State NOL carryforwards at Dec 31, 2025 ($mm) | B48: 4200 | C48: S-1 income tax note: $4.2B, begin to expire in 2033
A49: State NOLs suspended in 2026? (1 = yes) | B49: 1 | C49: California suspended NOL deductions for 2024-2026 above $1M income; applied to all state NOLs for simplicity
A50: IPO-related RSU tax deduction ($mm) | B50: 0 | C50: Likely large but not quantified in the S-1. Default 0
A51: Year of RSU deduction | B51: 2026 | C51: Applies to federal and state taxable income in that year
A53: Year-based settings | B53: 2026 | C53: 2027 | D53: 2028 | E53: 2029 | F53: 2030
A54: Legacy v1.1 tax rate ramp (tax method 0 only) | B54: 0 | C54: 0.1 | D54: 0.15 | E54: 0.21 | F54: 0.21
A55: Capital spending % of core revenue | B55: 0.03 | C55: 0.04 | D55: 0.05 | E55: 0.05 | F55: 0.05
A56: Other taxable income adjustments ($mm) | B56: 0 | C56: 0 | D56: 0 | E56: 0 | F56: 0
A57: Capex: H1 2026 was 3% of revenue; the S-1 says Anthropic plans its own data centers. Taxable income here is a proxy (operating income + interest + adjustments - RSU deduction), not a tax return.
A59: Scenario levers | B59: Bear | C59: Base | D59: Bull | E59: Why | G59: S1 Flat revenue | H59: S2 Compute +20% | I59: S3 Half growth | J59: S4 Lower multiples | K59: S5 Discount +2pts | L59: S6 Combined | M59: T21 Tax 21% | N59: T25 Tax 25% | O59: T28 Tax 28% | P59: S7 Funding test
A60: Q4 2026 revenue ($mm) | B60: 18500 | C60: 21000 | D60: 24000 | E60: Q3 implied ~$16.9B. Bear +9%, base +24%, bull +42% vs Q3 | G60: =$C60 -> 21000 | H60: =$C60 -> 21000 | I60: =$C60 -> 21000 | J60: =$C60 -> 21000 | K60: =$C60 -> 21000 | L60: =$C60 -> 21000 | M60: =$C60 -> 21000 | N60: =$C60 -> 21000 | ... P60: =$C60 -> 21000
A61: Subscription share of revenue (2027-2030) | B61: 0.22 | C61: 0.2 | D61: 0.18 | E61: H1 2026 actual: 19.8% | G61: =$C61 -> 0.2 | H61: =$C61 -> 0.2 | I61: =$C61 -> 0.2 | J61: =$C61 -> 0.2 | K61: =$C61 -> 0.2 | L61: =$C61 -> 0.2 | M61: =$C61 -> 0.2 | N61: =$C61 -> 0.2 | ... P61: =$C61 -> 0.2
A62: Revenue growth 2027 | B62: 0.6 | C62: 1 | D62: 1.5 | E62: Full-year growth | G62: =0 -> 0 | H62: =$C62 -> 1 | I62: =$C62*0.5 -> 0.5 | J62: =$C62 -> 1 | K62: =$C62 -> 1 | L62: =$C62*0.5 -> 0.5 | M62: =$C62 -> 1 | N62: =$C62 -> 1 | O62: =$C62 -> 1 | P62: =$C62 -> 1
A63: Revenue growth 2028 | B63: 0.3 | C63: 0.55 | D63: 0.8 | G63: =0 -> 0 | H63: =$C63 -> 0.55 | I63: =$C63*0.5 -> 0.275 | J63: =$C63 -> 0.55 | K63: =$C63 -> 0.55 | L63: =$C63*0.5 -> 0.275 | M63: =$C63 -> 0.55 | N63: =$C63 -> 0.55 | O63: =$C63 -> 0.55 | P63: =$C63 -> 0.55
A64: Revenue growth 2029 | B64: 0.2 | C64: 0.35 | D64: 0.5 | G64: =0 -> 0 | H64: =$C64 -> 0.35 | I64: =$C64*0.5 -> 0.175 | J64: =$C64 -> 0.35 | K64: =$C64 -> 0.35 | L64: =$C64*0.5 -> 0.175 | M64: =$C64 -> 0.35 | N64: =$C64 -> 0.35 | O64: =$C64 -> 0.35 | P64: =$C64 -> 0.35
A65: Revenue growth 2030 | B65: 0.15 | C65: 0.25 | D65: 0.35 | G65: =0 -> 0 | H65: =$C65 -> 0.25 | I65: =$C65*0.5 -> 0.125 | J65: =$C65 -> 0.25 | K65: =$C65 -> 0.25 | L65: =$C65*0.5 -> 0.125 | M65: =$C65 -> 0.25 | N65: =$C65 -> 0.25 | O65: =$C65 -> 0.25 | P65: =$C65 -> 0.25
A66: Compute % of revenue, H2 2026 | B66: 0.5 | C66: 0.45 | D66: 0.42 | E66: Q2 2026 actual: 48%. Sets the 2026 compute base that later growth compounds on | G66: =$C66 -> 0.45 | H66: =$C66 -> 0.45 | I66: =$C66 -> 0.45 | J66: =$C66 -> 0.45 | K66: =$C66 -> 0.45 | L66: =$C66 -> 0.45 | M66: =$C66 -> 0.45 | N66: =$C66 -> 0.45 | ... P66: =$C66 -> 0.45
A67: Compute spend growth 2027 | B67: 0.6 | C67: 0.7 | D67: 0.9 | E67: Compute is bought 12-18 months ahead and largely fixed; it grows on its own schedule. Note: Bear grows compute at the same rate as revenue | G67: =$C67 -> 0.7 | H67: =(1+$C67)*1.2-1 -> 1.04 | I67: =$C67 -> 0.7 | J67: =$C67 -> 0.7 | K67: =$C67 -> 0.7 | L67: =(1+$C67)*1.2-1 -> 1.04 | M67: =$C67 -> 0.7 | N67: =$C67 -> 0.7 | O67: =$C67 -> 0.7 | P67: =$C67 -> 0.7
A68: Compute spend growth 2028 | B68: 0.3 | C68: 0.45 | D68: 0.6 | G68: =$C68 -> 0.45 | H68: =$C68 -> 0.45 | I68: =$C68 -> 0.45 | J68: =$C68 -> 0.45 | K68: =$C68 -> 0.45 | L68: =$C68 -> 0.45 | M68: =$C68 -> 0.45 | N68: =$C68 -> 0.45 | ... P68: =$C68 -> 0.45
A69: Compute spend growth 2029 | B69: 0.2 | C69: 0.3 | D69: 0.45 | G69: =$C69 -> 0.3 | H69: =$C69 -> 0.3 | I69: =$C69 -> 0.3 | J69: =$C69 -> 0.3 | K69: =$C69 -> 0.3 | L69: =$C69 -> 0.3 | M69: =$C69 -> 0.3 | N69: =$C69 -> 0.3 | ... P69: =$C69 -> 0.3
A70: Compute spend growth 2030 | B70: 0.15 | C70: 0.2 | D70: 0.3 | G70: =$C70 -> 0.2 | H70: =$C70 -> 0.2 | I70: =$C70 -> 0.2 | J70: =$C70 -> 0.2 | K70: =$C70 -> 0.2 | L70: =$C70 -> 0.2 | M70: =$C70 -> 0.2 | N70: =$C70 -> 0.2 | ... P70: =$C70 -> 0.2
A71: Personnel % of revenue 2027 | B71: 0.16 | C71: 0.14 | D71: 0.13 | E71: Q2 2026 actual: 16% | G71: =$C71 -> 0.14 | H71: =$C71 -> 0.14 | I71: =$C71 -> 0.14 | J71: =$C71 -> 0.14 | K71: =$C71 -> 0.14 | L71: =$C71 -> 0.14 | M71: =$C71 -> 0.14 | N71: =$C71 -> 0.14 | ... P71: =$C71 -> 0.14
A72: Personnel % of revenue 2028 | B72: 0.15 | C72: 0.13 | D72: 0.12 | G72: =$C72 -> 0.13 | H72: =$C72 -> 0.13 | I72: =$C72 -> 0.13 | J72: =$C72 -> 0.13 | K72: =$C72 -> 0.13 | L72: =$C72 -> 0.13 | M72: =$C72 -> 0.13 | N72: =$C72 -> 0.13 | ... P72: =$C72 -> 0.13
A73: Personnel % of revenue 2029 | B73: 0.14 | C73: 0.12 | D73: 0.11 | G73: =$C73 -> 0.12 | H73: =$C73 -> 0.12 | I73: =$C73 -> 0.12 | J73: =$C73 -> 0.12 | K73: =$C73 -> 0.12 | L73: =$C73 -> 0.12 | M73: =$C73 -> 0.12 | N73: =$C73 -> 0.12 | ... P73: =$C73 -> 0.12
A74: Personnel % of revenue 2030 | B74: 0.13 | C74: 0.11 | D74: 0.1 | G74: =$C74 -> 0.11 | H74: =$C74 -> 0.11 | I74: =$C74 -> 0.11 | J74: =$C74 -> 0.11 | K74: =$C74 -> 0.11 | L74: =$C74 -> 0.11 | M74: =$C74 -> 0.11 | N74: =$C74 -> 0.11 | ... P74: =$C74 -> 0.11
A75: Stock comp % of revenue (inside personnel) 2027 | B75: 0.1 | C75: 0.09 | D75: 0.08 | E75: Q2 2026 actual: 11% | G75: =$C75 -> 0.09 | H75: =$C75 -> 0.09 | I75: =$C75 -> 0.09 | J75: =$C75 -> 0.09 | K75: =$C75 -> 0.09 | L75: =$C75 -> 0.09 | M75: =$C75 -> 0.09 | N75: =$C75 -> 0.09 | ... P75: =$C75 -> 0.09
A76: Stock comp % of revenue (inside personnel) 2028 | B76: 0.09 | C76: 0.08 | D76: 0.07 | G76: =$C76 -> 0.08 | H76: =$C76 -> 0.08 | I76: =$C76 -> 0.08 | J76: =$C76 -> 0.08 | K76: =$C76 -> 0.08 | L76: =$C76 -> 0.08 | M76: =$C76 -> 0.08 | N76: =$C76 -> 0.08 | ... P76: =$C76 -> 0.08
A77: Stock comp % of revenue (inside personnel) 2029 | B77: 0.08 | C77: 0.07 | D77: 0.06 | G77: =$C77 -> 0.07 | H77: =$C77 -> 0.07 | I77: =$C77 -> 0.07 | J77: =$C77 -> 0.07 | K77: =$C77 -> 0.07 | L77: =$C77 -> 0.07 | M77: =$C77 -> 0.07 | N77: =$C77 -> 0.07 | ... P77: =$C77 -> 0.07
A78: Stock comp % of revenue (inside personnel) 2030 | B78: 0.07 | C78: 0.06 | D78: 0.05 | G78: =$C78 -> 0.06 | H78: =$C78 -> 0.06 | I78: =$C78 -> 0.06 | J78: =$C78 -> 0.06 | K78: =$C78 -> 0.06 | L78: =$C78 -> 0.06 | M78: =$C78 -> 0.06 | N78: =$C78 -> 0.06 | ... P78: =$C78 -> 0.06
A79: Sales, marketing & partner fees % of revenue 2027 | B79: 0.18 | C79: 0.17 | D79: 0.16 | E79: Q2 2026 actual: 18% | G79: =$C79 -> 0.17 | H79: =$C79 -> 0.17 | I79: =$C79 -> 0.17 | J79: =$C79 -> 0.17 | K79: =$C79 -> 0.17 | L79: =$C79 -> 0.17 | M79: =$C79 -> 0.17 | N79: =$C79 -> 0.17 | ... P79: =$C79 -> 0.17
A80: Sales, marketing & partner fees % of revenue 2028 | B80: 0.17 | C80: 0.16 | D80: 0.15 | G80: =$C80 -> 0.16 | H80: =$C80 -> 0.16 | I80: =$C80 -> 0.16 | J80: =$C80 -> 0.16 | K80: =$C80 -> 0.16 | L80: =$C80 -> 0.16 | M80: =$C80 -> 0.16 | N80: =$C80 -> 0.16 | ... P80: =$C80 -> 0.16
A81: Sales, marketing & partner fees % of revenue 2029 | B81: 0.16 | C81: 0.15 | D81: 0.14 | G81: =$C81 -> 0.15 | H81: =$C81 -> 0.15 | I81: =$C81 -> 0.15 | J81: =$C81 -> 0.15 | K81: =$C81 -> 0.15 | L81: =$C81 -> 0.15 | M81: =$C81 -> 0.15 | N81: =$C81 -> 0.15 | ... P81: =$C81 -> 0.15
A82: Sales, marketing & partner fees % of revenue 2030 | B82: 0.16 | C82: 0.15 | D82: 0.13 | G82: =$C82 -> 0.15 | H82: =$C82 -> 0.15 | I82: =$C82 -> 0.15 | J82: =$C82 -> 0.15 | K82: =$C82 -> 0.15 | L82: =$C82 -> 0.15 | M82: =$C82 -> 0.15 | N82: =$C82 -> 0.15 | ... P82: =$C82 -> 0.15
A83: Other opex % of revenue 2027 | B83: 0.09 | C83: 0.08 | D83: 0.07 | E83: Q2 2026 actual: 9% | G83: =$C83 -> 0.08 | H83: =$C83 -> 0.08 | I83: =$C83 -> 0.08 | J83: =$C83 -> 0.08 | K83: =$C83 -> 0.08 | L83: =$C83 -> 0.08 | M83: =$C83 -> 0.08 | N83: =$C83 -> 0.08 | ... P83: =$C83 -> 0.08
A84: Other opex % of revenue 2028 | B84: 0.08 | C84: 0.07 | D84: 0.06 | G84: =$C84 -> 0.07 | H84: =$C84 -> 0.07 | I84: =$C84 -> 0.07 | J84: =$C84 -> 0.07 | K84: =$C84 -> 0.07 | L84: =$C84 -> 0.07 | M84: =$C84 -> 0.07 | N84: =$C84 -> 0.07 | ... P84: =$C84 -> 0.07
A85: Other opex % of revenue 2029 | B85: 0.07 | C85: 0.06 | D85: 0.05 | G85: =$C85 -> 0.06 | H85: =$C85 -> 0.06 | I85: =$C85 -> 0.06 | J85: =$C85 -> 0.06 | K85: =$C85 -> 0.06 | L85: =$C85 -> 0.06 | M85: =$C85 -> 0.06 | N85: =$C85 -> 0.06 | ... P85: =$C85 -> 0.06
A86: Other opex % of revenue 2030 | B86: 0.07 | C86: 0.06 | D86: 0.05 | G86: =$C86 -> 0.06 | H86: =$C86 -> 0.06 | I86: =$C86 -> 0.06 | J86: =$C86 -> 0.06 | K86: =$C86 -> 0.06 | L86: =$C86 -> 0.06 | M86: =$C86 -> 0.06 | N86: =$C86 -> 0.06 | ... P86: =$C86 -> 0.06
A87: Exit P/E on 2030 after-tax operating earnings | B87: 20 | C87: 30 | D87: 35 | E87: Earnings after stock comp, depreciation and tax | G87: =$C87 -> 30 | H87: =$C87 -> 30 | I87: =$C87 -> 30 | J87: =$C87*0.75 -> 22.5 | K87: =$C87 -> 30 | L87: =$C87*0.75 -> 22.5 | M87: =$C87 -> 30 | N87: =$C87 -> 30 | O87: =$C87 -> 30 | P87: =$C87 -> 30
A88: Exit multiple of 2030 economic cash flow | B88: 18 | C88: 28 | D88: 32 | E88: Used in the cash flow method | G88: =$C88 -> 28 | H88: =$C88 -> 28 | I88: =$C88 -> 28 | J88: =$C88*0.75 -> 21 | K88: =$C88 -> 28 | L88: =$C88*0.75 -> 21 | M88: =$C88 -> 28 | N88: =$C88 -> 28 | O88: =$C88 -> 28 | P88: =$C88 -> 28
A89: Discount rate add-on (points) | B89: 0 | C89: 0 | D89: 0 | E89: Added to the shared discount rate | G89: =$C89 -> 0 | H89: =$C89 -> 0 | I89: =$C89 -> 0 | J89: =$C89 -> 0 | K89: =0.02 -> 0.02 | L89: =0.02 -> 0.02 | M89: =$C89 -> 0 | N89: =$C89 -> 0 | O89: =$C89 -> 0 | P89: =$C89 -> 0
A90: Tax method (0 = v1.1 ramp, 1 = NOL + state, 2 = flat rate) | B90: 1 | C90: 1 | D90: 1 | E90: Method 1 is the v1.2 default | G90: =$C90 -> 1 | H90: =$C90 -> 1 | I90: =$C90 -> 1 | J90: =$C90 -> 1 | K90: =$C90 -> 1 | L90: =$C90 -> 1 | M90: =2 -> 2 | N90: =2 -> 2 | O90: =2 -> 2 | P90: =$C90 -> 1
A91: Flat combined tax rate (method 2 only) | B91: 0.25 | C91: 0.25 | D91: 0.25 | E91: Used only when tax method = 2 | G91: =$C91 -> 0.25 | H91: =$C91 -> 0.25 | I91: =$C91 -> 0.25 | J91: =$C91 -> 0.25 | K91: =$C91 -> 0.25 | L91: =$C91 -> 0.25 | M91: =0.21 -> 0.21 | N91: =0.25 -> 0.25 | O91: =0.28 -> 0.28 | P91: =$C91 -> 0.25
A92: Compute prepayment paid at the start of 2027 ($mm) | B92: 0 | C92: 0 | D92: 0 | E92: Cash paid ahead of use (S-1 shows large hosting prepayments). S7 uses $200B as an illustrative funding test; credits follow the prepaid roll-forward | G92: =$C92 -> 0 | H92: =$C92 -> 0 | I92: =$C92 -> 0 | J92: =$C92 -> 0 | K92: =$C92 -> 0 | L92: =$C92 -> 0 | M92: =$C92 -> 0 | N92: =$C92 -> 0 | O92: =$C92 -> 0 | P92: =200000 -> 200000
A93: Scenario probability | B93: 0.25 | C93: 0.5 | D93: 0.25 | E93: Must sum to 100%
A94: Probability check (should be 100%) | B94: =SUM(B93:D93) -> 1
A96: Value-share line (hypothetical) | B96: Bear | C96: Base | D96: Bull | E96: Why
A97: Share of core revenue base under value-share contracts 2027 | B97: 0.005 | C97: 0.02 | D97: 0.04 | E97: Hypothetical. Seeds in S-1: Ode with Anthropic, drug discovery partners. No such revenue line is disclosed | G97: =$C97 -> 0.02 | H97: =$C97 -> 0.02 | I97: =$C97 -> 0.02 | J97: =$C97 -> 0.02 | K97: =$C97 -> 0.02 | L97: =$C97 -> 0.02 | M97: =$C97 -> 0.02 | N97: =$C97 -> 0.02 | ... P97: =$C97 -> 0.02
A98: Share of core revenue base under value-share contracts 2028 | B98: 0.015 | C98: 0.05 | D98: 0.1 | G98: =$C98 -> 0.05 | H98: =$C98 -> 0.05 | I98: =$C98 -> 0.05 | J98: =$C98 -> 0.05 | K98: =$C98 -> 0.05 | L98: =$C98 -> 0.05 | M98: =$C98 -> 0.05 | N98: =$C98 -> 0.05 | ... P98: =$C98 -> 0.05
A99: Share of core revenue base under value-share contracts 2029 | B99: 0.03 | C99: 0.1 | D99: 0.18 | G99: =$C99 -> 0.1 | H99: =$C99 -> 0.1 | I99: =$C99 -> 0.1 | J99: =$C99 -> 0.1 | K99: =$C99 -> 0.1 | L99: =$C99 -> 0.1 | M99: =$C99 -> 0.1 | N99: =$C99 -> 0.1 | ... P99: =$C99 -> 0.1
A100: Share of core revenue base under value-share contracts 2030 | B100: 0.05 | C100: 0.15 | D100: 0.25 | G100: =$C100 -> 0.15 | H100: =$C100 -> 0.15 | I100: =$C100 -> 0.15 | J100: =$C100 -> 0.15 | K100: =$C100 -> 0.15 | L100: =$C100 -> 0.15 | M100: =$C100 -> 0.15 | N100: =$C100 -> 0.15 | ... P100: =$C100 -> 0.15
A101: Economic value created per $1 of Claude spend | B101: 4 | C101: 8 | D101: 12 | E101: Hypothetical. Measurable partner gain per $1 it would have paid in tokens | G101: =$C101 -> 8 | H101: =$C101 -> 8 | I101: =$C101 -> 8 | J101: =$C101 -> 8 | K101: =$C101 -> 8 | L101: =$C101 -> 8 | M101: =$C101 -> 8 | N101: =$C101 -> 8 | ... P101: =$C101 -> 8
A102: Anthropic's cut of value created | B102: 0.1 | C102: 0.15 | D102: 0.2 | E102: Hypothetical royalty / revenue share / success fee | G102: =$C102 -> 0.15 | H102: =$C102 -> 0.15 | I102: =$C102 -> 0.15 | J102: =$C102 -> 0.15 | K102: =$C102 -> 0.15 | L102: =$C102 -> 0.15 | M102: =$C102 -> 0.15 | N102: =$C102 -> 0.15 | ... P102: =$C102 -> 0.15
A103: Token revenue given up on those customers | B103: 0.5 | C103: 0.3 | D103: 0.2 | E103: Share of their per-token spend waived in exchange for the cut | G103: =$C103 -> 0.3 | H103: =$C103 -> 0.3 | I103: =$C103 -> 0.3 | J103: =$C103 -> 0.3 | K103: =$C103 -> 0.3 | L103: =$C103 -> 0.3 | M103: =$C103 -> 0.3 | N103: =$C103 -> 0.3 | ... P103: =$C103 -> 0.3
A104: Delivery cost % of value-share revenue | B104: 0.3 | C104: 0.2 | D104: 0.15 | E104: Embedded engineers, partner operations, measuring and auditing results | G104: =$C104 -> 0.2 | H104: =$C104 -> 0.2 | I104: =$C104 -> 0.2 | J104: =$C104 -> 0.2 | K104: =$C104 -> 0.2 | L104: =$C104 -> 0.2 | M104: =$C104 -> 0.2 | N104: =$C104 -> 0.2 | ... P104: =$C104 -> 0.2
A105: Extra compute % of value-share revenue | B105: 0.25 | C105: 0.15 | D105: 0.1 | E105: Dedicated capacity for partnered deployments | G105: =$C105 -> 0.15 | H105: =$C105 -> 0.15 | I105: =$C105 -> 0.15 | J105: =$C105 -> 0.15 | K105: =$C105 -> 0.15 | L105: =$C105 -> 0.15 | M105: =$C105 -> 0.15 | N105: =$C105 -> 0.15 | ... P105: =$C105 -> 0.15
A106: Selling, partner fees & overhead % of value-share revenue | B106: 0.15 | C106: 0.1 | D106: 0.08 | E106: Deal-making, cloud partner fees, legal and overhead | G106: =$C106 -> 0.1 | H106: =$C106 -> 0.1 | I106: =$C106 -> 0.1 | J106: =$C106 -> 0.1 | K106: =$C106 -> 0.1 | L106: =$C106 -> 0.1 | M106: =$C106 -> 0.1 | N106: =$C106 -> 0.1 | ... P106: =$C106 -> 0.1
A108: Input checks | B108: Problems | C108: What is checked
A109: Probabilities sum to 100% | B109: =IF(ABS($B$94-1)>0.0005,1,0) -> 0 | C109: Bear + Base + Bull probability
A110: Probabilities between 0 and 1 | B110: =SUMPRODUCT(($B$93:$D$93<0)+($B$93:$D$93>1)) -> 0
...

Sheet Bear
A1: Bear — projections, cash and valuation ($ millions except per share)
A2: 2026E = H1 2026 actual + Q3 2026 implied + assumed Q4. Compute is forecast as cash spending (hosting, leases and owned capacity all treated as paid when expensed); the S-1 gives no payment schedule.
A4: Core business: income statement | B4: 2025A | C4: 2026E | D4: 2027E | E4: 2028E | F4: 2029E | G4: 2030E
A5: Revenue | B5: =Historicals!D35 -> 4585 | C5: =Historicals!F35+(Inputs!$B$5+Inputs!$B$60) -> 51728 | D5: =C5*(1+Inputs!$B$62) -> 82764.8 | E5: =D5*(1+Inputs!$B$63) -> 107594.24 | F5: =E5*(1+Inputs!$B$64) -> 129113.09 | G5: =F5*(1+Inputs!$B$65) -> 148480.05
A6: Growth | C6: =IFERROR(C5/B5-1,0) -> 10.282007 | D6: =IFERROR(D5/C5-1,0) -> 0.6 | E6: =IFERROR(E5/D5-1,0) -> 0.3 | F6: =IFERROR(F5/E5-1,0) -> 0.2 | G6: =IFERROR(G5/F5-1,0) -> 0.15
A7: Subscription revenue | B7: =Historicals!D51 -> 789 | C7: =Historicals!F51+(Inputs!$B$5+Inputs!$B$60)*Historicals!F51/Historicals!F35 -> 10233.797 | D7: =D5*Inputs!$B$61 -> 18208.256 | E7: =E5*Inputs!$B$61 -> 23670.733 | F7: =F5*Inputs!$B$61 -> 28404.879 | G7: =G5*Inputs!$B$61 -> 32665.611
A8: Consumption revenue | B8: =B5-B7 -> 3796 | C8: =C5-C7 -> 41494.203 | D8: =D5-D7 -> 64556.544 | E8: =E5-E7 -> 83923.507 | F8: =F5-F7 -> 100708.21 | G8: =G5-G7 -> 115814.44
A10: Compute and infrastructure | B10: =Historicals!D36 -> 7326 | C10: =Historicals!F36+(Inputs!$B$5+Inputs!$B$60)*Inputs!$B$66 -> 26666 | D10: =C10*(1+Inputs!$B$67) -> 42665.6 | E10: =D10*(1+Inputs!$B$68) -> 55465.28 | F10: =E10*(1+Inputs!$B$69) -> 66558.336 | G10: =F10*(1+Inputs!$B$70) -> 76542.086
A11: Personnel (incl. stock comp) | B11: =Historicals!D37 -> 1839 | C11: =Historicals!F37+(Inputs!$B$5+Inputs!$B$60)*Historicals!G24 -> 8847.8714 | D11: =D5*Inputs!$B$71 -> 13242.368 | E11: =E5*Inputs!$B$72 -> 16139.136 | F11: =F5*Inputs!$B$73 -> 18075.832 | G11: =G5*Inputs!$B$74 -> 19302.407
A12: of which stock comp | B12: =Historicals!D49 -> 1158 | C12: =Historicals!F49+(Inputs!$B$5+Inputs!$B$60)*Historicals!G29 -> 6052.7942 | D12: =D5*Inputs!$B$75 -> 8276.48 | E12: =E5*Inputs!$B$76 -> 9683.4816 | F12: =F5*Inputs!$B$77 -> 10329.047 | G12: =G5*Inputs!$B$78 -> 10393.604
A13: Sales, marketing & partner fees | B13: =Historicals!D39 -> 568 | C13: =Historicals!F39+(Inputs!$B$5+Inputs!$B$60)*Historicals!G25 -> 9716.5651 | D13: =D5*Inputs!$B$79 -> 14897.664 | E13: =E5*Inputs!$B$80 -> 18291.021 | F13: =F5*Inputs!$B$81 -> 20658.094 | G13: =G5*Inputs!$B$82 -> 23756.808
A14: Other operating & administrative | B14: =Historicals!D40 -> 1412 | C14: =Historicals!F40+(Inputs!$B$5+Inputs!$B$60)*Historicals!G26 -> 4876.3282 | D14: =D5*Inputs!$B$83 -> 7448.832 | E14: =E5*Inputs!$B$84 -> 8607.5392 | F14: =F5*Inputs!$B$85 -> 9037.9162 | G14: =G5*Inputs!$B$86 -> 10393.604
A15: One-time items (2025 Bartz settlement; 2026 Q3 donation-matching charge) | B15: =Historicals!D38 -> 1500 | C15: =Inputs!$B$37 -> 2000 | D15: 0 | E15: 0 | F15: 0 | G15: 0
A16: Total operating expenses | B16: =B10+B11+B13+B14+B15 -> 12645 | C16: =C10+C11+C13+C14+C15 -> 52106.765 | D16: =D10+D11+D13+D14+D15 -> 78254.464 | E16: =E10+E11+E13+E14+E15 -> 98502.976 | F16: =F10+F11+F13+F14+F15 -> 114330.18 | G16: =G10+G11+G13+G14+G15 -> 129994.9
A17: Operating income before depreciation of new owned capacity | B17: =B5-B16 -> -8060 | C17: =C5-C16 -> -378.76469 | D17: =D5-D16 -> 4510.336 | E17: =E5-E16 -> 9091.264 | F17: =F5-F16 -> 14782.909 | G17: =G5-G16 -> 18485.146
A18: Margin | B18: =IFERROR(B17/B5,0) -> -1.7579062 | C18: =IFERROR(C17/C5,0) -> -0.0073222373 | D18: =IFERROR(D17/D5,0) -> 0.054495824 | E18: =IFERROR(E17/E5,0) -> 0.084495824 | F18: =IFERROR(F17/F5,0) -> 0.11449582 | G18: =IFERROR(G17/G5,0) -> 0.12449582
A19: Compute % of revenue | B19: =IFERROR(B10/B5,0) -> 1.597819 | C19: =IFERROR(C10/C5,0) -> 0.51550418 | D19: =IFERROR(D10/D5,0) -> 0.51550418 | E19: =IFERROR(E10/E5,0) -> 0.51550418 | F19: =IFERROR(F10/F5,0) -> 0.51550418 | G19: =IFERROR(G10/G5,0) -> 0.51550418
A20: Non-cash donation-matching charges (incl. in costs above) | C20: =Historicals!$B$78+Inputs!$B$37 -> 2126 | D20: 0 | E20: 0 | F20: 0 | G20: 0
A21: Discount factor to end 2026 | D21: =1/(1+Inputs!$B$19+Inputs!$B$89)^1 -> 0.89285714 | E21: =1/(1+Inputs!$B$19+Inputs!$B$89)^2 -> 0.79719388 | F21: =1/(1+Inputs!$B$19+Inputs!$B$89)^3 -> 0.71178025 | G21: =1/(1+Inputs!$B$19+Inputs!$B$89)^4 -> 0.63551808
A23: Third business line: value-share partnerships (hypothetical)
A24: Share of core revenue base under value-share | C24: 0 | D24: =Inputs!$B$97 -> 0.005 | E24: =Inputs!$B$98 -> 0.015 | F24: =Inputs!$B$99 -> 0.03 | G24: =Inputs!$B$100 -> 0.05
A25: Revenue base moved to value-share | C25: =C5*C24 -> 0 | D25: =D5*D24 -> 413.824 | E25: =E5*E24 -> 1613.9136 | F25: =F5*F24 -> 3873.3926 | G25: =G5*G24 -> 7424.0026
A26: Value created per $1 of Claude spend | C26: =Inputs!$B$101 -> 4 | D26: =Inputs!$B$101 -> 4 | E26: =Inputs!$B$101 -> 4 | F26: =Inputs!$B$101 -> 4 | G26: =Inputs!$B$101 -> 4
A27: Economic value created for partners | C27: =C25*C26 -> 0 | D27: =D25*D26 -> 1655.296 | E27: =E25*E26 -> 6455.6544 | F27: =F25*F26 -> 15493.571 | G27: =G25*G26 -> 29696.01
A28: Anthropic's cut | C28: =Inputs!$B$102 -> 0.1 | D28: =Inputs!$B$102 -> 0.1 | E28: =Inputs!$B$102 -> 0.1 | F28: =Inputs!$B$102 -> 0.1 | G28: =Inputs!$B$102 -> 0.1
A29: Value-share revenue (gross) | C29: =C27*C28 -> 0 | D29: =D27*D28 -> 165.5296 | E29: =E27*E28 -> 645.56544 | F29: =F27*F28 -> 1549.3571 | G29: =G27*G28 -> 2969.601
A30: Token revenue given up | C30: =C25*Inputs!$B$103 -> 0 | D30: =D25*Inputs!$B$103 -> 206.912 | E30: =E25*Inputs!$B$103 -> 806.9568 | F30: =F25*Inputs!$B$103 -> 1936.6963 | G30: =G25*Inputs!$B$103 -> 3712.0013
A31: Net new revenue | C31: =C29-C30 -> 0 | D31: =D29-D30 -> -41.3824 | E31: =E29-E30 -> -161.39136 | F31: =F29-F30 -> -387.33926 | G31: =G29-G30 -> -742.40026
A32: Delivery cost | C32: =C29*Inputs!$B$104 -> 0 | D32: =D29*Inputs!$B$104 -> 49.65888 | E32: =E29*Inputs!$B$104 -> 193.66963 | F32: =F29*Inputs!$B$104 -> 464.80712 | G32: =G29*Inputs!$B$104 -> 890.88031
A33: Extra compute | C33: =C29*Inputs!$B$105 -> 0 | D33: =D29*Inputs!$B$105 -> 41.3824 | E33: =E29*Inputs!$B$105 -> 161.39136 | F33: =F29*Inputs!$B$105 -> 387.33926 | G33: =G29*Inputs!$B$105 -> 742.40026
A34: Selling, partner fees & overhead | C34: =C29*Inputs!$B$106 -> 0 | D34: =D29*Inputs!$B$106 -> 24.82944 | E34: =E29*Inputs!$B$106 -> 96.834816 | F34: =F29*Inputs!$B$106 -> 232.40356 | G34: =G29*Inputs!$B$106 -> 445.44015
A35: Value-share operating contribution | C35: =C29-C30-C32-C33-C34 -> 0 | D35: =D29-D30-D32-D33-D34 -> -157.25312 | E35: =E29-E30-E32-E33-E34 -> -613.28717 | F35: =F29-F30-F32-F33-F34 -> -1471.8892 | G35: =G29-G30-G32-G33-G34 -> -2821.121
A36: Value created as % of $40T knowledge-work pool | C36: =IFERROR(C27/Inputs!$B$27,0) -> 0 | D36: =IFERROR(D27/Inputs!$B$27,0) -> 4.13824e-05 | E36: =IFERROR(E27/Inputs!$B$27,0) -> 0.00016139136 | F36: =IFERROR(F27/Inputs!$B$27,0) -> 0.00038733926 | G36: =IFERROR(G27/Inputs!$B$27,0) -> 0.00074240026
A37: Value-share capital spending (per selected basis) | C37: =CHOOSE(Inputs!$B$35,C31*Inputs!B$55,C29*Inputs!$B$36,0) -> 0 | D37: =CHOOSE(Inputs!$B$35,D31*Inputs!C$55,D29*Inputs!$B$36,0) -> -1.655296 | E37: =CHOOSE(Inputs!$B$35,E31*Inputs!D$55,E29*Inputs!$B$36,0) -> -8.069568 | F37: =CHOOSE(Inputs!$B$35,F31*Inputs!E$55,F29*Inputs!$B$36,0) -> -19.366963 | G37: =CHOOSE(Inputs!$B$35,G31*Inputs!F$55,G29*Inputs!$B$36,0) -> -37.120013
A38: Value-share collection timing (working capital) | C38: 0 | D38: =-(D29-C29)*Inputs!$B$34/365 -> 0 | E38: =-(E29-D29)*Inputs!$B$34/365 -> 0 | F38: =-(F29-E29)*Inputs!$B$34/365 -> 0 | G38: =-(G29-F29)*Inputs!$B$34/365 -> 0
A40: Prepaid compute roll-forward (cash paid ahead of use)
A41: Prepaid balance, opening | C41: 0 | D41: =C46 -> 0 | E41: =D46 -> 0 | F41: =E46 -> 0 | G41: =F46 -> 0
A42: Prepayment paid (start of year) | C42: 0 | D42: =Inputs!$B$92 -> 0 | E42: 0 | F42: 0 | G42: 0
A43: Scheduled credits available (cumulative scheduled less used) | C43: =MAX(0,0) -> 0 | D43: =MAX(0,0) -> 0 | E43: =MAX(0,$D$42/Inputs!$B$40*MIN(1,Inputs!$B$40)-SUM($C45:D45)) -> 0 | F43: =MAX(0,$D$42/Inputs!$B$40*MIN(2,Inputs!$B$40)-SUM($C45:E45)) -> 0 | G43: =MAX(0,$D$42/Inputs!$B$40*MIN(3,Inputs!$B$40)-SUM($C45:F45)) -> 0
A44: Eligible compute charges this year | C44: =C10*Inputs!$B$39 -> 26666 | D44: =D10*Inputs!$B$39 -> 42665.6 | E44: =E10*Inputs!$B$39 -> 55465.28 | F44: =F10*Inputs!$B$39 -> 66558.336 | G44: =G10*Inputs!$B$39 -> 76542.086
A45: Credits used (capped by balance, schedule and eligible charges) | C45: =MAX(0,MIN(C41+C42,C43,C44)) -> 0 | D45: =MAX(0,MIN(D41+D42,D43,D44)) -> 0 | E45: =MAX(0,MIN(E41+E42,E43,E44)) -> 0 | F45: =MAX(0,MIN(F41+F42,F43,F44)) -> 0 | G45: =MAX(0,MIN(G41+G42,G43,G44)) -> 0
A46: Prepaid balance, closing | C46: =C41+C42-C45 -> 0 | D46: =D41+D42-D45 -> 0 | E46: =E41+E42-E45 -> 0 | F46: =F41+F42-F45 -> 0 | G46: =G41+G42-G45 -> 0
A48: Core business (tokens + subscriptions): earnings, taxes, cash
A49: Revenue | C49: =C5 -> 51728 | D49: =D5 -> 82764.8 | E49: =E5 -> 107594.24 | F49: =F5 -> 129113.09 | G49: =G5 -> 148480.05
A50: Operating income before depreciation of new owned capacity | C50: =C17 -> -378.76469 | D50: =D17 -> 4510.336 | E50: =E17 -> 9091.264 | F50: =F17 -> 14782.909 | G50: =G17 -> 18485.146
A51: Capital spending | C51: =C5*Inputs!B$55 -> 1551.84 | D51: =D5*Inputs!C$55 -> 3310.592 | E51: =E5*Inputs!D$55 -> 5379.712 | F51: =F5*Inputs!E$55 -> 6455.6544 | G51: =G5*Inputs!F$55 -> 7424.0026
A52: Depreciation of owned capacity bought from 2027 | C52: 0 | D52: =SUMPRODUCT($D51:D51,--((4-COLUMN($D51:D51))<Inputs!$B$32))/Inputs!$B$32 -> 662.1184 | E52: =SUMPRODUCT($D51:E51,--((5-COLUMN($D51:E51))<Inputs!$B$32))/Inputs!$B$32 -> 1738.0608 | F52: =SUMPRODUCT($D51:F51,--((6-COLUMN($D51:F51))<Inputs!$B$32))/Inputs!$B$32 -> 3029.1917 | G52: =SUMPRODUCT($D51:G51,--((7-COLUMN($D51:G51))<Inputs!$B$32))/Inputs!$B$32 -> 4513.9922
A53: Operating income (earnings basis, after stock comp) | C53: =C50-C52 -> -378.76469 | D53: =D50-D52 -> 3848.2176 | E53: =E50-E52 -> 7353.2032 | F53: =F50-F52 -> 11753.718 | G53: =G50-G52 -> 13971.154
A54: Operating margin | C54: =IFERROR(C53/C49,0) -> -0.0073222373 | D54: =IFERROR(D53/D49,0) -> 0.046495824 | E54: =IFERROR(E53/E49,0) -> 0.068341978 | F54: =IFERROR(F53/F49,0) -> 0.091034286 | G54: =IFERROR(G53/G49,0) -> 0.094094487
A55: Interest income (on opening cash) | C55: =Historicals!F43+C80*Inputs!$B$20/2 -> 2756.6375 | D55: =MAX(0,D80-D81)*Inputs!$B$20 -> 3455.7887 | E55: =MAX(0,E80-E81)*Inputs!$B$20 -> 3769.8982 | F55: =MAX(0,F80-F81)*Inputs!$B$20 -> 4134.2193 | G55: =MAX(0,G80-G81)*Inputs!$B$20 -> 4607.0151
A56: Other taxable income adjustments | C56: =Inputs!B$56 -> 0 | D56: =Inputs!C$56 -> 0 | E56: =Inputs!D$56 -> 0 | F56: =Inputs!E$56 -> 0 | G56: =Inputs!F$56 -> 0
A57: IPO RSU tax deduction | C57: =IF(Inputs!$B$51=2026,Inputs!$B$50,0) -> 0 | D57: =IF(Inputs!$B$51=2027,Inputs!$B$50,0) -> 0 | E57: =IF(Inputs!$B$51=2028,Inputs!$B$50,0) -> 0 | F57: =IF(Inputs!$B$51=2029,Inputs!$B$50,0) -> 0 | G57: =IF(Inputs!$B$51=2030,Inputs!$B$50,0) -> 0
A58: Taxable income proxy | C58: =C53+C55+C56-C57 -> 2377.8728 | D58: =D53+D55+D56-D57 -> 7304.0063 | E58: =E53+E55+E56-E57 -> 11123.101 | F58: =F53+F55+F56-F57 -> 15887.937 | G58: =G53+G55+G56-G57 -> 18578.169
A59: State taxable base (apportioned) | C59: =C58*Inputs!$B$46 -> 1712.0684 | D59: =D58*Inputs!$B$46 -> 5258.8845 | E59: =E58*Inputs!$B$46 -> 8008.633 | F59: =F58*Inputs!$B$46 -> 11439.315 | G59: =G58*Inputs!$B$46 -> 13376.282
A60: State NOL, opening | C60: =Inputs!$B$48 -> 4200 | D60: =C62 -> 4200 | E60: =D62 -> 0 | F60: =E62 -> 0 | G60: =F62 -> 0
A61: State NOL used | C61: =IF(AND(2026=2026,Inputs!$B$49=1),0,MIN(C60,MAX(0,C59))) -> 0 | D61: =IF(AND(2027=2026,Inputs!$B$49=1),0,MIN(D60,MAX(0,D59))) -> 4200 | E61: =IF(AND(2028=2026,Inputs!$B$49=1),0,MIN(E60,MAX(0,E59))) -> 0 | F61: =IF(AND(2029=2026,Inputs!$B$49=1),0,MIN(F60,MAX(0,F59))) -> 0 | G61: =IF(AND(2030=2026,Inputs!$B$49=1),0,MIN(G60,MAX(0,G59))) -> 0
A62: State NOL, closing | C62: =C60-C61+MAX(0,-C59) -> 4200 | D62: =D60-D61+MAX(0,-D59) -> 0 | E62: =E60-E61+MAX(0,-E59) -> 0 | F62: =F60-F61+MAX(0,-F59) -> 0 | G62: =G60-G61+MAX(0,-G59) -> 0
A63: State tax | C63: =MAX(0,C59-C61)*Inputs!$B$47 -> 102.72411 | D63: =MAX(0,D59-D61)*Inputs!$B$47 -> 63.533071 | E63: =MAX(0,E59-E61)*Inputs!$B$47 -> 480.51798 | F63: =MAX(0,F59-F61)*Inputs!$B$47 -> 686.35888 | G63: =MAX(0,G59-G61)*Inputs!$B$47 -> 802.57691
A64: Federal taxable income before NOL (after state tax) | C64: =C58-C63 -> 2275.1487 | D64: =D58-D63 -> 7240.4732 | E64: =E58-E63 -> 10642.583 | F64: =F58-F63 -> 15201.578 | G64: =G58-G63 -> 17775.592
A65: Federal NOL, opening | C65: =Inputs!$B$44 -> 8200 | D65: =C67 -> 6379.881 | E65: =D67 -> 587.50248 | F65: =E67 -> 0 | G65: =F67 -> 0
A66: Federal NOL used (80% limit) | C66: =MIN(C65,Inputs!$B$45*MAX(0,C64)) -> 1820.119 | D66: =MIN(D65,Inputs!$B$45*MAX(0,D64)) -> 5792.3786 | E66: =MIN(E65,Inputs!$B$45*MAX(0,E64)) -> 587.50248 | F66: =MIN(F65,Inputs!$B$45*MAX(0,F64)) -> 0 | G66: =MIN(G65,Inputs!$B$45*MAX(0,G64)) -> 0
A67: Federal NOL, closing | C67: =C65-C66+MAX(0,-C64) -> 6379.881 | D67: =D65-D66+MAX(0,-D64) -> 587.50248 | E67: =E65-E66+MAX(0,-E64) -> 0 | F67: =F65-F66+MAX(0,-F64) -> 0 | G67: =G65-G66+MAX(0,-G64) -> 0
A68: Federal tax | C68: =MAX(0,C64-C66)*Inputs!$B$43 -> 95.556246 | D68: =MAX(0,D64-D66)*Inputs!$B$43 -> 304.09987 | E68: =MAX(0,E64-E66)*Inputs!$B$43 -> 2111.567 | F68: =MAX(0,F64-F66)*Inputs!$B$43 -> 3192.3314 | G68: =MAX(0,G64-G66)*Inputs!$B$43 -> 3732.8744
A69: Cash taxes (selected method) | C69: =IF(Inputs!$B$90=0,MAX(0,C53+C55)*Inputs!B$54,IF(Inputs!$B$90=2,MAX(0,C58)*Inputs!$B$91,C63+C68)) -> 198.28035 | D69: =IF(Inputs!$B$90=0,MAX(0,D53+D55)*Inputs!C$54,IF(Inputs!$B$90=2,MAX(0,D58)*Inputs!$B$91,D63+D68)) -> 367.63294 | E69: =IF(Inputs!$B$90=0,MAX(0,E53+E55)*Inputs!D$54,IF(Inputs!$B$90=2,MAX(0,E58)*Inputs!$B$91,E63+E68)) -> 2592.085 | F69: =IF(Inputs!$B$90=0,MAX(0,F53+F55)*Inputs!E$54,IF(Inputs!$B$90=2,MAX(0,F58)*Inputs!$B$91,F63+F68)) -> 3878.6903 | G69: =IF(Inputs!$B$90=0,MAX(0,G53+G55)*Inputs!F$54,IF(Inputs!$B$90=2,MAX(0,G58)*Inputs!$B$91,G63+G68)) -> 4535.4513
A70: Effective tax rate on taxable income | C70: =IF(C58>0,MIN(1,C69/C58),0) -> 0.0833856 | D70: =IF(D58>0,MIN(1,D69/D58),0) -> 0.050333054 | E70: =IF(E58>0,MIN(1,E69/E58),0) -> 0.23303617 | F70: =IF(F58>0,MIN(1,F69/F58),0) -> 0.244128 | G70: =IF(G58>0,MIN(1,G69/G58),0) -> 0.244128
A71: Net income excl. non-cash fair value items | C71: =C53+C55-C69 -> 2179.5925 | D71: =D53+D55-D69 -> 6936.3733 | E71: =E53+E55-E69 -> 8531.0164 | F71: =F53+F55-F69 -> 12009.247 | G71: =G53+G55-G69 -> 14042.718
A72: Non-cash stock comp & donation charges (added back for liquidity) | C72: =C12+C20 -> 8178.7942 | D72: =D12+D20 -> 8276.48 | E72: =E12+E20 -> 9683.4816 | F72: =F12+F20 -> 10329.047 | G72: =G12+G20 -> 10393.604
A73: Working capital | C73: 0 | D73: =-(D5-C5)*Inputs!$B$33 -> 0 | E73: =-(E5-D5)*Inputs!$B$33 -> 0 | F73: =-(F5-E5)*Inputs!$B$33 -> 0 | G73: =-(G5-F5)*Inputs!$B$33 -> 0
A74: Compute prepayment timing (non-recurring; excluded from exit value) | C74: =-C$42+C$45 -> 0 | D74: =-D$42+D$45 -> 0 | E74: =-E$42+E$45 -> 0 | F74: =-F$42+F$45 -> 0 | G74: =-G$42+G$45 -> 0
A75: Actual cash flow (liquidity basis) | C75: =C53+C72+C52+C55-C69-C51+C73+C74 -> 8806.5467 | D75: =D53+D72+D52+D55-D69-D51+D73+D74 -> 12564.38 | E75: =E53+E72+E52+E55-E69-E51+E73+E74 -> 14572.847 | F75: =F53+F72+F52+F55-F69-F51+F73+F74 -> 18911.831 | G75: =G53+G72+G52+G55-G69-G51+G73+G74 -> 21526.311
A76: Economic operating cash flow (valuation basis: after stock comp, excl. interest) | C76: =C53+C52-(C69-C55*C70)-C51+C73+C74 -> -1899.0212 | D76: =D53+D52-(D69-D55*D70)-D51+D73+D74 -> 1006.0515 | E76: =E53+E52-(E69-E55*E70)-E51+E73+E74 -> 1997.9897 | F76: =F53+F52-(F69-F55*F70)-F51+F73+F74 -> 5457.8434 | G76: =G53+G52-(G69-G55*G70)-G51+G73+G74 -> 7650.3939
A77: Economic cash flow margin | C77: =IFERROR(C76/C49,0) -> -0.036711668 | D77: =IFERROR(D76/D49,0) -> 0.012155547 | E77: =IFERROR(E76/E49,0) -> 0.018569671 | F77: =IFERROR(F76/F49,0) -> 0.042271806 | G77: =IFERROR(G76/G49,0) -> 0.051524726
A79: Cash roll-forward | C79: H2 2026 | D79: 2027E | E79: 2028E | F79: 2029E | G79: 2030E
A80: Opening cash | C80: =Inputs!$B$6 -> 131651 | D80: =C85 -> 138231.55 | E80: =D85 -> 150795.93 | F80: =E85 -> 165368.77 | G80: =F85 -> 184280.6
A81: of which paid at start of year (prepayment) | C81: =C$42 -> 0 | D81: =D$42 -> 0 | E81: =E$42 -> 0 | F81: =F$42 -> 0 | G81: =G$42 -> 0
A82: Cash flow in period (H2 only for 2026) | B82: 2026: full-year cash flow less H1 actual on the same basis | C82: =C75-Historicals!$B$79 -> 6580.5467 | D82: =D75 -> 12564.38 | E82: =E75 -> 14572.847 | F82: =F75 -> 18911.831 | G82: =G75 -> 21526.311
A83: RSU tax withholding paid | C83: =-Inputs!$B$17 -> 0 | D83: 0 | E83: 0 | F83: 0 | G83: 0
A84: Primary IPO proceeds | C84: =Inputs!$B$15 -> 0 | D84: 0 | E84: 0 | F84: 0 | G84: 0
A85: Closing cash | C85: =C80+C82+C83+C84 -> 138231.55 | D85: =D80+D82+D83+D84 -> 150795.93 | E85: =E80+E82+E83+E84 -> 165368.77 | F85: =F80+F82+F83+F84 -> 184280.6 | G85: =G80+G82+G83+G84 -> 205806.92
A86: Lowest cash in the year (start-of-year payments or year end) | C86: =MIN(C80-C81,C85) -> 131651 | D86: =MIN(D80-D81,D85) -> 138231.55 | E86: =MIN(E80-E81,E85) -> 150795.93 | F86: =MIN(F80-F81,F85) -> 165368.77 | G86: =MIN(G80-G81,G85) -> 184280.6
A87: Lowest cash above the shortfall threshold | C87: =C86-Inputs!$B$29 -> 126651 | D87: =D86-Inputs!$B$29 -> 133231.55 | E87: =E86-Inputs!$B$29 -> 145795.93 | F87: =F86-Inputs!$B$29 -> 160368.77 | G87: =G86-Inputs!$B$29 -> 179280.6
A88: Year-end cash vs $5B covenant (cash proxy) | C88: =IF(C85<Inputs!$B$38,"Below","OK") -> OK | D88: =IF(D85<Inputs!$B$38,"Below","OK") -> OK | E88: =IF(E85<Inputs!$B$38,"Below","OK") -> OK | F88: =IF(F85<Inputs!$B$38,"Below","OK") -> OK | G88: =IF(G85<Inputs!$B$38,"Below","OK") -> OK
A89: Funding status | C89: =IF(C87<0,"Shortfall","OK") -> OK | D89: =IF(D87<0,"Shortfall","OK") -> OK | E89: =IF(E87<0,"Shortfall","OK") -> OK | F89: =IF(F87<0,"Shortfall","OK") -> OK | G89: =IF(G87<0,"Shortfall","OK") -> OK
A90: Peak funding need (intra-year) | G90: =MAX(0,-MIN(C87:G87)) -> 0
A91: Sensitivity: peak funding need with a $0 buffer | G91: =MAX(0,-MIN(C86:G86)) -> 0
A92: Funded cash path (illustrative equity raise) | C92: H2 2026 | D92: 2027E | E92: 2028E | F92: 2029E | G92: 2030E
A93: Financing year (start of the first shortfall year; proceeds arrive with the payment) | G93: =IF(G90=0,"none",IFERROR(2025+MATCH(1,INDEX(--(C87:G87<0),0),0),"none")) -> none
A94: Net proceeds needed (covers peak need) | G94: =G90 -> 0
A95: Issuance fees | G95: =G94/(1-Inputs!$B$31)*Inputs!$B$31 -> 0
A96: Gross amount raised | G96: =G94+G95 -> 0
A97: Net proceeds received in year | C97: =IF(AND(ISNUMBER($G$93),$G$93=2026),$G$94,0) -> 0 | D97: =IF(AND(ISNUMBER($G$93),$G$93=2027),$G$94,0) -> 0 | E97: =IF(AND(ISNUMBER($G$93),$G$93=2028),$G$94,0) -> 0 | F97: =IF(AND(ISNUMBER($G$93),$G$93=2029),$G$94,0) -> 0 | G97: =IF(AND(ISNUMBER($G$93),$G$93=2030),$G$94,0) -> 0
A98: Interest change vs. unfunded path (funded balance after start-of-year payments) | C98: =C97*Inputs!$B$20/2 -> 0 | D98: =MAX(0,C100-D81+D97)*Inputs!$B$20-D55 -> 0 | E98: =MAX(0,D100-E81+E97)*Inputs!$B$20-E55 -> 0 | F98: =MAX(0,E100-F81+F97)*Inputs!$B$20-F55 -> 0 | G98: =MAX(0,F100-G81+G97)*Inputs!$B$20-G55 -> 0
A99: Extra tax on that interest | C99: =C98*C70 -> 0 | D99: =D98*D70 -> 0 | E99: =E98*E70 -> 0 | F99: =F98*F70 -> 0 | G99: =G98*G70 -> 0
A100: Closing cash — funded | C100: =C85+SUM($C97:C97)+SUM($C98:C98)-SUM($C99:C99) -> 138231.55 | D100: =D85+SUM($C97:D97)+SUM($C98:D98)-SUM($C99:D99) -> 150795.93 | E100: =E85+SUM($C97:E97)+SUM($C98:E98)-SUM($C99:E99) -> 165368.77 | F100: =F85+SUM($C97:F97)+SUM($C98:F98)-SUM($C99:F99) -> 184280.6 | G100: =G85+SUM($C97:G97)+SUM($C98:G98)-SUM($C99:G99) -> 205806.92
A101: Lowest cash in the year — funded | C101: =MIN(C80-C81+0+C97,C100) -> 131651 | D101: =MIN(D80-D81+SUM($C97:C97)+SUM($C98:C98)-SUM($C99:C99)+D97,D100) -> 138231.55 | E101: =MIN(E80-E81+SUM($C97:D97)+SUM($C98:D98)-SUM($C99:D99)+E97,E100) -> 150795.93 | F101: =MIN(F80-F81+SUM($C97:E97)+SUM($C98:E98)-SUM($C99:E99)+F97,F100) -> 165368.77 | G101: =MIN(G80-G81+SUM($C97:F97)+SUM($C98:F98)-SUM($C99:F99)+G97,G100) -> 184280.6
A102: Funded path stays above threshold? | C102: =IF(C101-Inputs!$B$29<-0.5,"No","Yes") -> Yes | D102: =IF(D101-Inputs!$B$29<-0.5,"No","Yes") -> Yes | E102: =IF(E101-Inputs!$B$29<-0.5,"No","Yes") -> Yes | F102: =IF(F101-Inputs!$B$29<-0.5,"No","Yes") -> Yes | G102: =IF(G101-Inputs!$B$29<-0.5,"No","Yes") -> Yes
A104: Hybrid company (core + value-share): earnings, taxes, cash
A105: Revenue | C105: =C5+C31 -> 51728 | D105: =D5+D31 -> 82723.418 | E105: =E5+E31 -> 107432.85 | F105: =F5+F31 -> 128725.75 | G105: =G5+G31 -> 147737.65
A106: Operating income before depreciation of new owned capacity | C106: =C17+C35 -> -378.76469 | D106: =D17+D35 -> 4353.0829 | E106: =E17+E35 -> 8477.9768 | F106: =F17+F35 -> 13311.02 | G106: =G17+G35 -> 15664.025
A107: Capital spending | C107: =C51+C37 -> 1551.84 | D107: =D51+D37 -> 3308.9367 | E107: =E51+E37 -> 5371.6424 | F107: =F51+F37 -> 6436.2874 | G107: =G51+G37 -> 7386.8825
...

Sheet Base
A1: Base — projections, cash and valuation ($ millions except per share)
A2: 2026E = H1 2026 actual + Q3 2026 implied + assumed Q4. Compute is forecast as cash spending (hosting, leases and owned capacity all treated as paid when expensed); the S-1 gives no payment schedule.
A4: Core business: income statement | B4: 2025A | C4: 2026E | D4: 2027E | E4: 2028E | F4: 2029E | G4: 2030E
A5: Revenue | B5: =Historicals!D35 -> 4585 | C5: =Historicals!F35+(Inputs!$B$5+Inputs!$C$60) -> 54228 | D5: =C5*(1+Inputs!$C$62) -> 108456 | E5: =D5*(1+Inputs!$C$63) -> 168106.8 | F5: =E5*(1+Inputs!$C$64) -> 226944.18 | G5: =F5*(1+Inputs!$C$65) -> 283680.22
A6: Growth | C6: =IFERROR(C5/B5-1,0) -> 10.827263 | D6: =IFERROR(D5/C5-1,0) -> 1 | E6: =IFERROR(E5/D5-1,0) -> 0.55 | F6: =IFERROR(F5/E5-1,0) -> 0.35 | G6: =IFERROR(G5/F5-1,0) -> 0.25
A7: Subscription revenue | B7: =Historicals!D51 -> 789 | C7: =Historicals!F51+(Inputs!$B$5+Inputs!$C$60)*Historicals!F51/Historicals!F35 -> 10728.393 | D7: =D5*Inputs!$C$61 -> 21691.2 | E7: =E5*Inputs!$C$61 -> 33621.36 | F7: =F5*Inputs!$C$61 -> 45388.836 | G7: =G5*Inputs!$C$61 -> 56736.045
A8: Consumption revenue | B8: =B5-B7 -> 3796 | C8: =C5-C7 -> 43499.607 | D8: =D5-D7 -> 86764.8 | E8: =E5-E7 -> 134485.44 | F8: =F5-F7 -> 181555.34 | G8: =G5-G7 -> 226944.18
A10: Compute and infrastructure | B10: =Historicals!D36 -> 7326 | C10: =Historicals!F36+(Inputs!$B$5+Inputs!$C$60)*Inputs!$C$66 -> 26018.9 | D10: =C10*(1+Inputs!$C$67) -> 44232.13 | E10: =D10*(1+Inputs!$C$68) -> 64136.588 | F10: =E10*(1+Inputs!$C$69) -> 83377.565 | G10: =F10*(1+Inputs!$C$70) -> 100053.08
A11: Personnel (incl. stock comp) | B11: =Historicals!D37 -> 1839 | C11: =Historicals!F37+(Inputs!$B$5+Inputs!$C$60)*Historicals!G24 -> 9249.6455 | D11: =D5*Inputs!$C$71 -> 15183.84 | E11: =E5*Inputs!$C$72 -> 21853.884 | F11: =F5*Inputs!$C$73 -> 27233.302 | G11: =G5*Inputs!$C$74 -> 31204.825
A12: of which stock comp | B12: =Historicals!D49 -> 1158 | C12: =Historicals!F49+(Inputs!$B$5+Inputs!$C$60)*Historicals!G29 -> 6325.6198 | D12: =D5*Inputs!$C$75 -> 9761.04 | E12: =E5*Inputs!$C$76 -> 13448.544 | F12: =F5*Inputs!$C$77 -> 15886.093 | G12: =G5*Inputs!$C$78 -> 17020.814
A13: Sales, marketing & partner fees | B13: =Historicals!D39 -> 568 | C13: =Historicals!F39+(Inputs!$B$5+Inputs!$C$60)*Historicals!G25 -> 10178.486 | D13: =D5*Inputs!$C$79 -> 18437.52 | E13: =E5*Inputs!$C$80 -> 26897.088 | F13: =F5*Inputs!$C$81 -> 34041.627 | G13: =G5*Inputs!$C$82 -> 42552.034
A14: Other operating & administrative | B14: =Historicals!D40 -> 1412 | C14: =Historicals!F40+(Inputs!$B$5+Inputs!$C$60)*Historicals!G26 -> 5099.3918 | D14: =D5*Inputs!$C$83 -> 8676.48 | E14: =E5*Inputs!$C$84 -> 11767.476 | F14: =F5*Inputs!$C$85 -> 13616.651 | G14: =G5*Inputs!$C$86 -> 17020.814
A15: One-time items (2025 Bartz settlement; 2026 Q3 donation-matching charge) | B15: =Historicals!D38 -> 1500 | C15: =Inputs!$B$37 -> 2000 | D15: 0 | E15: 0 | F15: 0 | G15: 0
A16: Total operating expenses | B16: =B10+B11+B13+B14+B15 -> 12645 | C16: =C10+C11+C13+C14+C15 -> 52546.424 | D16: =D10+D11+D13+D14+D15 -> 86529.97 | E16: =E10+E11+E13+E14+E15 -> 124655.04 | F16: =F10+F11+F13+F14+F15 -> 158269.14 | G16: =G10+G11+G13+G14+G15 -> 190830.75
A17: Operating income before depreciation of new owned capacity | B17: =B5-B16 -> -8060 | C17: =C5-C16 -> 1681.5763 | D17: =D5-D16 -> 21926.03 | E17: =E5-E16 -> 43451.764 | F17: =F5-F16 -> 68675.036 | G17: =G5-G16 -> 92849.475
A18: Margin | B18: =IFERROR(B17/B5,0) -> -1.7579062 | C18: =IFERROR(C17/C5,0) -> 0.031009374 | D18: =IFERROR(D17/D5,0) -> 0.20216521 | E18: =IFERROR(E17/E5,0) -> 0.25847713 | F18: =IFERROR(F17/F5,0) -> 0.30260761 | G18: =IFERROR(G17/G5,0) -> 0.3273033
A19: Compute % of revenue | B19: =IFERROR(B10/B5,0) -> 1.597819 | C19: =IFERROR(C10/C5,0) -> 0.47980564 | D19: =IFERROR(D10/D5,0) -> 0.40783479 | E19: =IFERROR(E10/E5,0) -> 0.38152287 | F19: =IFERROR(F10/F5,0) -> 0.36739239 | G19: =IFERROR(G10/G5,0) -> 0.3526967
A20: Non-cash donation-matching charges (incl. in costs above) | C20: =Historicals!$B$78+Inputs!$B$37 -> 2126 | D20: 0 | E20: 0 | F20: 0 | G20: 0
A21: Discount factor to end 2026 | D21: =1/(1+Inputs!$B$19+Inputs!$C$89)^1 -> 0.89285714 | E21: =1/(1+Inputs!$B$19+Inputs!$C$89)^2 -> 0.79719388 | F21: =1/(1+Inputs!$B$19+Inputs!$C$89)^3 -> 0.71178025 | G21: =1/(1+Inputs!$B$19+Inputs!$C$89)^4 -> 0.63551808
A23: Third business line: value-share partnerships (hypothetical)
A24: Share of core revenue base under value-share | C24: 0 | D24: =Inputs!$C$97 -> 0.02 | E24: =Inputs!$C$98 -> 0.05 | F24: =Inputs!$C$99 -> 0.1 | G24: =Inputs!$C$100 -> 0.15
A25: Revenue base moved to value-share | C25: =C5*C24 -> 0 | D25: =D5*D24 -> 2169.12 | E25: =E5*E24 -> 8405.34 | F25: =F5*F24 -> 22694.418 | G25: =G5*G24 -> 42552.034
A26: Value created per $1 of Claude spend | C26: =Inputs!$C$101 -> 8 | D26: =Inputs!$C$101 -> 8 | E26: =Inputs!$C$101 -> 8 | F26: =Inputs!$C$101 -> 8 | G26: =Inputs!$C$101 -> 8
A27: Economic value created for partners | C27: =C25*C26 -> 0 | D27: =D25*D26 -> 17352.96 | E27: =E25*E26 -> 67242.72 | F27: =F25*F26 -> 181555.34 | G27: =G25*G26 -> 340416.27
A28: Anthropic's cut | C28: =Inputs!$C$102 -> 0.15 | D28: =Inputs!$C$102 -> 0.15 | E28: =Inputs!$C$102 -> 0.15 | F28: =Inputs!$C$102 -> 0.15 | G28: =Inputs!$C$102 -> 0.15
A29: Value-share revenue (gross) | C29: =C27*C28 -> 0 | D29: =D27*D28 -> 2602.944 | E29: =E27*E28 -> 10086.408 | F29: =F27*F28 -> 27233.302 | G29: =G27*G28 -> 51062.44
A30: Token revenue given up | C30: =C25*Inputs!$C$103 -> 0 | D30: =D25*Inputs!$C$103 -> 650.736 | E30: =E25*Inputs!$C$103 -> 2521.602 | F30: =F25*Inputs!$C$103 -> 6808.3254 | G30: =G25*Inputs!$C$103 -> 12765.61
A31: Net new revenue | C31: =C29-C30 -> 0 | D31: =D29-D30 -> 1952.208 | E31: =E29-E30 -> 7564.806 | F31: =F29-F30 -> 20424.976 | G31: =G29-G30 -> 38296.83
A32: Delivery cost | C32: =C29*Inputs!$C$104 -> 0 | D32: =D29*Inputs!$C$104 -> 520.5888 | E32: =E29*Inputs!$C$104 -> 2017.2816 | F32: =F29*Inputs!$C$104 -> 5446.6603 | G32: =G29*Inputs!$C$104 -> 10212.488
A33: Extra compute | C33: =C29*Inputs!$C$105 -> 0 | D33: =D29*Inputs!$C$105 -> 390.4416 | E33: =E29*Inputs!$C$105 -> 1512.9612 | F33: =F29*Inputs!$C$105 -> 4084.9952 | G33: =G29*Inputs!$C$105 -> 7659.3661
A34: Selling, partner fees & overhead | C34: =C29*Inputs!$C$106 -> 0 | D34: =D29*Inputs!$C$106 -> 260.2944 | E34: =E29*Inputs!$C$106 -> 1008.6408 | F34: =F29*Inputs!$C$106 -> 2723.3302 | G34: =G29*Inputs!$C$106 -> 5106.2441
A35: Value-share operating contribution | C35: =C29-C30-C32-C33-C34 -> 0 | D35: =D29-D30-D32-D33-D34 -> 780.8832 | E35: =E29-E30-E32-E33-E34 -> 3025.9224 | F35: =F29-F30-F32-F33-F34 -> 8169.9905 | G35: =G29-G30-G32-G33-G34 -> 15318.732
A36: Value created as % of $40T knowledge-work pool | C36: =IFERROR(C27/Inputs!$B$27,0) -> 0 | D36: =IFERROR(D27/Inputs!$B$27,0) -> 0.000433824 | E36: =IFERROR(E27/Inputs!$B$27,0) -> 0.001681068 | F36: =IFERROR(F27/Inputs!$B$27,0) -> 0.0045388836 | G36: =IFERROR(G27/Inputs!$B$27,0) -> 0.0085104067
A37: Value-share capital spending (per selected basis) | C37: =CHOOSE(Inputs!$B$35,C31*Inputs!B$55,C29*Inputs!$B$36,0) -> 0 | D37: =CHOOSE(Inputs!$B$35,D31*Inputs!C$55,D29*Inputs!$B$36,0) -> 78.08832 | E37: =CHOOSE(Inputs!$B$35,E31*Inputs!D$55,E29*Inputs!$B$36,0) -> 378.2403 | F37: =CHOOSE(Inputs!$B$35,F31*Inputs!E$55,F29*Inputs!$B$36,0) -> 1021.2488 | G37: =CHOOSE(Inputs!$B$35,G31*Inputs!F$55,G29*Inputs!$B$36,0) -> 1914.8415
A38: Value-share collection timing (working capital) | C38: 0 | D38: =-(D29-C29)*Inputs!$B$34/365 -> 0 | E38: =-(E29-D29)*Inputs!$B$34/365 -> 0 | F38: =-(F29-E29)*Inputs!$B$34/365 -> 0 | G38: =-(G29-F29)*Inputs!$B$34/365 -> 0
A40: Prepaid compute roll-forward (cash paid ahead of use)
A41: Prepaid balance, opening | C41: 0 | D41: =C46 -> 0 | E41: =D46 -> 0 | F41: =E46 -> 0 | G41: =F46 -> 0
A42: Prepayment paid (start of year) | C42: 0 | D42: =Inputs!$C$92 -> 0 | E42: 0 | F42: 0 | G42: 0
A43: Scheduled credits available (cumulative scheduled less used) | C43: =MAX(0,0) -> 0 | D43: =MAX(0,0) -> 0 | E43: =MAX(0,$D$42/Inputs!$B$40*MIN(1,Inputs!$B$40)-SUM($C45:D45)) -> 0 | F43: =MAX(0,$D$42/Inputs!$B$40*MIN(2,Inputs!$B$40)-SUM($C45:E45)) -> 0 | G43: =MAX(0,$D$42/Inputs!$B$40*MIN(3,Inputs!$B$40)-SUM($C45:F45)) -> 0
A44: Eligible compute charges this year | C44: =C10*Inputs!$B$39 -> 26018.9 | D44: =D10*Inputs!$B$39 -> 44232.13 | E44: =E10*Inputs!$B$39 -> 64136.588 | F44: =F10*Inputs!$B$39 -> 83377.565 | G44: =G10*Inputs!$B$39 -> 100053.08
A45: Credits used (capped by balance, schedule and eligible charges) | C45: =MAX(0,MIN(C41+C42,C43,C44)) -> 0 | D45: =MAX(0,MIN(D41+D42,D43,D44)) -> 0 | E45: =MAX(0,MIN(E41+E42,E43,E44)) -> 0 | F45: =MAX(0,MIN(F41+F42,F43,F44)) -> 0 | G45: =MAX(0,MIN(G41+G42,G43,G44)) -> 0
A46: Prepaid balance, closing | C46: =C41+C42-C45 -> 0 | D46: =D41+D42-D45 -> 0 | E46: =E41+E42-E45 -> 0 | F46: =F41+F42-F45 -> 0 | G46: =G41+G42-G45 -> 0
A48: Core business (tokens + subscriptions): earnings, taxes, cash
A49: Revenue | C49: =C5 -> 54228 | D49: =D5 -> 108456 | E49: =E5 -> 168106.8 | F49: =F5 -> 226944.18 | G49: =G5 -> 283680.22
A50: Operating income before depreciation of new owned capacity | C50: =C17 -> 1681.5763 | D50: =D17 -> 21926.03 | E50: =E17 -> 43451.764 | F50: =F17 -> 68675.036 | G50: =G17 -> 92849.475
A51: Capital spending | C51: =C5*Inputs!B$55 -> 1626.84 | D51: =D5*Inputs!C$55 -> 4338.24 | E51: =E5*Inputs!D$55 -> 8405.34 | F51: =F5*Inputs!E$55 -> 11347.209 | G51: =G5*Inputs!F$55 -> 14184.011
A52: Depreciation of owned capacity bought from 2027 | C52: 0 | D52: =SUMPRODUCT($D51:D51,--((4-COLUMN($D51:D51))<Inputs!$B$32))/Inputs!$B$32 -> 867.648 | E52: =SUMPRODUCT($D51:E51,--((5-COLUMN($D51:E51))<Inputs!$B$32))/Inputs!$B$32 -> 2548.716 | F52: =SUMPRODUCT($D51:F51,--((6-COLUMN($D51:F51))<Inputs!$B$32))/Inputs!$B$32 -> 4818.1578 | G52: =SUMPRODUCT($D51:G51,--((7-COLUMN($D51:G51))<Inputs!$B$32))/Inputs!$B$32 -> 7654.96
A53: Operating income (earnings basis, after stock comp) | C53: =C50-C52 -> 1681.5763 | D53: =D50-D52 -> 21058.382 | E53: =E50-E52 -> 40903.048 | F53: =F50-F52 -> 63856.878 | G53: =G50-G52 -> 85194.515
A54: Operating margin | C54: =IFERROR(C53/C49,0) -> 0.031009374 | D54: =IFERROR(D53/D49,0) -> 0.19416521 | E54: =IFERROR(E53/E49,0) -> 0.24331584 | F54: =IFERROR(F53/F49,0) -> 0.28137702 | G54: =IFERROR(G53/G49,0) -> 0.30031884
A55: Interest income (on opening cash) | C55: =Historicals!F43+C80*Inputs!$B$20/2 -> 2756.6375 | D55: =MAX(0,D80-D81)*Inputs!$B$20 -> 3507.9478 | E55: =MAX(0,E80-E81)*Inputs!$B$20 -> 4159.6258 | F55: =MAX(0,F80-F81)*Inputs!$B$20 -> 5200.9641 | G55: =MAX(0,G80-G81)*Inputs!$B$20 -> 6739.8623
A56: Other taxable income adjustments | C56: =Inputs!B$56 -> 0 | D56: =Inputs!C$56 -> 0 | E56: =Inputs!D$56 -> 0 | F56: =Inputs!E$56 -> 0 | G56: =Inputs!F$56 -> 0
A57: IPO RSU tax deduction | C57: =IF(Inputs!$B$51=2026,Inputs!$B$50,0) -> 0 | D57: =IF(Inputs!$B$51=2027,Inputs!$B$50,0) -> 0 | E57: =IF(Inputs!$B$51=2028,Inputs!$B$50,0) -> 0 | F57: =IF(Inputs!$B$51=2029,Inputs!$B$50,0) -> 0 | G57: =IF(Inputs!$B$51=2030,Inputs!$B$50,0) -> 0
A58: Taxable income proxy | C58: =C53+C55+C56-C57 -> 4438.2138 | D58: =D53+D55+D56-D57 -> 24566.33 | E58: =E53+E55+E56-E57 -> 45062.673 | F58: =F53+F55+F56-F57 -> 69057.842 | G58: =G53+G55+G56-G57 -> 91934.377
A59: State taxable base (apportioned) | C59: =C58*Inputs!$B$46 -> 3195.514 | D59: =D58*Inputs!$B$46 -> 17687.757 | E59: =E58*Inputs!$B$46 -> 32445.125 | F59: =F58*Inputs!$B$46 -> 49721.646 | G59: =G58*Inputs!$B$46 -> 66192.752
A60: State NOL, opening | C60: =Inputs!$B$48 -> 4200 | D60: =C62 -> 4200 | E60: =D62 -> 0 | F60: =E62 -> 0 | G60: =F62 -> 0
A61: State NOL used | C61: =IF(AND(2026=2026,Inputs!$B$49=1),0,MIN(C60,MAX(0,C59))) -> 0 | D61: =IF(AND(2027=2026,Inputs!$B$49=1),0,MIN(D60,MAX(0,D59))) -> 4200 | E61: =IF(AND(2028=2026,Inputs!$B$49=1),0,MIN(E60,MAX(0,E59))) -> 0 | F61: =IF(AND(2029=2026,Inputs!$B$49=1),0,MIN(F60,MAX(0,F59))) -> 0 | G61: =IF(AND(2030=2026,Inputs!$B$49=1),0,MIN(G60,MAX(0,G59))) -> 0
A62: State NOL, closing | C62: =C60-C61+MAX(0,-C59) -> 4200 | D62: =D60-D61+MAX(0,-D59) -> 0 | E62: =E60-E61+MAX(0,-E59) -> 0 | F62: =F60-F61+MAX(0,-F59) -> 0 | G62: =G60-G61+MAX(0,-G59) -> 0
A63: State tax | C63: =MAX(0,C59-C61)*Inputs!$B$47 -> 191.73084 | D63: =MAX(0,D59-D61)*Inputs!$B$47 -> 809.26545 | E63: =MAX(0,E59-E61)*Inputs!$B$47 -> 1946.7075 | F63: =MAX(0,F59-F61)*Inputs!$B$47 -> 2983.2988 | G63: =MAX(0,G59-G61)*Inputs!$B$47 -> 3971.5651
A64: Federal taxable income before NOL (after state tax) | C64: =C58-C63 -> 4246.483 | D64: =D58-D63 -> 23757.064 | E64: =E58-E63 -> 43115.966 | F64: =F58-F63 -> 66074.543 | G64: =G58-G63 -> 87962.812
A65: Federal NOL, opening | C65: =Inputs!$B$44 -> 8200 | D65: =C67 -> 4802.8136 | E65: =D67 -> 0 | F65: =E67 -> 0 | G65: =F67 -> 0
A66: Federal NOL used (80% limit) | C66: =MIN(C65,Inputs!$B$45*MAX(0,C64)) -> 3397.1864 | D66: =MIN(D65,Inputs!$B$45*MAX(0,D64)) -> 4802.8136 | E66: =MIN(E65,Inputs!$B$45*MAX(0,E64)) -> 0 | F66: =MIN(F65,Inputs!$B$45*MAX(0,F64)) -> 0 | G66: =MIN(G65,Inputs!$B$45*MAX(0,G64)) -> 0
A67: Federal NOL, closing | C67: =C65-C66+MAX(0,-C64) -> 4802.8136 | D67: =D65-D66+MAX(0,-D64) -> 0 | E67: =E65-E66+MAX(0,-E64) -> 0 | F67: =F65-F66+MAX(0,-F64) -> 0 | G67: =G65-G66+MAX(0,-G64) -> 0
A68: Federal tax | C68: =MAX(0,C64-C66)*Inputs!$B$43 -> 178.35229 | D68: =MAX(0,D64-D66)*Inputs!$B$43 -> 3980.3926 | E68: =MAX(0,E64-E66)*Inputs!$B$43 -> 9054.3528 | F68: =MAX(0,F64-F66)*Inputs!$B$43 -> 13875.654 | G68: =MAX(0,G64-G66)*Inputs!$B$43 -> 18472.191
A69: Cash taxes (selected method) | C69: =IF(Inputs!$C$90=0,MAX(0,C53+C55)*Inputs!B$54,IF(Inputs!$C$90=2,MAX(0,C58)*Inputs!$C$91,C63+C68)) -> 370.08312 | D69: =IF(Inputs!$C$90=0,MAX(0,D53+D55)*Inputs!C$54,IF(Inputs!$C$90=2,MAX(0,D58)*Inputs!$C$91,D63+D68)) -> 4789.6581 | E69: =IF(Inputs!$C$90=0,MAX(0,E53+E55)*Inputs!D$54,IF(Inputs!$C$90=2,MAX(0,E58)*Inputs!$C$91,E63+E68)) -> 11001.06 | F69: =IF(Inputs!$C$90=0,MAX(0,F53+F55)*Inputs!E$54,IF(Inputs!$C$90=2,MAX(0,F58)*Inputs!$C$91,F63+F68)) -> 16858.953 | G69: =IF(Inputs!$C$90=0,MAX(0,G53+G55)*Inputs!F$54,IF(Inputs!$C$90=2,MAX(0,G58)*Inputs!$C$91,G63+G68)) -> 22443.756
A70: Effective tax rate on taxable income | C70: =IF(C58>0,MIN(1,C69/C58),0) -> 0.0833856 | D70: =IF(D58>0,MIN(1,D69/D58),0) -> 0.1949684 | E70: =IF(E58>0,MIN(1,E69/E58),0) -> 0.244128 | F70: =IF(F58>0,MIN(1,F69/F58),0) -> 0.244128 | G70: =IF(G58>0,MIN(1,G69/G58),0) -> 0.244128
A71: Net income excl. non-cash fair value items | C71: =C53+C55-C69 -> 4068.1307 | D71: =D53+D55-D69 -> 19776.672 | E71: =E53+E55-E69 -> 34061.613 | F71: =F53+F55-F69 -> 52198.889 | G71: =G53+G55-G69 -> 69490.622
A72: Non-cash stock comp & donation charges (added back for liquidity) | C72: =C12+C20 -> 8451.6198 | D72: =D12+D20 -> 9761.04 | E72: =E12+E20 -> 13448.544 | F72: =F12+F20 -> 15886.093 | G72: =G12+G20 -> 17020.814
A73: Working capital | C73: 0 | D73: =-(D5-C5)*Inputs!$B$33 -> 0 | E73: =-(E5-D5)*Inputs!$B$33 -> 0 | F73: =-(F5-E5)*Inputs!$B$33 -> 0 | G73: =-(G5-F5)*Inputs!$B$33 -> 0
A74: Compute prepayment timing (non-recurring; excluded from exit value) | C74: =-C$42+C$45 -> 0 | D74: =-D$42+D$45 -> 0 | E74: =-E$42+E$45 -> 0 | F74: =-F$42+F$45 -> 0 | G74: =-G$42+G$45 -> 0
A75: Actual cash flow (liquidity basis) | C75: =C53+C72+C52+C55-C69-C51+C73+C74 -> 10892.911 | D75: =D53+D72+D52+D55-D69-D51+D73+D74 -> 26067.12 | E75: =E53+E72+E52+E55-E69-E51+E73+E74 -> 41653.533 | F75: =F53+F72+F52+F55-F69-F51+F73+F74 -> 61555.93 | G75: =G53+G72+G52+G55-G69-G51+G73+G74 -> 79982.384
A76: Economic operating cash flow (valuation basis: after stock comp, excl. interest) | C76: =C53+C52-(C69-C55*C70)-C51+C73+C74 -> -85.482921 | D76: =D53+D52-(D69-D55*D70)-D51+D73+D74 -> 13482.071 | E76: =E53+E52-(E69-E55*E70)-E51+E73+E74 -> 25060.844 | F76: =F53+F52-(F69-F55*F70)-F51+F73+F74 -> 41738.575 | G76: =G53+G52-(G69-G55*G70)-G51+G73+G74 -> 57867.097
A77: Economic cash flow margin | C77: =IFERROR(C76/C49,0) -> -0.0015763613 | D77: =IFERROR(D76/D49,0) -> 0.12430913 | E77: =IFERROR(E76/E49,0) -> 0.14907692 | F77: =IFERROR(F76/F49,0) -> 0.1839156 | G77: =IFERROR(G76/G49,0) -> 0.20398707
A79: Cash roll-forward | C79: H2 2026 | D79: 2027E | E79: 2028E | F79: 2029E | G79: 2030E
A80: Opening cash | C80: =Inputs!$B$6 -> 131651 | D80: =C85 -> 140317.91 | E80: =D85 -> 166385.03 | F80: =E85 -> 208038.56 | G80: =F85 -> 269594.49
A81: of which paid at start of year (prepayment) | C81: =C$42 -> 0 | D81: =D$42 -> 0 | E81: =E$42 -> 0 | F81: =F$42 -> 0 | G81: =G$42 -> 0
A82: Cash flow in period (H2 only for 2026) | B82: 2026: full-year cash flow less H1 actual on the same basis | C82: =C75-Historicals!$B$79 -> 8666.9105 | D82: =D75 -> 26067.12 | E82: =E75 -> 41653.533 | F82: =F75 -> 61555.93 | G82: =G75 -> 79982.384
A83: RSU tax withholding paid | C83: =-Inputs!$B$17 -> 0 | D83: 0 | E83: 0 | F83: 0 | G83: 0
A84: Primary IPO proceeds | C84: =Inputs!$B$15 -> 0 | D84: 0 | E84: 0 | F84: 0 | G84: 0
A85: Closing cash | C85: =C80+C82+C83+C84 -> 140317.91 | D85: =D80+D82+D83+D84 -> 166385.03 | E85: =E80+E82+E83+E84 -> 208038.56 | F85: =F80+F82+F83+F84 -> 269594.49 | G85: =G80+G82+G83+G84 -> 349576.88
A86: Lowest cash in the year (start-of-year payments or year end) | C86: =MIN(C80-C81,C85) -> 131651 | D86: =MIN(D80-D81,D85) -> 140317.91 | E86: =MIN(E80-E81,E85) -> 166385.03 | F86: =MIN(F80-F81,F85) -> 208038.56 | G86: =MIN(G80-G81,G85) -> 269594.49
A87: Lowest cash above the shortfall threshold | C87: =C86-Inputs!$B$29 -> 126651 | D87: =D86-Inputs!$B$29 -> 135317.91 | E87: =E86-Inputs!$B$29 -> 161385.03 | F87: =F86-Inputs!$B$29 -> 203038.56 | G87: =G86-Inputs!$B$29 -> 264594.49
A88: Year-end cash vs $5B covenant (cash proxy) | C88: =IF(C85<Inputs!$B$38,"Below","OK") -> OK | D88: =IF(D85<Inputs!$B$38,"Below","OK") -> OK | E88: =IF(E85<Inputs!$B$38,"Below","OK") -> OK | F88: =IF(F85<Inputs!$B$38,"Below","OK") -> OK | G88: =IF(G85<Inputs!$B$38,"Below","OK") -> OK
A89: Funding status | C89: =IF(C87<0,"Shortfall","OK") -> OK | D89: =IF(D87<0,"Shortfall","OK") -> OK | E89: =IF(E87<0,"Shortfall","OK") -> OK | F89: =IF(F87<0,"Shortfall","OK") -> OK | G89: =IF(G87<0,"Shortfall","OK") -> OK
A90: Peak funding need (intra-year) | G90: =MAX(0,-MIN(C87:G87)) -> 0
A91: Sensitivity: peak funding need with a $0 buffer | G91: =MAX(0,-MIN(C86:G86)) -> 0
A92: Funded cash path (illustrative equity raise) | C92: H2 2026 | D92: 2027E | E92: 2028E | F92: 2029E | G92: 2030E
A93: Financing year (start of the first shortfall year; proceeds arrive with the payment) | G93: =IF(G90=0,"none",IFERROR(2025+MATCH(1,INDEX(--(C87:G87<0),0),0),"none")) -> none
A94: Net proceeds needed (covers peak need) | G94: =G90 -> 0
A95: Issuance fees | G95: =G94/(1-Inputs!$B$31)*Inputs!$B$31 -> 0
A96: Gross amount raised | G96: =G94+G95 -> 0
A97: Net proceeds received in year | C97: =IF(AND(ISNUMBER($G$93),$G$93=2026),$G$94,0) -> 0 | D97: =IF(AND(ISNUMBER($G$93),$G$93=2027),$G$94,0) -> 0 | E97: =IF(AND(ISNUMBER($G$93),$G$93=2028),$G$94,0) -> 0 | F97: =IF(AND(ISNUMBER($G$93),$G$93=2029),$G$94,0) -> 0 | G97: =IF(AND(ISNUMBER($G$93),$G$93=2030),$G$94,0) -> 0
A98: Interest change vs. unfunded path (funded balance after start-of-year payments) | C98: =C97*Inputs!$B$20/2 -> 0 | D98: =MAX(0,C100-D81+D97)*Inputs!$B$20-D55 -> 0 | E98: =MAX(0,D100-E81+E97)*Inputs!$B$20-E55 -> 0 | F98: =MAX(0,E100-F81+F97)*Inputs!$B$20-F55 -> 0 | G98: =MAX(0,F100-G81+G97)*Inputs!$B$20-G55 -> 0
A99: Extra tax on that interest | C99: =C98*C70 -> 0 | D99: =D98*D70 -> 0 | E99: =E98*E70 -> 0 | F99: =F98*F70 -> 0 | G99: =G98*G70 -> 0
A100: Closing cash — funded | C100: =C85+SUM($C97:C97)+SUM($C98:C98)-SUM($C99:C99) -> 140317.91 | D100: =D85+SUM($C97:D97)+SUM($C98:D98)-SUM($C99:D99) -> 166385.03 | E100: =E85+SUM($C97:E97)+SUM($C98:E98)-SUM($C99:E99) -> 208038.56 | F100: =F85+SUM($C97:F97)+SUM($C98:F98)-SUM($C99:F99) -> 269594.49 | G100: =G85+SUM($C97:G97)+SUM($C98:G98)-SUM($C99:G99) -> 349576.88
A101: Lowest cash in the year — funded | C101: =MIN(C80-C81+0+C97,C100) -> 131651 | D101: =MIN(D80-D81+SUM($C97:C97)+SUM($C98:C98)-SUM($C99:C99)+D97,D100) -> 140317.91 | E101: =MIN(E80-E81+SUM($C97:D97)+SUM($C98:D98)-SUM($C99:D99)+E97,E100) -> 166385.03 | F101: =MIN(F80-F81+SUM($C97:E97)+SUM($C98:E98)-SUM($C99:E99)+F97,F100) -> 208038.56 | G101: =MIN(G80-G81+SUM($C97:F97)+SUM($C98:F98)-SUM($C99:F99)+G97,G100) -> 269594.49
A102: Funded path stays above threshold? | C102: =IF(C101-Inputs!$B$29<-0.5,"No","Yes") -> Yes | D102: =IF(D101-Inputs!$B$29<-0.5,"No","Yes") -> Yes | E102: =IF(E101-Inputs!$B$29<-0.5,"No","Yes") -> Yes | F102: =IF(F101-Inputs!$B$29<-0.5,"No","Yes") -> Yes | G102: =IF(G101-Inputs!$B$29<-0.5,"No","Yes") -> Yes
A104: Hybrid company (core + value-share): earnings, taxes, cash
A105: Revenue | C105: =C5+C31 -> 54228 | D105: =D5+D31 -> 110408.21 | E105: =E5+E31 -> 175671.61 | F105: =F5+F31 -> 247369.16 | G105: =G5+G31 -> 321977.06
A106: Operating income before depreciation of new owned capacity | C106: =C17+C35 -> 1681.5763 | D106: =D17+D35 -> 22706.913 | E106: =E17+E35 -> 46477.686 | F106: =F17+F35 -> 76845.026 | G106: =G17+G35 -> 108168.21
A107: Capital spending | C107: =C51+C37 -> 1626.84 | D107: =D51+D37 -> 4416.3283 | E107: =E51+E37 -> 8783.5803 | F107: =F51+F37 -> 12368.458 | G107: =G51+G37 -> 16098.853
...

Sheet Bull
A1: Bull — projections, cash and valuation ($ millions except per share)
A2: 2026E = H1 2026 actual + Q3 2026 implied + assumed Q4. Compute is forecast as cash spending (hosting, leases and owned capacity all treated as paid when expensed); the S-1 gives no payment schedule.
A4: Core business: income statement | B4: 2025A | C4: 2026E | D4: 2027E | E4: 2028E | F4: 2029E | G4: 2030E
A5: Revenue | B5: =Historicals!D35 -> 4585 | C5: =Historicals!F35+(Inputs!$B$5+Inputs!$D$60) -> 57228 | D5: =C5*(1+Inputs!$D$62) -> 143070 | E5: =D5*(1+Inputs!$D$63) -> 257526 | F5: =E5*(1+Inputs!$D$64) -> 386289 | G5: =F5*(1+Inputs!$D$65) -> 521490.15
A6: Growth | C6: =IFERROR(C5/B5-1,0) -> 11.48157 | D6: =IFERROR(D5/C5-1,0) -> 1.5 | E6: =IFERROR(E5/D5-1,0) -> 0.8 | F6: =IFERROR(F5/E5-1,0) -> 0.5 | G6: =IFERROR(G5/F5-1,0) -> 0.35
A7: Subscription revenue | B7: =Historicals!D51 -> 789 | C7: =Historicals!F51+(Inputs!$B$5+Inputs!$D$60)*Historicals!F51/Historicals!F35 -> 11321.909 | D7: =D5*Inputs!$D$61 -> 25752.6 | E7: =E5*Inputs!$D$61 -> 46354.68 | F7: =F5*Inputs!$D$61 -> 69532.02 | G7: =G5*Inputs!$D$61 -> 93868.227
A8: Consumption revenue | B8: =B5-B7 -> 3796 | C8: =C5-C7 -> 45906.091 | D8: =D5-D7 -> 117317.4 | E8: =E5-E7 -> 211171.32 | F8: =F5-F7 -> 316756.98 | G8: =G5-G7 -> 427621.92
A10: Compute and infrastructure | B10: =Historicals!D36 -> 7326 | C10: =Historicals!F36+(Inputs!$B$5+Inputs!$D$60)*Inputs!$D$66 -> 26140.64 | D10: =C10*(1+Inputs!$D$67) -> 49667.216 | E10: =D10*(1+Inputs!$D$68) -> 79467.546 | F10: =E10*(1+Inputs!$D$69) -> 115227.94 | G10: =F10*(1+Inputs!$D$70) -> 149796.32
A11: Personnel (incl. stock comp) | B11: =Historicals!D37 -> 1839 | C11: =Historicals!F37+(Inputs!$B$5+Inputs!$D$60)*Historicals!G24 -> 9731.7745 | D11: =D5*Inputs!$D$71 -> 18599.1 | E11: =E5*Inputs!$D$72 -> 30903.12 | F11: =F5*Inputs!$D$73 -> 42491.79 | G11: =G5*Inputs!$D$74 -> 52149.015
A12: of which stock comp | B12: =Historicals!D49 -> 1158 | C12: =Historicals!F49+(Inputs!$B$5+Inputs!$D$60)*Historicals!G29 -> 6653.0106 | D12: =D5*Inputs!$D$75 -> 11445.6 | E12: =E5*Inputs!$D$76 -> 18026.82 | F12: =F5*Inputs!$D$77 -> 23177.34 | G12: =G5*Inputs!$D$78 -> 26074.507
A13: Sales, marketing & partner fees | B13: =Historicals!D39 -> 568 | C13: =Historicals!F39+(Inputs!$B$5+Inputs!$D$60)*Historicals!G25 -> 10732.792 | D13: =D5*Inputs!$D$79 -> 22891.2 | E13: =E5*Inputs!$D$80 -> 38628.9 | F13: =F5*Inputs!$D$81 -> 54080.46 | G13: =G5*Inputs!$D$82 -> 67793.72
A14: Other operating & administrative | B14: =Historicals!D40 -> 1412 | C14: =Historicals!F40+(Inputs!$B$5+Inputs!$D$60)*Historicals!G26 -> 5367.0681 | D14: =D5*Inputs!$D$83 -> 10014.9 | E14: =E5*Inputs!$D$84 -> 15451.56 | F14: =F5*Inputs!$D$85 -> 19314.45 | G14: =G5*Inputs!$D$86 -> 26074.507
A15: One-time items (2025 Bartz settlement; 2026 Q3 donation-matching charge) | B15: =Historicals!D38 -> 1500 | C15: =Inputs!$B$37 -> 2000 | D15: 0 | E15: 0 | F15: 0 | G15: 0
A16: Total operating expenses | B16: =B10+B11+B13+B14+B15 -> 12645 | C16: =C10+C11+C13+C14+C15 -> 53972.274 | D16: =D10+D11+D13+D14+D15 -> 101172.42 | E16: =E10+E11+E13+E14+E15 -> 164451.13 | F16: =F10+F11+F13+F14+F15 -> 231114.64 | G16: =G10+G11+G13+G14+G15 -> 295813.57
A17: Operating income before depreciation of new owned capacity | B17: =B5-B16 -> -8060 | C17: =C5-C16 -> 3255.7256 | D17: =D5-D16 -> 41897.584 | E17: =E5-E16 -> 93074.874 | F17: =F5-F16 -> 155174.36 | G17: =G5-G16 -> 225676.58
A18: Margin | B18: =IFERROR(B17/B5,0) -> -1.7579062 | C18: =IFERROR(C17/C5,0) -> 0.05689043 | D18: =IFERROR(D17/D5,0) -> 0.29284675 | E18: =IFERROR(E17/E5,0) -> 0.36141933 | F18: =IFERROR(F17/F5,0) -> 0.40170535 | G18: =IFERROR(G17/G5,0) -> 0.4327533
A19: Compute % of revenue | B19: =IFERROR(B10/B5,0) -> 1.597819 | C19: =IFERROR(C10/C5,0) -> 0.4567806 | D19: =IFERROR(D10/D5,0) -> 0.34715325 | E19: =IFERROR(E10/E5,0) -> 0.30858067 | F19: =IFERROR(F10/F5,0) -> 0.29829465 | G19: =IFERROR(G10/G5,0) -> 0.2872467
A20: Non-cash donation-matching charges (incl. in costs above) | C20: =Historicals!$B$78+Inputs!$B$37 -> 2126 | D20: 0 | E20: 0 | F20: 0 | G20: 0
A21: Discount factor to end 2026 | D21: =1/(1+Inputs!$B$19+Inputs!$D$89)^1 -> 0.89285714 | E21: =1/(1+Inputs!$B$19+Inputs!$D$89)^2 -> 0.79719388 | F21: =1/(1+Inputs!$B$19+Inputs!$D$89)^3 -> 0.71178025 | G21: =1/(1+Inputs!$B$19+Inputs!$D$89)^4 -> 0.63551808
A23: Third business line: value-share partnerships (hypothetical)
A24: Share of core revenue base under value-share | C24: 0 | D24: =Inputs!$D$97 -> 0.04 | E24: =Inputs!$D$98 -> 0.1 | F24: =Inputs!$D$99 -> 0.18 | G24: =Inputs!$D$100 -> 0.25
A25: Revenue base moved to value-share | C25: =C5*C24 -> 0 | D25: =D5*D24 -> 5722.8 | E25: =E5*E24 -> 25752.6 | F25: =F5*F24 -> 69532.02 | G25: =G5*G24 -> 130372.54
A26: Value created per $1 of Claude spend | C26: =Inputs!$D$101 -> 12 | D26: =Inputs!$D$101 -> 12 | E26: =Inputs!$D$101 -> 12 | F26: =Inputs!$D$101 -> 12 | G26: =Inputs!$D$101 -> 12
A27: Economic value created for partners | C27: =C25*C26 -> 0 | D27: =D25*D26 -> 68673.6 | E27: =E25*E26 -> 309031.2 | F27: =F25*F26 -> 834384.24 | G27: =G25*G26 -> 1564470.4
A28: Anthropic's cut | C28: =Inputs!$D$102 -> 0.2 | D28: =Inputs!$D$102 -> 0.2 | E28: =Inputs!$D$102 -> 0.2 | F28: =Inputs!$D$102 -> 0.2 | G28: =Inputs!$D$102 -> 0.2
A29: Value-share revenue (gross) | C29: =C27*C28 -> 0 | D29: =D27*D28 -> 13734.72 | E29: =E27*E28 -> 61806.24 | F29: =F27*F28 -> 166876.85 | G29: =G27*G28 -> 312894.09
A30: Token revenue given up | C30: =C25*Inputs!$D$103 -> 0 | D30: =D25*Inputs!$D$103 -> 1144.56 | E30: =E25*Inputs!$D$103 -> 5150.52 | F30: =F25*Inputs!$D$103 -> 13906.404 | G30: =G25*Inputs!$D$103 -> 26074.507
A31: Net new revenue | C31: =C29-C30 -> 0 | D31: =D29-D30 -> 12590.16 | E31: =E29-E30 -> 56655.72 | F31: =F29-F30 -> 152970.44 | G31: =G29-G30 -> 286819.58
A32: Delivery cost | C32: =C29*Inputs!$D$104 -> 0 | D32: =D29*Inputs!$D$104 -> 2060.208 | E32: =E29*Inputs!$D$104 -> 9270.936 | F32: =F29*Inputs!$D$104 -> 25031.527 | G32: =G29*Inputs!$D$104 -> 46934.113
A33: Extra compute | C33: =C29*Inputs!$D$105 -> 0 | D33: =D29*Inputs!$D$105 -> 1373.472 | E33: =E29*Inputs!$D$105 -> 6180.624 | F33: =F29*Inputs!$D$105 -> 16687.685 | G33: =G29*Inputs!$D$105 -> 31289.409
A34: Selling, partner fees & overhead | C34: =C29*Inputs!$D$106 -> 0 | D34: =D29*Inputs!$D$106 -> 1098.7776 | E34: =E29*Inputs!$D$106 -> 4944.4992 | F34: =F29*Inputs!$D$106 -> 13350.148 | G34: =G29*Inputs!$D$106 -> 25031.527
A35: Value-share operating contribution | C35: =C29-C30-C32-C33-C34 -> 0 | D35: =D29-D30-D32-D33-D34 -> 8057.7024 | E35: =E29-E30-E32-E33-E34 -> 36259.661 | F35: =F29-F30-F32-F33-F34 -> 97901.084 | G35: =G29-G30-G32-G33-G34 -> 183564.53
A36: Value created as % of $40T knowledge-work pool | C36: =IFERROR(C27/Inputs!$B$27,0) -> 0 | D36: =IFERROR(D27/Inputs!$B$27,0) -> 0.00171684 | E36: =IFERROR(E27/Inputs!$B$27,0) -> 0.00772578 | F36: =IFERROR(F27/Inputs!$B$27,0) -> 0.020859606 | G36: =IFERROR(G27/Inputs!$B$27,0) -> 0.039111761
A37: Value-share capital spending (per selected basis) | C37: =CHOOSE(Inputs!$B$35,C31*Inputs!B$55,C29*Inputs!$B$36,0) -> 0 | D37: =CHOOSE(Inputs!$B$35,D31*Inputs!C$55,D29*Inputs!$B$36,0) -> 503.6064 | E37: =CHOOSE(Inputs!$B$35,E31*Inputs!D$55,E29*Inputs!$B$36,0) -> 2832.786 | F37: =CHOOSE(Inputs!$B$35,F31*Inputs!E$55,F29*Inputs!$B$36,0) -> 7648.5222 | G37: =CHOOSE(Inputs!$B$35,G31*Inputs!F$55,G29*Inputs!$B$36,0) -> 14340.979
A38: Value-share collection timing (working capital) | C38: 0 | D38: =-(D29-C29)*Inputs!$B$34/365 -> 0 | E38: =-(E29-D29)*Inputs!$B$34/365 -> 0 | F38: =-(F29-E29)*Inputs!$B$34/365 -> 0 | G38: =-(G29-F29)*Inputs!$B$34/365 -> 0
A40: Prepaid compute roll-forward (cash paid ahead of use)
A41: Prepaid balance, opening | C41: 0 | D41: =C46 -> 0 | E41: =D46 -> 0 | F41: =E46 -> 0 | G41: =F46 -> 0
A42: Prepayment paid (start of year) | C42: 0 | D42: =Inputs!$D$92 -> 0 | E42: 0 | F42: 0 | G42: 0
A43: Scheduled credits available (cumulative scheduled less used) | C43: =MAX(0,0) -> 0 | D43: =MAX(0,0) -> 0 | E43: =MAX(0,$D$42/Inputs!$B$40*MIN(1,Inputs!$B$40)-SUM($C45:D45)) -> 0 | F43: =MAX(0,$D$42/Inputs!$B$40*MIN(2,Inputs!$B$40)-SUM($C45:E45)) -> 0 | G43: =MAX(0,$D$42/Inputs!$B$40*MIN(3,Inputs!$B$40)-SUM($C45:F45)) -> 0
A44: Eligible compute charges this year | C44: =C10*Inputs!$B$39 -> 26140.64 | D44: =D10*Inputs!$B$39 -> 49667.216 | E44: =E10*Inputs!$B$39 -> 79467.546 | F44: =F10*Inputs!$B$39 -> 115227.94 | G44: =G10*Inputs!$B$39 -> 149796.32
A45: Credits used (capped by balance, schedule and eligible charges) | C45: =MAX(0,MIN(C41+C42,C43,C44)) -> 0 | D45: =MAX(0,MIN(D41+D42,D43,D44)) -> 0 | E45: =MAX(0,MIN(E41+E42,E43,E44)) -> 0 | F45: =MAX(0,MIN(F41+F42,F43,F44)) -> 0 | G45: =MAX(0,MIN(G41+G42,G43,G44)) -> 0
A46: Prepaid balance, closing | C46: =C41+C42-C45 -> 0 | D46: =D41+D42-D45 -> 0 | E46: =E41+E42-E45 -> 0 | F46: =F41+F42-F45 -> 0 | G46: =G41+G42-G45 -> 0
A48: Core business (tokens + subscriptions): earnings, taxes, cash
A49: Revenue | C49: =C5 -> 57228 | D49: =D5 -> 143070 | E49: =E5 -> 257526 | F49: =F5 -> 386289 | G49: =G5 -> 521490.15
A50: Operating income before depreciation of new owned capacity | C50: =C17 -> 3255.7256 | D50: =D17 -> 41897.584 | E50: =E17 -> 93074.874 | F50: =F17 -> 155174.36 | G50: =G17 -> 225676.58
A51: Capital spending | C51: =C5*Inputs!B$55 -> 1716.84 | D51: =D5*Inputs!C$55 -> 5722.8 | E51: =E5*Inputs!D$55 -> 12876.3 | F51: =F5*Inputs!E$55 -> 19314.45 | G51: =G5*Inputs!F$55 -> 26074.507
A52: Depreciation of owned capacity bought from 2027 | C52: 0 | D52: =SUMPRODUCT($D51:D51,--((4-COLUMN($D51:D51))<Inputs!$B$32))/Inputs!$B$32 -> 1144.56 | E52: =SUMPRODUCT($D51:E51,--((5-COLUMN($D51:E51))<Inputs!$B$32))/Inputs!$B$32 -> 3719.82 | F52: =SUMPRODUCT($D51:F51,--((6-COLUMN($D51:F51))<Inputs!$B$32))/Inputs!$B$32 -> 7582.71 | G52: =SUMPRODUCT($D51:G51,--((7-COLUMN($D51:G51))<Inputs!$B$32))/Inputs!$B$32 -> 12797.612
A53: Operating income (earnings basis, after stock comp) | C53: =C50-C52 -> 3255.7256 | D53: =D50-D52 -> 40753.024 | E53: =E50-E52 -> 89355.054 | F53: =F50-F52 -> 147591.65 | G53: =G50-G52 -> 212878.97
A54: Operating margin | C54: =IFERROR(C53/C49,0) -> 0.05689043 | D54: =IFERROR(D53/D49,0) -> 0.28484675 | E54: =IFERROR(E53/E49,0) -> 0.34697489 | F54: =IFERROR(F53/F49,0) -> 0.38207572 | G54: =IFERROR(G53/G49,0) -> 0.40821284
A55: Interest income (on opening cash) | C55: =Historicals!F43+C80*Inputs!$B$20/2 -> 2756.6375 | D55: =MAX(0,D80-D81)*Inputs!$B$20 -> 3549.9547 | E55: =MAX(0,E80-E81)*Inputs!$B$20 -> 4582.6892 | F55: =MAX(0,F80-F81)*Inputs!$B$20 -> 6579.5705 | G55: =MAX(0,G80-G81)*Inputs!$B$20 -> 9779.0532
A56: Other taxable income adjustments | C56: =Inputs!B$56 -> 0 | D56: =Inputs!C$56 -> 0 | E56: =Inputs!D$56 -> 0 | F56: =Inputs!E$56 -> 0 | G56: =Inputs!F$56 -> 0
A57: IPO RSU tax deduction | C57: =IF(Inputs!$B$51=2026,Inputs!$B$50,0) -> 0 | D57: =IF(Inputs!$B$51=2027,Inputs!$B$50,0) -> 0 | E57: =IF(Inputs!$B$51=2028,Inputs!$B$50,0) -> 0 | F57: =IF(Inputs!$B$51=2029,Inputs!$B$50,0) -> 0 | G57: =IF(Inputs!$B$51=2030,Inputs!$B$50,0) -> 0
A58: Taxable income proxy | C58: =C53+C55+C56-C57 -> 6012.3631 | D58: =D53+D55+D56-D57 -> 44302.979 | E58: =E53+E55+E56-E57 -> 93937.744 | F58: =F53+F55+F56-F57 -> 154171.22 | G58: =G53+G55+G56-G57 -> 222658.03
A59: State taxable base (apportioned) | C59: =C58*Inputs!$B$46 -> 4328.9014 | D59: =D58*Inputs!$B$46 -> 31898.145 | E59: =E58*Inputs!$B$46 -> 67635.175 | F59: =F58*Inputs!$B$46 -> 111003.28 | G59: =G58*Inputs!$B$46 -> 160313.78
A60: State NOL, opening | C60: =Inputs!$B$48 -> 4200 | D60: =C62 -> 4200 | E60: =D62 -> 0 | F60: =E62 -> 0 | G60: =F62 -> 0
A61: State NOL used | C61: =IF(AND(2026=2026,Inputs!$B$49=1),0,MIN(C60,MAX(0,C59))) -> 0 | D61: =IF(AND(2027=2026,Inputs!$B$49=1),0,MIN(D60,MAX(0,D59))) -> 4200 | E61: =IF(AND(2028=2026,Inputs!$B$49=1),0,MIN(E60,MAX(0,E59))) -> 0 | F61: =IF(AND(2029=2026,Inputs!$B$49=1),0,MIN(F60,MAX(0,F59))) -> 0 | G61: =IF(AND(2030=2026,Inputs!$B$49=1),0,MIN(G60,MAX(0,G59))) -> 0
A62: State NOL, closing | C62: =C60-C61+MAX(0,-C59) -> 4200 | D62: =D60-D61+MAX(0,-D59) -> 0 | E62: =E60-E61+MAX(0,-E59) -> 0 | F62: =F60-F61+MAX(0,-F59) -> 0 | G62: =G60-G61+MAX(0,-G59) -> 0
A63: State tax | C63: =MAX(0,C59-C61)*Inputs!$B$47 -> 259.73408 | D63: =MAX(0,D59-D61)*Inputs!$B$47 -> 1661.8887 | E63: =MAX(0,E59-E61)*Inputs!$B$47 -> 4058.1105 | F63: =MAX(0,F59-F61)*Inputs!$B$47 -> 6660.1967 | G63: =MAX(0,G59-G61)*Inputs!$B$47 -> 9618.8267
A64: Federal taxable income before NOL (after state tax) | C64: =C58-C63 -> 5752.629 | D64: =D58-D63 -> 42641.09 | E64: =E58-E63 -> 89879.633 | F64: =F58-F63 -> 147511.02 | G64: =G58-G63 -> 213039.2
A65: Federal NOL, opening | C65: =Inputs!$B$44 -> 8200 | D65: =C67 -> 3597.8968 | E65: =D67 -> 0 | F65: =E67 -> 0 | G65: =F67 -> 0
A66: Federal NOL used (80% limit) | C66: =MIN(C65,Inputs!$B$45*MAX(0,C64)) -> 4602.1032 | D66: =MIN(D65,Inputs!$B$45*MAX(0,D64)) -> 3597.8968 | E66: =MIN(E65,Inputs!$B$45*MAX(0,E64)) -> 0 | F66: =MIN(F65,Inputs!$B$45*MAX(0,F64)) -> 0 | G66: =MIN(G65,Inputs!$B$45*MAX(0,G64)) -> 0
A67: Federal NOL, closing | C67: =C65-C66+MAX(0,-C64) -> 3597.8968 | D67: =D65-D66+MAX(0,-D64) -> 0 | E67: =E65-E66+MAX(0,-E64) -> 0 | F67: =F65-F66+MAX(0,-F64) -> 0 | G67: =G65-G66+MAX(0,-G64) -> 0
A68: Federal tax | C68: =MAX(0,C64-C66)*Inputs!$B$43 -> 241.61042 | D68: =MAX(0,D64-D66)*Inputs!$B$43 -> 8199.0706 | E68: =MAX(0,E64-E66)*Inputs!$B$43 -> 18874.723 | F68: =MAX(0,F64-F66)*Inputs!$B$43 -> 30977.315 | G68: =MAX(0,G64-G66)*Inputs!$B$43 -> 44738.232
A69: Cash taxes (selected method) | C69: =IF(Inputs!$D$90=0,MAX(0,C53+C55)*Inputs!B$54,IF(Inputs!$D$90=2,MAX(0,C58)*Inputs!$D$91,C63+C68)) -> 501.3445 | D69: =IF(Inputs!$D$90=0,MAX(0,D53+D55)*Inputs!C$54,IF(Inputs!$D$90=2,MAX(0,D58)*Inputs!$D$91,D63+D68)) -> 9860.9593 | E69: =IF(Inputs!$D$90=0,MAX(0,E53+E55)*Inputs!D$54,IF(Inputs!$D$90=2,MAX(0,E58)*Inputs!$D$91,E63+E68)) -> 22932.833 | F69: =IF(Inputs!$D$90=0,MAX(0,F53+F55)*Inputs!E$54,IF(Inputs!$D$90=2,MAX(0,F58)*Inputs!$D$91,F63+F68)) -> 37637.511 | G69: =IF(Inputs!$D$90=0,MAX(0,G53+G55)*Inputs!F$54,IF(Inputs!$D$90=2,MAX(0,G58)*Inputs!$D$91,G63+G68)) -> 54357.059
A70: Effective tax rate on taxable income | C70: =IF(C58>0,MIN(1,C69/C58),0) -> 0.0833856 | D70: =IF(D58>0,MIN(1,D69/D58),0) -> 0.22258005 | E70: =IF(E58>0,MIN(1,E69/E58),0) -> 0.244128 | F70: =IF(F58>0,MIN(1,F69/F58),0) -> 0.244128 | G70: =IF(G58>0,MIN(1,G69/G58),0) -> 0.244128
A71: Net income excl. non-cash fair value items | C71: =C53+C55-C69 -> 5511.0186 | D71: =D53+D55-D69 -> 34442.019 | E71: =E53+E55-E69 -> 71004.91 | F71: =F53+F55-F69 -> 116533.71 | G71: =G53+G55-G69 -> 168300.97
A72: Non-cash stock comp & donation charges (added back for liquidity) | C72: =C12+C20 -> 8779.0106 | D72: =D12+D20 -> 11445.6 | E72: =E12+E20 -> 18026.82 | F72: =F12+F20 -> 23177.34 | G72: =G12+G20 -> 26074.507
A73: Working capital | C73: 0 | D73: =-(D5-C5)*Inputs!$B$33 -> 0 | E73: =-(E5-D5)*Inputs!$B$33 -> 0 | F73: =-(F5-E5)*Inputs!$B$33 -> 0 | G73: =-(G5-F5)*Inputs!$B$33 -> 0
A74: Compute prepayment timing (non-recurring; excluded from exit value) | C74: =-C$42+C$45 -> 0 | D74: =-D$42+D$45 -> 0 | E74: =-E$42+E$45 -> 0 | F74: =-F$42+F$45 -> 0 | G74: =-G$42+G$45 -> 0
A75: Actual cash flow (liquidity basis) | C75: =C53+C72+C52+C55-C69-C51+C73+C74 -> 12573.189 | D75: =D53+D72+D52+D55-D69-D51+D73+D74 -> 41309.379 | E75: =E53+E72+E52+E55-E69-E51+E73+E74 -> 79875.25 | F75: =F53+F72+F52+F55-F69-F51+F73+F74 -> 127979.31 | G75: =G53+G72+G52+G55-G69-G51+G73+G74 -> 181098.58
A76: Economic operating cash flow (valuation basis: after stock comp, excl. interest) | C76: =C53+C52-(C69-C55*C70)-C51+C73+C74 -> 1267.4049 | D76: =D53+D52-(D69-D55*D70)-D51+D73+D74 -> 27103.974 | E76: =E53+E52-(E69-E55*E70)-E51+E73+E74 -> 58384.504 | F76: =F53+F52-(F69-F55*F70)-F51+F73+F74 -> 99828.655 | G76: =G53+G52-(G69-G55*G70)-G51+G73+G74 -> 147632.36
A77: Economic cash flow margin | C77: =IFERROR(C76/C49,0) -> 0.022146588 | D77: =IFERROR(D76/D49,0) -> 0.18944554 | E77: =IFERROR(E76/E49,0) -> 0.22671305 | F77: =IFERROR(F76/F49,0) -> 0.25842997 | G77: =IFERROR(G76/G49,0) -> 0.28309712
A79: Cash roll-forward | C79: H2 2026 | D79: 2027E | E79: 2028E | F79: 2029E | G79: 2030E
A80: Opening cash | C80: =Inputs!$B$6 -> 131651 | D80: =C85 -> 141998.19 | E80: =D85 -> 183307.57 | F80: =E85 -> 263182.82 | G80: =F85 -> 391162.13
A81: of which paid at start of year (prepayment) | C81: =C$42 -> 0 | D81: =D$42 -> 0 | E81: =E$42 -> 0 | F81: =F$42 -> 0 | G81: =G$42 -> 0
A82: Cash flow in period (H2 only for 2026) | B82: 2026: full-year cash flow less H1 actual on the same basis | C82: =C75-Historicals!$B$79 -> 10347.189 | D82: =D75 -> 41309.379 | E82: =E75 -> 79875.25 | F82: =F75 -> 127979.31 | G82: =G75 -> 181098.58
A83: RSU tax withholding paid | C83: =-Inputs!$B$17 -> 0 | D83: 0 | E83: 0 | F83: 0 | G83: 0
A84: Primary IPO proceeds | C84: =Inputs!$B$15 -> 0 | D84: 0 | E84: 0 | F84: 0 | G84: 0
A85: Closing cash | C85: =C80+C82+C83+C84 -> 141998.19 | D85: =D80+D82+D83+D84 -> 183307.57 | E85: =E80+E82+E83+E84 -> 263182.82 | F85: =F80+F82+F83+F84 -> 391162.13 | G85: =G80+G82+G83+G84 -> 572260.71
A86: Lowest cash in the year (start-of-year payments or year end) | C86: =MIN(C80-C81,C85) -> 131651 | D86: =MIN(D80-D81,D85) -> 141998.19 | E86: =MIN(E80-E81,E85) -> 183307.57 | F86: =MIN(F80-F81,F85) -> 263182.82 | G86: =MIN(G80-G81,G85) -> 391162.13
A87: Lowest cash above the shortfall threshold | C87: =C86-Inputs!$B$29 -> 126651 | D87: =D86-Inputs!$B$29 -> 136998.19 | E87: =E86-Inputs!$B$29 -> 178307.57 | F87: =F86-Inputs!$B$29 -> 258182.82 | G87: =G86-Inputs!$B$29 -> 386162.13
A88: Year-end cash vs $5B covenant (cash proxy) | C88: =IF(C85<Inputs!$B$38,"Below","OK") -> OK | D88: =IF(D85<Inputs!$B$38,"Below","OK") -> OK | E88: =IF(E85<Inputs!$B$38,"Below","OK") -> OK | F88: =IF(F85<Inputs!$B$38,"Below","OK") -> OK | G88: =IF(G85<Inputs!$B$38,"Below","OK") -> OK
A89: Funding status | C89: =IF(C87<0,"Shortfall","OK") -> OK | D89: =IF(D87<0,"Shortfall","OK") -> OK | E89: =IF(E87<0,"Shortfall","OK") -> OK | F89: =IF(F87<0,"Shortfall","OK") -> OK | G89: =IF(G87<0,"Shortfall","OK") -> OK
A90: Peak funding need (intra-year) | G90: =MAX(0,-MIN(C87:G87)) -> 0
A91: Sensitivity: peak funding need with a $0 buffer | G91: =MAX(0,-MIN(C86:G86)) -> 0
A92: Funded cash path (illustrative equity raise) | C92: H2 2026 | D92: 2027E | E92: 2028E | F92: 2029E | G92: 2030E
A93: Financing year (start of the first shortfall year; proceeds arrive with the payment) | G93: =IF(G90=0,"none",IFERROR(2025+MATCH(1,INDEX(--(C87:G87<0),0),0),"none")) -> none
A94: Net proceeds needed (covers peak need) | G94: =G90 -> 0
A95: Issuance fees | G95: =G94/(1-Inputs!$B$31)*Inputs!$B$31 -> 0
A96: Gross amount raised | G96: =G94+G95 -> 0
A97: Net proceeds received in year | C97: =IF(AND(ISNUMBER($G$93),$G$93=2026),$G$94,0) -> 0 | D97: =IF(AND(ISNUMBER($G$93),$G$93=2027),$G$94,0) -> 0 | E97: =IF(AND(ISNUMBER($G$93),$G$93=2028),$G$94,0) -> 0 | F97: =IF(AND(ISNUMBER($G$93),$G$93=2029),$G$94,0) -> 0 | G97: =IF(AND(ISNUMBER($G$93),$G$93=2030),$G$94,0) -> 0
A98: Interest change vs. unfunded path (funded balance after start-of-year payments) | C98: =C97*Inputs!$B$20/2 -> 0 | D98: =MAX(0,C100-D81+D97)*Inputs!$B$20-D55 -> 0 | E98: =MAX(0,D100-E81+E97)*Inputs!$B$20-E55 -> 0 | F98: =MAX(0,E100-F81+F97)*Inputs!$B$20-F55 -> 0 | G98: =MAX(0,F100-G81+G97)*Inputs!$B$20-G55 -> 0
A99: Extra tax on that interest | C99: =C98*C70 -> 0 | D99: =D98*D70 -> 0 | E99: =E98*E70 -> 0 | F99: =F98*F70 -> 0 | G99: =G98*G70 -> 0
A100: Closing cash — funded | C100: =C85+SUM($C97:C97)+SUM($C98:C98)-SUM($C99:C99) -> 141998.19 | D100: =D85+SUM($C97:D97)+SUM($C98:D98)-SUM($C99:D99) -> 183307.57 | E100: =E85+SUM($C97:E97)+SUM($C98:E98)-SUM($C99:E99) -> 263182.82 | F100: =F85+SUM($C97:F97)+SUM($C98:F98)-SUM($C99:F99) -> 391162.13 | G100: =G85+SUM($C97:G97)+SUM($C98:G98)-SUM($C99:G99) -> 572260.71
A101: Lowest cash in the year — funded | C101: =MIN(C80-C81+0+C97,C100) -> 131651 | D101: =MIN(D80-D81+SUM($C97:C97)+SUM($C98:C98)-SUM($C99:C99)+D97,D100) -> 141998.19 | E101: =MIN(E80-E81+SUM($C97:D97)+SUM($C98:D98)-SUM($C99:D99)+E97,E100) -> 183307.57 | F101: =MIN(F80-F81+SUM($C97:E97)+SUM($C98:E98)-SUM($C99:E99)+F97,F100) -> 263182.82 | G101: =MIN(G80-G81+SUM($C97:F97)+SUM($C98:F98)-SUM($C99:F99)+G97,G100) -> 391162.13
A102: Funded path stays above threshold? | C102: =IF(C101-Inputs!$B$29<-0.5,"No","Yes") -> Yes | D102: =IF(D101-Inputs!$B$29<-0.5,"No","Yes") -> Yes | E102: =IF(E101-Inputs!$B$29<-0.5,"No","Yes") -> Yes | F102: =IF(F101-Inputs!$B$29<-0.5,"No","Yes") -> Yes | G102: =IF(G101-Inputs!$B$29<-0.5,"No","Yes") -> Yes
A104: Hybrid company (core + value-share): earnings, taxes, cash
A105: Revenue | C105: =C5+C31 -> 57228 | D105: =D5+D31 -> 155660.16 | E105: =E5+E31 -> 314181.72 | F105: =F5+F31 -> 539259.44 | G105: =G5+G31 -> 808309.73
A106: Operating income before depreciation of new owned capacity | C106: =C17+C35 -> 3255.7256 | D106: =D17+D35 -> 49955.286 | E106: =E17+E35 -> 129334.54 | F106: =F17+F35 -> 253075.44 | G106: =G17+G35 -> 409241.12
A107: Capital spending | C107: =C51+C37 -> 1716.84 | D107: =D51+D37 -> 6226.4064 | E107: =E51+E37 -> 15709.086 | F107: =F51+F37 -> 26962.972 | G107: =G51+G37 -> 40415.487
...

Sheet S1
A1: S1 Flat revenue — projections, cash and valuation ($ millions except per share)
A2: 2026E = H1 2026 actual + Q3 2026 implied + assumed Q4. Compute is forecast as cash spending (hosting, leases and owned capacity all treated as paid when expensed); the S-1 gives no payment schedule.
A4: Core business: income statement | B4: 2025A | C4: 2026E | D4: 2027E | E4: 2028E | F4: 2029E | G4: 2030E
A5: Revenue | B5: =Historicals!D35 -> 4585 | C5: =Historicals!F35+(Inputs!$B$5+Inputs!$G$60) -> 54228 | D5: =C5*(1+Inputs!$G$62) -> 54228 | E5: =D5*(1+Inputs!$G$63) -> 54228 | F5: =E5*(1+Inputs!$G$64) -> 54228 | G5: =F5*(1+Inputs!$G$65) -> 54228
A6: Growth | C6: =IFERROR(C5/B5-1,0) -> 10.827263 | D6: =IFERROR(D5/C5-1,0) -> 0 | E6: =IFERROR(E5/D5-1,0) -> 0 | F6: =IFERROR(F5/E5-1,0) -> 0 | G6: =IFERROR(G5/F5-1,0) -> 0
A7: Subscription revenue | B7: =Historicals!D51 -> 789 | C7: =Historicals!F51+(Inputs!$B$5+Inputs!$G$60)*Historicals!F51/Historicals!F35 -> 10728.393 | D7: =D5*Inputs!$G$61 -> 10845.6 | E7: =E5*Inputs!$G$61 -> 10845.6 | F7: =F5*Inputs!$G$61 -> 10845.6 | G7: =G5*Inputs!$G$61 -> 10845.6
A8: Consumption revenue | B8: =B5-B7 -> 3796 | C8: =C5-C7 -> 43499.607 | D8: =D5-D7 -> 43382.4 | E8: =E5-E7 -> 43382.4 | F8: =F5-F7 -> 43382.4 | G8: =G5-G7 -> 43382.4
A10: Compute and infrastructure | B10: =Historicals!D36 -> 7326 | C10: =Historicals!F36+(Inputs!$B$5+Inputs!$G$60)*Inputs!$G$66 -> 26018.9 | D10: =C10*(1+Inputs!$G$67) -> 44232.13 | E10: =D10*(1+Inputs!$G$68) -> 64136.588 | F10: =E10*(1+Inputs!$G$69) -> 83377.565 | G10: =F10*(1+Inputs!$G$70) -> 100053.08
A11: Personnel (incl. stock comp) | B11: =Historicals!D37 -> 1839 | C11: =Historicals!F37+(Inputs!$B$5+Inputs!$G$60)*Historicals!G24 -> 9249.6455 | D11: =D5*Inputs!$G$71 -> 7591.92 | E11: =E5*Inputs!$G$72 -> 7049.64 | F11: =F5*Inputs!$G$73 -> 6507.36 | G11: =G5*Inputs!$G$74 -> 5965.08
A12: of which stock comp | B12: =Historicals!D49 -> 1158 | C12: =Historicals!F49+(Inputs!$B$5+Inputs!$G$60)*Historicals!G29 -> 6325.6198 | D12: =D5*Inputs!$G$75 -> 4880.52 | E12: =E5*Inputs!$G$76 -> 4338.24 | F12: =F5*Inputs!$G$77 -> 3795.96 | G12: =G5*Inputs!$G$78 -> 3253.68
A13: Sales, marketing & partner fees | B13: =Historicals!D39 -> 568 | C13: =Historicals!F39+(Inputs!$B$5+Inputs!$G$60)*Historicals!G25 -> 10178.486 | D13: =D5*Inputs!$G$79 -> 9218.76 | E13: =E5*Inputs!$G$80 -> 8676.48 | F13: =F5*Inputs!$G$81 -> 8134.2 | G13: =G5*Inputs!$G$82 -> 8134.2
A14: Other operating & administrative | B14: =Historicals!D40 -> 1412 | C14: =Historicals!F40+(Inputs!$B$5+Inputs!$G$60)*Historicals!G26 -> 5099.3918 | D14: =D5*Inputs!$G$83 -> 4338.24 | E14: =E5*Inputs!$G$84 -> 3795.96 | F14: =F5*Inputs!$G$85 -> 3253.68 | G14: =G5*Inputs!$G$86 -> 3253.68
A15: One-time items (2025 Bartz settlement; 2026 Q3 donation-matching charge) | B15: =Historicals!D38 -> 1500 | C15: =Inputs!$B$37 -> 2000 | D15: 0 | E15: 0 | F15: 0 | G15: 0
A16: Total operating expenses | B16: =B10+B11+B13+B14+B15 -> 12645 | C16: =C10+C11+C13+C14+C15 -> 52546.424 | D16: =D10+D11+D13+D14+D15 -> 65381.05 | E16: =E10+E11+E13+E14+E15 -> 83658.668 | F16: =F10+F11+F13+F14+F15 -> 101272.81 | G16: =G10+G11+G13+G14+G15 -> 117406.04
A17: Operating income before depreciation of new owned capacity | B17: =B5-B16 -> -8060 | C17: =C5-C16 -> 1681.5763 | D17: =D5-D16 -> -11153.05 | E17: =E5-E16 -> -29430.668 | F17: =F5-F16 -> -47044.805 | G17: =G5-G16 -> -63178.038
A18: Margin | B18: =IFERROR(B17/B5,0) -> -1.7579062 | C18: =IFERROR(C17/C5,0) -> 0.031009374 | D18: =IFERROR(D17/D5,0) -> -0.20566958 | E18: =IFERROR(E17/E5,0) -> -0.54272089 | F18: =IFERROR(F17/F5,0) -> -0.86753716 | G18: =IFERROR(G17/G5,0) -> -1.1650446
A19: Compute % of revenue | B19: =IFERROR(B10/B5,0) -> 1.597819 | C19: =IFERROR(C10/C5,0) -> 0.47980564 | D19: =IFERROR(D10/D5,0) -> 0.81566958 | E19: =IFERROR(E10/E5,0) -> 1.1827209 | F19: =IFERROR(F10/F5,0) -> 1.5375372 | G19: =IFERROR(G10/G5,0) -> 1.8450446
A20: Non-cash donation-matching charges (incl. in costs above) | C20: =Historicals!$B$78+Inputs!$B$37 -> 2126 | D20: 0 | E20: 0 | F20: 0 | G20: 0
A21: Discount factor to end 2026 | D21: =1/(1+Inputs!$B$19+Inputs!$G$89)^1 -> 0.89285714 | E21: =1/(1+Inputs!$B$19+Inputs!$G$89)^2 -> 0.79719388 | F21: =1/(1+Inputs!$B$19+Inputs!$G$89)^3 -> 0.71178025 | G21: =1/(1+Inputs!$B$19+Inputs!$G$89)^4 -> 0.63551808
A23: Third business line: value-share partnerships (hypothetical)
A24: Share of core revenue base under value-share | C24: 0 | D24: =Inputs!$C$97 -> 0.02 | E24: =Inputs!$C$98 -> 0.05 | F24: =Inputs!$C$99 -> 0.1 | G24: =Inputs!$C$100 -> 0.15
A25: Revenue base moved to value-share | C25: =C5*C24 -> 0 | D25: =D5*D24 -> 1084.56 | E25: =E5*E24 -> 2711.4 | F25: =F5*F24 -> 5422.8 | G25: =G5*G24 -> 8134.2
A26: Value created per $1 of Claude spend | C26: =Inputs!$C$101 -> 8 | D26: =Inputs!$C$101 -> 8 | E26: =Inputs!$C$101 -> 8 | F26: =Inputs!$C$101 -> 8 | G26: =Inputs!$C$101 -> 8
A27: Economic value created for partners | C27: =C25*C26 -> 0 | D27: =D25*D26 -> 8676.48 | E27: =E25*E26 -> 21691.2 | F27: =F25*F26 -> 43382.4 | G27: =G25*G26 -> 65073.6
A28: Anthropic's cut | C28: =Inputs!$C$102 -> 0.15 | D28: =Inputs!$C$102 -> 0.15 | E28: =Inputs!$C$102 -> 0.15 | F28: =Inputs!$C$102 -> 0.15 | G28: =Inputs!$C$102 -> 0.15
A29: Value-share revenue (gross) | C29: =C27*C28 -> 0 | D29: =D27*D28 -> 1301.472 | E29: =E27*E28 -> 3253.68 | F29: =F27*F28 -> 6507.36 | G29: =G27*G28 -> 9761.04
A30: Token revenue given up | C30: =C25*Inputs!$C$103 -> 0 | D30: =D25*Inputs!$C$103 -> 325.368 | E30: =E25*Inputs!$C$103 -> 813.42 | F30: =F25*Inputs!$C$103 -> 1626.84 | G30: =G25*Inputs!$C$103 -> 2440.26
A31: Net new revenue | C31: =C29-C30 -> 0 | D31: =D29-D30 -> 976.104 | E31: =E29-E30 -> 2440.26 | F31: =F29-F30 -> 4880.52 | G31: =G29-G30 -> 7320.78
A32: Delivery cost | C32: =C29*Inputs!$C$104 -> 0 | D32: =D29*Inputs!$C$104 -> 260.2944 | E32: =E29*Inputs!$C$104 -> 650.736 | F32: =F29*Inputs!$C$104 -> 1301.472 | G32: =G29*Inputs!$C$104 -> 1952.208
A33: Extra compute | C33: =C29*Inputs!$C$105 -> 0 | D33: =D29*Inputs!$C$105 -> 195.2208 | E33: =E29*Inputs!$C$105 -> 488.052 | F33: =F29*Inputs!$C$105 -> 976.104 | G33: =G29*Inputs!$C$105 -> 1464.156
A34: Selling, partner fees & overhead | C34: =C29*Inputs!$C$106 -> 0 | D34: =D29*Inputs!$C$106 -> 130.1472 | E34: =E29*Inputs!$C$106 -> 325.368 | F34: =F29*Inputs!$C$106 -> 650.736 | G34: =G29*Inputs!$C$106 -> 976.104
A35: Value-share operating contribution | C35: =C29-C30-C32-C33-C34 -> 0 | D35: =D29-D30-D32-D33-D34 -> 390.4416 | E35: =E29-E30-E32-E33-E34 -> 976.104 | F35: =F29-F30-F32-F33-F34 -> 1952.208 | G35: =G29-G30-G32-G33-G34 -> 2928.312
A36: Value created as % of $40T knowledge-work pool | C36: =IFERROR(C27/Inputs!$B$27,0) -> 0 | D36: =IFERROR(D27/Inputs!$B$27,0) -> 0.000216912 | E36: =IFERROR(E27/Inputs!$B$27,0) -> 0.00054228 | F36: =IFERROR(F27/Inputs!$B$27,0) -> 0.00108456 | G36: =IFERROR(G27/Inputs!$B$27,0) -> 0.00162684
A37: Value-share capital spending (per selected basis) | C37: =CHOOSE(Inputs!$B$35,C31*Inputs!B$55,C29*Inputs!$B$36,0) -> 0 | D37: =CHOOSE(Inputs!$B$35,D31*Inputs!C$55,D29*Inputs!$B$36,0) -> 39.04416 | E37: =CHOOSE(Inputs!$B$35,E31*Inputs!D$55,E29*Inputs!$B$36,0) -> 122.013 | F37: =CHOOSE(Inputs!$B$35,F31*Inputs!E$55,F29*Inputs!$B$36,0) -> 244.026 | G37: =CHOOSE(Inputs!$B$35,G31*Inputs!F$55,G29*Inputs!$B$36,0) -> 366.039
A38: Value-share collection timing (working capital) | C38: 0 | D38: =-(D29-C29)*Inputs!$B$34/365 -> 0 | E38: =-(E29-D29)*Inputs!$B$34/365 -> 0 | F38: =-(F29-E29)*Inputs!$B$34/365 -> 0 | G38: =-(G29-F29)*Inputs!$B$34/365 -> 0
A40: Prepaid compute roll-forward (cash paid ahead of use)
A41: Prepaid balance, opening | C41: 0 | D41: =C46 -> 0 | E41: =D46 -> 0 | F41: =E46 -> 0 | G41: =F46 -> 0
A42: Prepayment paid (start of year) | C42: 0 | D42: =Inputs!$G$92 -> 0 | E42: 0 | F42: 0 | G42: 0
A43: Scheduled credits available (cumulative scheduled less used) | C43: =MAX(0,0) -> 0 | D43: =MAX(0,0) -> 0 | E43: =MAX(0,$D$42/Inputs!$B$40*MIN(1,Inputs!$B$40)-SUM($C45:D45)) -> 0 | F43: =MAX(0,$D$42/Inputs!$B$40*MIN(2,Inputs!$B$40)-SUM($C45:E45)) -> 0 | G43: =MAX(0,$D$42/Inputs!$B$40*MIN(3,Inputs!$B$40)-SUM($C45:F45)) -> 0
A44: Eligible compute charges this year | C44: =C10*Inputs!$B$39 -> 26018.9 | D44: =D10*Inputs!$B$39 -> 44232.13 | E44: =E10*Inputs!$B$39 -> 64136.588 | F44: =F10*Inputs!$B$39 -> 83377.565 | G44: =G10*Inputs!$B$39 -> 100053.08
A45: Credits used (capped by balance, schedule and eligible charges) | C45: =MAX(0,MIN(C41+C42,C43,C44)) -> 0 | D45: =MAX(0,MIN(D41+D42,D43,D44)) -> 0 | E45: =MAX(0,MIN(E41+E42,E43,E44)) -> 0 | F45: =MAX(0,MIN(F41+F42,F43,F44)) -> 0 | G45: =MAX(0,MIN(G41+G42,G43,G44)) -> 0
A46: Prepaid balance, closing | C46: =C41+C42-C45 -> 0 | D46: =D41+D42-D45 -> 0 | E46: =E41+E42-E45 -> 0 | F46: =F41+F42-F45 -> 0 | G46: =G41+G42-G45 -> 0
A48: Core business (tokens + subscriptions): earnings, taxes, cash
A49: Revenue | C49: =C5 -> 54228 | D49: =D5 -> 54228 | E49: =E5 -> 54228 | F49: =F5 -> 54228 | G49: =G5 -> 54228
A50: Operating income before depreciation of new owned capacity | C50: =C17 -> 1681.5763 | D50: =D17 -> -11153.05 | E50: =E17 -> -29430.668 | F50: =F17 -> -47044.805 | G50: =G17 -> -63178.038
A51: Capital spending | C51: =C5*Inputs!B$55 -> 1626.84 | D51: =D5*Inputs!C$55 -> 2169.12 | E51: =E5*Inputs!D$55 -> 2711.4 | F51: =F5*Inputs!E$55 -> 2711.4 | G51: =G5*Inputs!F$55 -> 2711.4
A52: Depreciation of owned capacity bought from 2027 | C52: 0 | D52: =SUMPRODUCT($D51:D51,--((4-COLUMN($D51:D51))<Inputs!$B$32))/Inputs!$B$32 -> 433.824 | E52: =SUMPRODUCT($D51:E51,--((5-COLUMN($D51:E51))<Inputs!$B$32))/Inputs!$B$32 -> 976.104 | F52: =SUMPRODUCT($D51:F51,--((6-COLUMN($D51:F51))<Inputs!$B$32))/Inputs!$B$32 -> 1518.384 | G52: =SUMPRODUCT($D51:G51,--((7-COLUMN($D51:G51))<Inputs!$B$32))/Inputs!$B$32 -> 2060.664
A53: Operating income (earnings basis, after stock comp) | C53: =C50-C52 -> 1681.5763 | D53: =D50-D52 -> -11586.874 | E53: =E50-E52 -> -30406.772 | F53: =F50-F52 -> -48563.189 | G53: =G50-G52 -> -65238.702
A54: Operating margin | C54: =IFERROR(C53/C49,0) -> 0.031009374 | D54: =IFERROR(D53/D49,0) -> -0.21366958 | E54: =IFERROR(E53/E49,0) -> -0.56072089 | F54: =IFERROR(F53/F49,0) -> -0.89553716 | G54: =IFERROR(G53/G49,0) -> -1.2030446
A55: Interest income (on opening cash) | C55: =Historicals!F43+C80*Inputs!$B$20/2 -> 2756.6375 | D55: =MAX(0,D80-D81)*Inputs!$B$20 -> 3507.9478 | E55: =MAX(0,E80-E81)*Inputs!$B$20 -> 3384.6052 | F55: =MAX(0,F80-F81)*Inputs!$B$20 -> 2774.1246 | G55: =MAX(0,G80-G81)*Inputs!$B$20 -> 1694.4716
A56: Other taxable income adjustments | C56: =Inputs!B$56 -> 0 | D56: =Inputs!C$56 -> 0 | E56: =Inputs!D$56 -> 0 | F56: =Inputs!E$56 -> 0 | G56: =Inputs!F$56 -> 0
A57: IPO RSU tax deduction | C57: =IF(Inputs!$B$51=2026,Inputs!$B$50,0) -> 0 | D57: =IF(Inputs!$B$51=2027,Inputs!$B$50,0) -> 0 | E57: =IF(Inputs!$B$51=2028,Inputs!$B$50,0) -> 0 | F57: =IF(Inputs!$B$51=2029,Inputs!$B$50,0) -> 0 | G57: =IF(Inputs!$B$51=2030,Inputs!$B$50,0) -> 0
A58: Taxable income proxy | C58: =C53+C55+C56-C57 -> 4438.2138 | D58: =D53+D55+D56-D57 -> -8078.9262 | E58: =E53+E55+E56-E57 -> -27022.167 | F58: =F53+F55+F56-F57 -> -45789.064 | G58: =G53+G55+G56-G57 -> -63544.23
A59: State taxable base (apportioned) | C59: =C58*Inputs!$B$46 -> 3195.514 | D59: =D58*Inputs!$B$46 -> -5816.8269 | E59: =E58*Inputs!$B$46 -> -19455.96 | F59: =F58*Inputs!$B$46 -> -32968.126 | G59: =G58*Inputs!$B$46 -> -45751.846
A60: State NOL, opening | C60: =Inputs!$B$48 -> 4200 | D60: =C62 -> 4200 | E60: =D62 -> 10016.827 | F60: =E62 -> 29472.787 | G60: =F62 -> 62440.914
A61: State NOL used | C61: =IF(AND(2026=2026,Inputs!$B$49=1),0,MIN(C60,MAX(0,C59))) -> 0 | D61: =IF(AND(2027=2026,Inputs!$B$49=1),0,MIN(D60,MAX(0,D59))) -> 0 | E61: =IF(AND(2028=2026,Inputs!$B$49=1),0,MIN(E60,MAX(0,E59))) -> 0 | F61: =IF(AND(2029=2026,Inputs!$B$49=1),0,MIN(F60,MAX(0,F59))) -> 0 | G61: =IF(AND(2030=2026,Inputs!$B$49=1),0,MIN(G60,MAX(0,G59))) -> 0
A62: State NOL, closing | C62: =C60-C61+MAX(0,-C59) -> 4200 | D62: =D60-D61+MAX(0,-D59) -> 10016.827 | E62: =E60-E61+MAX(0,-E59) -> 29472.787 | F62: =F60-F61+MAX(0,-F59) -> 62440.914 | G62: =G60-G61+MAX(0,-G59) -> 108192.76
A63: State tax | C63: =MAX(0,C59-C61)*Inputs!$B$47 -> 191.73084 | D63: =MAX(0,D59-D61)*Inputs!$B$47 -> 0 | E63: =MAX(0,E59-E61)*Inputs!$B$47 -> 0 | F63: =MAX(0,F59-F61)*Inputs!$B$47 -> 0 | G63: =MAX(0,G59-G61)*Inputs!$B$47 -> 0
A64: Federal taxable income before NOL (after state tax) | C64: =C58-C63 -> 4246.483 | D64: =D58-D63 -> -8078.9262 | E64: =E58-E63 -> -27022.167 | F64: =F58-F63 -> -45789.064 | G64: =G58-G63 -> -63544.23
A65: Federal NOL, opening | C65: =Inputs!$B$44 -> 8200 | D65: =C67 -> 4802.8136 | E65: =D67 -> 12881.74 | F65: =E67 -> 39903.907 | G65: =F67 -> 85692.972
A66: Federal NOL used (80% limit) | C66: =MIN(C65,Inputs!$B$45*MAX(0,C64)) -> 3397.1864 | D66: =MIN(D65,Inputs!$B$45*MAX(0,D64)) -> 0 | E66: =MIN(E65,Inputs!$B$45*MAX(0,E64)) -> 0 | F66: =MIN(F65,Inputs!$B$45*MAX(0,F64)) -> 0 | G66: =MIN(G65,Inputs!$B$45*MAX(0,G64)) -> 0
A67: Federal NOL, closing | C67: =C65-C66+MAX(0,-C64) -> 4802.8136 | D67: =D65-D66+MAX(0,-D64) -> 12881.74 | E67: =E65-E66+MAX(0,-E64) -> 39903.907 | F67: =F65-F66+MAX(0,-F64) -> 85692.972 | G67: =G65-G66+MAX(0,-G64) -> 149237.2
A68: Federal tax | C68: =MAX(0,C64-C66)*Inputs!$B$43 -> 178.35229 | D68: =MAX(0,D64-D66)*Inputs!$B$43 -> 0 | E68: =MAX(0,E64-E66)*Inputs!$B$43 -> 0 | F68: =MAX(0,F64-F66)*Inputs!$B$43 -> 0 | G68: =MAX(0,G64-G66)*Inputs!$B$43 -> 0
A69: Cash taxes (selected method) | C69: =IF(Inputs!$G$90=0,MAX(0,C53+C55)*Inputs!B$54,IF(Inputs!$G$90=2,MAX(0,C58)*Inputs!$G$91,C63+C68)) -> 370.08312 | D69: =IF(Inputs!$G$90=0,MAX(0,D53+D55)*Inputs!C$54,IF(Inputs!$G$90=2,MAX(0,D58)*Inputs!$G$91,D63+D68)) -> 0 | E69: =IF(Inputs!$G$90=0,MAX(0,E53+E55)*Inputs!D$54,IF(Inputs!$G$90=2,MAX(0,E58)*Inputs!$G$91,E63+E68)) -> 0 | F69: =IF(Inputs!$G$90=0,MAX(0,F53+F55)*Inputs!E$54,IF(Inputs!$G$90=2,MAX(0,F58)*Inputs!$G$91,F63+F68)) -> 0 | G69: =IF(Inputs!$G$90=0,MAX(0,G53+G55)*Inputs!F$54,IF(Inputs!$G$90=2,MAX(0,G58)*Inputs!$G$91,G63+G68)) -> 0
A70: Effective tax rate on taxable income | C70: =IF(C58>0,MIN(1,C69/C58),0) -> 0.0833856 | D70: =IF(D58>0,MIN(1,D69/D58),0) -> 0 | E70: =IF(E58>0,MIN(1,E69/E58),0) -> 0 | F70: =IF(F58>0,MIN(1,F69/F58),0) -> 0 | G70: =IF(G58>0,MIN(1,G69/G58),0) -> 0
A71: Net income excl. non-cash fair value items | C71: =C53+C55-C69 -> 4068.1307 | D71: =D53+D55-D69 -> -8078.9262 | E71: =E53+E55-E69 -> -27022.167 | F71: =F53+F55-F69 -> -45789.064 | G71: =G53+G55-G69 -> -63544.23
A72: Non-cash stock comp & donation charges (added back for liquidity) | C72: =C12+C20 -> 8451.6198 | D72: =D12+D20 -> 4880.52 | E72: =E12+E20 -> 4338.24 | F72: =F12+F20 -> 3795.96 | G72: =G12+G20 -> 3253.68
A73: Working capital | C73: 0 | D73: =-(D5-C5)*Inputs!$B$33 -> 0 | E73: =-(E5-D5)*Inputs!$B$33 -> 0 | F73: =-(F5-E5)*Inputs!$B$33 -> 0 | G73: =-(G5-F5)*Inputs!$B$33 -> 0
A74: Compute prepayment timing (non-recurring; excluded from exit value) | C74: =-C$42+C$45 -> 0 | D74: =-D$42+D$45 -> 0 | E74: =-E$42+E$45 -> 0 | F74: =-F$42+F$45 -> 0 | G74: =-G$42+G$45 -> 0
A75: Actual cash flow (liquidity basis) | C75: =C53+C72+C52+C55-C69-C51+C73+C74 -> 10892.911 | D75: =D53+D72+D52+D55-D69-D51+D73+D74 -> -4933.7022 | E75: =E53+E72+E52+E55-E69-E51+E73+E74 -> -24419.223 | F75: =F53+F72+F52+F55-F69-F51+F73+F74 -> -43186.12 | G75: =G53+G72+G52+G55-G69-G51+G73+G74 -> -60941.286
A76: Economic operating cash flow (valuation basis: after stock comp, excl. interest) | C76: =C53+C52-(C69-C55*C70)-C51+C73+C74 -> -85.482921 | D76: =D53+D52-(D69-D55*D70)-D51+D73+D74 -> -13322.17 | E76: =E53+E52-(E69-E55*E70)-E51+E73+E74 -> -32142.069 | F76: =F53+F52-(F69-F55*F70)-F51+F73+F74 -> -49756.205 | G76: =G53+G52-(G69-G55*G70)-G51+G73+G74 -> -65889.438
A77: Economic cash flow margin | C77: =IFERROR(C76/C49,0) -> -0.0015763613 | D77: =IFERROR(D76/D49,0) -> -0.24566958 | E77: =IFERROR(E76/E49,0) -> -0.59272089 | F77: =IFERROR(F76/F49,0) -> -0.91753716 | G77: =IFERROR(G76/G49,0) -> -1.2150446
A79: Cash roll-forward | C79: H2 2026 | D79: 2027E | E79: 2028E | F79: 2029E | G79: 2030E
A80: Opening cash | C80: =Inputs!$B$6 -> 131651 | D80: =C85 -> 140317.91 | E80: =D85 -> 135384.21 | F80: =E85 -> 110964.98 | G80: =F85 -> 67778.865
A81: of which paid at start of year (prepayment) | C81: =C$42 -> 0 | D81: =D$42 -> 0 | E81: =E$42 -> 0 | F81: =F$42 -> 0 | G81: =G$42 -> 0
A82: Cash flow in period (H2 only for 2026) | B82: 2026: full-year cash flow less H1 actual on the same basis | C82: =C75-Historicals!$B$79 -> 8666.9105 | D82: =D75 -> -4933.7022 | E82: =E75 -> -24419.223 | F82: =F75 -> -43186.12 | G82: =G75 -> -60941.286
A83: RSU tax withholding paid | C83: =-Inputs!$B$17 -> 0 | D83: 0 | E83: 0 | F83: 0 | G83: 0
A84: Primary IPO proceeds | C84: =Inputs!$B$15 -> 0 | D84: 0 | E84: 0 | F84: 0 | G84: 0
A85: Closing cash | C85: =C80+C82+C83+C84 -> 140317.91 | D85: =D80+D82+D83+D84 -> 135384.21 | E85: =E80+E82+E83+E84 -> 110964.98 | F85: =F80+F82+F83+F84 -> 67778.865 | G85: =G80+G82+G83+G84 -> 6837.5781
A86: Lowest cash in the year (start-of-year payments or year end) | C86: =MIN(C80-C81,C85) -> 131651 | D86: =MIN(D80-D81,D85) -> 135384.21 | E86: =MIN(E80-E81,E85) -> 110964.98 | F86: =MIN(F80-F81,F85) -> 67778.865 | G86: =MIN(G80-G81,G85) -> 6837.5781
A87: Lowest cash above the shortfall threshold | C87: =C86-Inputs!$B$29 -> 126651 | D87: =D86-Inputs!$B$29 -> 130384.21 | E87: =E86-Inputs!$B$29 -> 105964.98 | F87: =F86-Inputs!$B$29 -> 62778.865 | G87: =G86-Inputs!$B$29 -> 1837.5781
A88: Year-end cash vs $5B covenant (cash proxy) | C88: =IF(C85<Inputs!$B$38,"Below","OK") -> OK | D88: =IF(D85<Inputs!$B$38,"Below","OK") -> OK | E88: =IF(E85<Inputs!$B$38,"Below","OK") -> OK | F88: =IF(F85<Inputs!$B$38,"Below","OK") -> OK | G88: =IF(G85<Inputs!$B$38,"Below","OK") -> OK
A89: Funding status | C89: =IF(C87<0,"Shortfall","OK") -> OK | D89: =IF(D87<0,"Shortfall","OK") -> OK | E89: =IF(E87<0,"Shortfall","OK") -> OK | F89: =IF(F87<0,"Shortfall","OK") -> OK | G89: =IF(G87<0,"Shortfall","OK") -> OK
A90: Peak funding need (intra-year) | G90: =MAX(0,-MIN(C87:G87)) -> 0
A91: Sensitivity: peak funding need with a $0 buffer | G91: =MAX(0,-MIN(C86:G86)) -> 0
A92: Funded cash path (illustrative equity raise) | C92: H2 2026 | D92: 2027E | E92: 2028E | F92: 2029E | G92: 2030E
A93: Financing year (start of the first shortfall year; proceeds arrive with the payment) | G93: =IF(G90=0,"none",IFERROR(2025+MATCH(1,INDEX(--(C87:G87<0),0),0),"none")) -> none
A94: Net proceeds needed (covers peak need) | G94: =G90 -> 0
A95: Issuance fees | G95: =G94/(1-Inputs!$B$31)*Inputs!$B$31 -> 0
A96: Gross amount raised | G96: =G94+G95 -> 0
A97: Net proceeds received in year | C97: =IF(AND(ISNUMBER($G$93),$G$93=2026),$G$94,0) -> 0 | D97: =IF(AND(ISNUMBER($G$93),$G$93=2027),$G$94,0) -> 0 | E97: =IF(AND(ISNUMBER($G$93),$G$93=2028),$G$94,0) -> 0 | F97: =IF(AND(ISNUMBER($G$93),$G$93=2029),$G$94,0) -> 0 | G97: =IF(AND(ISNUMBER($G$93),$G$93=2030),$G$94,0) -> 0
A98: Interest change vs. unfunded path (funded balance after start-of-year payments) | C98: =C97*Inputs!$B$20/2 -> 0 | D98: =MAX(0,C100-D81+D97)*Inputs!$B$20-D55 -> 0 | E98: =MAX(0,D100-E81+E97)*Inputs!$B$20-E55 -> 0 | F98: =MAX(0,E100-F81+F97)*Inputs!$B$20-F55 -> 0 | G98: =MAX(0,F100-G81+G97)*Inputs!$B$20-G55 -> 0
A99: Extra tax on that interest | C99: =C98*C70 -> 0 | D99: =D98*D70 -> 0 | E99: =E98*E70 -> 0 | F99: =F98*F70 -> 0 | G99: =G98*G70 -> 0
A100: Closing cash — funded | C100: =C85+SUM($C97:C97)+SUM($C98:C98)-SUM($C99:C99) -> 140317.91 | D100: =D85+SUM($C97:D97)+SUM($C98:D98)-SUM($C99:D99) -> 135384.21 | E100: =E85+SUM($C97:E97)+SUM($C98:E98)-SUM($C99:E99) -> 110964.98 | F100: =F85+SUM($C97:F97)+SUM($C98:F98)-SUM($C99:F99) -> 67778.865 | G100: =G85+SUM($C97:G97)+SUM($C98:G98)-SUM($C99:G99) -> 6837.5781
A101: Lowest cash in the year — funded | C101: =MIN(C80-C81+0+C97,C100) -> 131651 | D101: =MIN(D80-D81+SUM($C97:C97)+SUM($C98:C98)-SUM($C99:C99)+D97,D100) -> 135384.21 | E101: =MIN(E80-E81+SUM($C97:D97)+SUM($C98:D98)-SUM($C99:D99)+E97,E100) -> 110964.98 | F101: =MIN(F80-F81+SUM($C97:E97)+SUM($C98:E98)-SUM($C99:E99)+F97,F100) -> 67778.865 | G101: =MIN(G80-G81+SUM($C97:F97)+SUM($C98:F98)-SUM($C99:F99)+G97,G100) -> 6837.5781
A102: Funded path stays above threshold? | C102: =IF(C101-Inputs!$B$29<-0.5,"No","Yes") -> Yes | D102: =IF(D101-Inputs!$B$29<-0.5,"No","Yes") -> Yes | E102: =IF(E101-Inputs!$B$29<-0.5,"No","Yes") -> Yes | F102: =IF(F101-Inputs!$B$29<-0.5,"No","Yes") -> Yes | G102: =IF(G101-Inputs!$B$29<-0.5,"No","Yes") -> Yes
A104: Hybrid company (core + value-share): earnings, taxes, cash
A105: Revenue | C105: =C5+C31 -> 54228 | D105: =D5+D31 -> 55204.104 | E105: =E5+E31 -> 56668.26 | F105: =F5+F31 -> 59108.52 | G105: =G5+G31 -> 61548.78
A106: Operating income before depreciation of new owned capacity | C106: =C17+C35 -> 1681.5763 | D106: =D17+D35 -> -10762.608 | E106: =E17+E35 -> -28454.565 | F106: =F17+F35 -> -45092.597 | G106: =G17+G35 -> -60249.726
A107: Capital spending | C107: =C51+C37 -> 1626.84 | D107: =D51+D37 -> 2208.1642 | E107: =E51+E37 -> 2833.413 | F107: =F51+F37 -> 2955.426 | G107: =G51+G37 -> 3077.439
...

Sheet S2
A1: S2 Compute +20% — projections, cash and valuation ($ millions except per share)
A2: 2026E = H1 2026 actual + Q3 2026 implied + assumed Q4. Compute is forecast as cash spending (hosting, leases and owned capacity all treated as paid when expensed); the S-1 gives no payment schedule.
A4: Core business: income statement | B4: 2025A | C4: 2026E | D4: 2027E | E4: 2028E | F4: 2029E | G4: 2030E
A5: Revenue | B5: =Historicals!D35 -> 4585 | C5: =Historicals!F35+(Inputs!$B$5+Inputs!$H$60) -> 54228 | D5: =C5*(1+Inputs!$H$62) -> 108456 | E5: =D5*(1+Inputs!$H$63) -> 168106.8 | F5: =E5*(1+Inputs!$H$64) -> 226944.18 | G5: =F5*(1+Inputs!$H$65) -> 283680.22
A6: Growth | C6: =IFERROR(C5/B5-1,0) -> 10.827263 | D6: =IFERROR(D5/C5-1,0) -> 1 | E6: =IFERROR(E5/D5-1,0) -> 0.55 | F6: =IFERROR(F5/E5-1,0) -> 0.35 | G6: =IFERROR(G5/F5-1,0) -> 0.25
A7: Subscription revenue | B7: =Historicals!D51 -> 789 | C7: =Historicals!F51+(Inputs!$B$5+Inputs!$H$60)*Historicals!F51/Historicals!F35 -> 10728.393 | D7: =D5*Inputs!$H$61 -> 21691.2 | E7: =E5*Inputs!$H$61 -> 33621.36 | F7: =F5*Inputs!$H$61 -> 45388.836 | G7: =G5*Inputs!$H$61 -> 56736.045
A8: Consumption revenue | B8: =B5-B7 -> 3796 | C8: =C5-C7 -> 43499.607 | D8: =D5-D7 -> 86764.8 | E8: =E5-E7 -> 134485.44 | F8: =F5-F7 -> 181555.34 | G8: =G5-G7 -> 226944.18
A10: Compute and infrastructure | B10: =Historicals!D36 -> 7326 | C10: =Historicals!F36+(Inputs!$B$5+Inputs!$H$60)*Inputs!$H$66 -> 26018.9 | D10: =C10*(1+Inputs!$H$67) -> 53078.556 | E10: =D10*(1+Inputs!$H$68) -> 76963.906 | F10: =E10*(1+Inputs!$H$69) -> 100053.08 | G10: =F10*(1+Inputs!$H$70) -> 120063.69
A11: Personnel (incl. stock comp) | B11: =Historicals!D37 -> 1839 | C11: =Historicals!F37+(Inputs!$B$5+Inputs!$H$60)*Historicals!G24 -> 9249.6455 | D11: =D5*Inputs!$H$71 -> 15183.84 | E11: =E5*Inputs!$H$72 -> 21853.884 | F11: =F5*Inputs!$H$73 -> 27233.302 | G11: =G5*Inputs!$H$74 -> 31204.825
A12: of which stock comp | B12: =Historicals!D49 -> 1158 | C12: =Historicals!F49+(Inputs!$B$5+Inputs!$H$60)*Historicals!G29 -> 6325.6198 | D12: =D5*Inputs!$H$75 -> 9761.04 | E12: =E5*Inputs!$H$76 -> 13448.544 | F12: =F5*Inputs!$H$77 -> 15886.093 | G12: =G5*Inputs!$H$78 -> 17020.814
A13: Sales, marketing & partner fees | B13: =Historicals!D39 -> 568 | C13: =Historicals!F39+(Inputs!$B$5+Inputs!$H$60)*Historicals!G25 -> 10178.486 | D13: =D5*Inputs!$H$79 -> 18437.52 | E13: =E5*Inputs!$H$80 -> 26897.088 | F13: =F5*Inputs!$H$81 -> 34041.627 | G13: =G5*Inputs!$H$82 -> 42552.034
A14: Other operating & administrative | B14: =Historicals!D40 -> 1412 | C14: =Historicals!F40+(Inputs!$B$5+Inputs!$H$60)*Historicals!G26 -> 5099.3918 | D14: =D5*Inputs!$H$83 -> 8676.48 | E14: =E5*Inputs!$H$84 -> 11767.476 | F14: =F5*Inputs!$H$85 -> 13616.651 | G14: =G5*Inputs!$H$86 -> 17020.814
A15: One-time items (2025 Bartz settlement; 2026 Q3 donation-matching charge) | B15: =Historicals!D38 -> 1500 | C15: =Inputs!$B$37 -> 2000 | D15: 0 | E15: 0 | F15: 0 | G15: 0
A16: Total operating expenses | B16: =B10+B11+B13+B14+B15 -> 12645 | C16: =C10+C11+C13+C14+C15 -> 52546.424 | D16: =D10+D11+D13+D14+D15 -> 95376.396 | E16: =E10+E11+E13+E14+E15 -> 137482.35 | F16: =F10+F11+F13+F14+F15 -> 174944.66 | G16: =G10+G11+G13+G14+G15 -> 210841.37
A17: Operating income before depreciation of new owned capacity | B17: =B5-B16 -> -8060 | C17: =C5-C16 -> 1681.5763 | D17: =D5-D16 -> 13079.604 | E17: =E5-E16 -> 30624.446 | F17: =F5-F16 -> 51999.523 | G17: =G5-G16 -> 72838.859
A18: Margin | B18: =IFERROR(B17/B5,0) -> -1.7579062 | C18: =IFERROR(C17/C5,0) -> 0.031009374 | D18: =IFERROR(D17/D5,0) -> 0.12059825 | E18: =IFERROR(E17/E5,0) -> 0.18217256 | F18: =IFERROR(F17/F5,0) -> 0.22912913 | G18: =IFERROR(G17/G5,0) -> 0.25676396
A19: Compute % of revenue | B19: =IFERROR(B10/B5,0) -> 1.597819 | C19: =IFERROR(C10/C5,0) -> 0.47980564 | D19: =IFERROR(D10/D5,0) -> 0.48940175 | E19: =IFERROR(E10/E5,0) -> 0.45782744 | F19: =IFERROR(F10/F5,0) -> 0.44087087 | G19: =IFERROR(G10/G5,0) -> 0.42323604
A20: Non-cash donation-matching charges (incl. in costs above) | C20: =Historicals!$B$78+Inputs!$B$37 -> 2126 | D20: 0 | E20: 0 | F20: 0 | G20: 0
A21: Discount factor to end 2026 | D21: =1/(1+Inputs!$B$19+Inputs!$H$89)^1 -> 0.89285714 | E21: =1/(1+Inputs!$B$19+Inputs!$H$89)^2 -> 0.79719388 | F21: =1/(1+Inputs!$B$19+Inputs!$H$89)^3 -> 0.71178025 | G21: =1/(1+Inputs!$B$19+Inputs!$H$89)^4 -> 0.63551808
A23: Third business line: value-share partnerships (hypothetical)
A24: Share of core revenue base under value-share | C24: 0 | D24: =Inputs!$C$97 -> 0.02 | E24: =Inputs!$C$98 -> 0.05 | F24: =Inputs!$C$99 -> 0.1 | G24: =Inputs!$C$100 -> 0.15
A25: Revenue base moved to value-share | C25: =C5*C24 -> 0 | D25: =D5*D24 -> 2169.12 | E25: =E5*E24 -> 8405.34 | F25: =F5*F24 -> 22694.418 | G25: =G5*G24 -> 42552.034
A26: Value created per $1 of Claude spend | C26: =Inputs!$C$101 -> 8 | D26: =Inputs!$C$101 -> 8 | E26: =Inputs!$C$101 -> 8 | F26: =Inputs!$C$101 -> 8 | G26: =Inputs!$C$101 -> 8
A27: Economic value created for partners | C27: =C25*C26 -> 0 | D27: =D25*D26 -> 17352.96 | E27: =E25*E26 -> 67242.72 | F27: =F25*F26 -> 181555.34 | G27: =G25*G26 -> 340416.27
A28: Anthropic's cut | C28: =Inputs!$C$102 -> 0.15 | D28: =Inputs!$C$102 -> 0.15 | E28: =Inputs!$C$102 -> 0.15 | F28: =Inputs!$C$102 -> 0.15 | G28: =Inputs!$C$102 -> 0.15
A29: Value-share revenue (gross) | C29: =C27*C28 -> 0 | D29: =D27*D28 -> 2602.944 | E29: =E27*E28 -> 10086.408 | F29: =F27*F28 -> 27233.302 | G29: =G27*G28 -> 51062.44
A30: Token revenue given up | C30: =C25*Inputs!$C$103 -> 0 | D30: =D25*Inputs!$C$103 -> 650.736 | E30: =E25*Inputs!$C$103 -> 2521.602 | F30: =F25*Inputs!$C$103 -> 6808.3254 | G30: =G25*Inputs!$C$103 -> 12765.61
A31: Net new revenue | C31: =C29-C30 -> 0 | D31: =D29-D30 -> 1952.208 | E31: =E29-E30 -> 7564.806 | F31: =F29-F30 -> 20424.976 | G31: =G29-G30 -> 38296.83
A32: Delivery cost | C32: =C29*Inputs!$C$104 -> 0 | D32: =D29*Inputs!$C$104 -> 520.5888 | E32: =E29*Inputs!$C$104 -> 2017.2816 | F32: =F29*Inputs!$C$104 -> 5446.6603 | G32: =G29*Inputs!$C$104 -> 10212.488
A33: Extra compute | C33: =C29*Inputs!$C$105 -> 0 | D33: =D29*Inputs!$C$105 -> 390.4416 | E33: =E29*Inputs!$C$105 -> 1512.9612 | F33: =F29*Inputs!$C$105 -> 4084.9952 | G33: =G29*Inputs!$C$105 -> 7659.3661
A34: Selling, partner fees & overhead | C34: =C29*Inputs!$C$106 -> 0 | D34: =D29*Inputs!$C$106 -> 260.2944 | E34: =E29*Inputs!$C$106 -> 1008.6408 | F34: =F29*Inputs!$C$106 -> 2723.3302 | G34: =G29*Inputs!$C$106 -> 5106.2441
A35: Value-share operating contribution | C35: =C29-C30-C32-C33-C34 -> 0 | D35: =D29-D30-D32-D33-D34 -> 780.8832 | E35: =E29-E30-E32-E33-E34 -> 3025.9224 | F35: =F29-F30-F32-F33-F34 -> 8169.9905 | G35: =G29-G30-G32-G33-G34 -> 15318.732
A36: Value created as % of $40T knowledge-work pool | C36: =IFERROR(C27/Inputs!$B$27,0) -> 0 | D36: =IFERROR(D27/Inputs!$B$27,0) -> 0.000433824 | E36: =IFERROR(E27/Inputs!$B$27,0) -> 0.001681068 | F36: =IFERROR(F27/Inputs!$B$27,0) -> 0.0045388836 | G36: =IFERROR(G27/Inputs!$B$27,0) -> 0.0085104067
A37: Value-share capital spending (per selected basis) | C37: =CHOOSE(Inputs!$B$35,C31*Inputs!B$55,C29*Inputs!$B$36,0) -> 0 | D37: =CHOOSE(Inputs!$B$35,D31*Inputs!C$55,D29*Inputs!$B$36,0) -> 78.08832 | E37: =CHOOSE(Inputs!$B$35,E31*Inputs!D$55,E29*Inputs!$B$36,0) -> 378.2403 | F37: =CHOOSE(Inputs!$B$35,F31*Inputs!E$55,F29*Inputs!$B$36,0) -> 1021.2488 | G37: =CHOOSE(Inputs!$B$35,G31*Inputs!F$55,G29*Inputs!$B$36,0) -> 1914.8415
A38: Value-share collection timing (working capital) | C38: 0 | D38: =-(D29-C29)*Inputs!$B$34/365 -> 0 | E38: =-(E29-D29)*Inputs!$B$34/365 -> 0 | F38: =-(F29-E29)*Inputs!$B$34/365 -> 0 | G38: =-(G29-F29)*Inputs!$B$34/365 -> 0
A40: Prepaid compute roll-forward (cash paid ahead of use)
A41: Prepaid balance, opening | C41: 0 | D41: =C46 -> 0 | E41: =D46 -> 0 | F41: =E46 -> 0 | G41: =F46 -> 0
A42: Prepayment paid (start of year) | C42: 0 | D42: =Inputs!$H$92 -> 0 | E42: 0 | F42: 0 | G42: 0
A43: Scheduled credits available (cumulative scheduled less used) | C43: =MAX(0,0) -> 0 | D43: =MAX(0,0) -> 0 | E43: =MAX(0,$D$42/Inputs!$B$40*MIN(1,Inputs!$B$40)-SUM($C45:D45)) -> 0 | F43: =MAX(0,$D$42/Inputs!$B$40*MIN(2,Inputs!$B$40)-SUM($C45:E45)) -> 0 | G43: =MAX(0,$D$42/Inputs!$B$40*MIN(3,Inputs!$B$40)-SUM($C45:F45)) -> 0
A44: Eligible compute charges this year | C44: =C10*Inputs!$B$39 -> 26018.9 | D44: =D10*Inputs!$B$39 -> 53078.556 | E44: =E10*Inputs!$B$39 -> 76963.906 | F44: =F10*Inputs!$B$39 -> 100053.08 | G44: =G10*Inputs!$B$39 -> 120063.69
A45: Credits used (capped by balance, schedule and eligible charges) | C45: =MAX(0,MIN(C41+C42,C43,C44)) -> 0 | D45: =MAX(0,MIN(D41+D42,D43,D44)) -> 0 | E45: =MAX(0,MIN(E41+E42,E43,E44)) -> 0 | F45: =MAX(0,MIN(F41+F42,F43,F44)) -> 0 | G45: =MAX(0,MIN(G41+G42,G43,G44)) -> 0
A46: Prepaid balance, closing | C46: =C41+C42-C45 -> 0 | D46: =D41+D42-D45 -> 0 | E46: =E41+E42-E45 -> 0 | F46: =F41+F42-F45 -> 0 | G46: =G41+G42-G45 -> 0
A48: Core business (tokens + subscriptions): earnings, taxes, cash
A49: Revenue | C49: =C5 -> 54228 | D49: =D5 -> 108456 | E49: =E5 -> 168106.8 | F49: =F5 -> 226944.18 | G49: =G5 -> 283680.22
A50: Operating income before depreciation of new owned capacity | C50: =C17 -> 1681.5763 | D50: =D17 -> 13079.604 | E50: =E17 -> 30624.446 | F50: =F17 -> 51999.523 | G50: =G17 -> 72838.859
A51: Capital spending | C51: =C5*Inputs!B$55 -> 1626.84 | D51: =D5*Inputs!C$55 -> 4338.24 | E51: =E5*Inputs!D$55 -> 8405.34 | F51: =F5*Inputs!E$55 -> 11347.209 | G51: =G5*Inputs!F$55 -> 14184.011
A52: Depreciation of owned capacity bought from 2027 | C52: 0 | D52: =SUMPRODUCT($D51:D51,--((4-COLUMN($D51:D51))<Inputs!$B$32))/Inputs!$B$32 -> 867.648 | E52: =SUMPRODUCT($D51:E51,--((5-COLUMN($D51:E51))<Inputs!$B$32))/Inputs!$B$32 -> 2548.716 | F52: =SUMPRODUCT($D51:F51,--((6-COLUMN($D51:F51))<Inputs!$B$32))/Inputs!$B$32 -> 4818.1578 | G52: =SUMPRODUCT($D51:G51,--((7-COLUMN($D51:G51))<Inputs!$B$32))/Inputs!$B$32 -> 7654.96
A53: Operating income (earnings basis, after stock comp) | C53: =C50-C52 -> 1681.5763 | D53: =D50-D52 -> 12211.956 | E53: =E50-E52 -> 28075.73 | F53: =F50-F52 -> 47181.365 | G53: =G50-G52 -> 65183.899
A54: Operating margin | C54: =IFERROR(C53/C49,0) -> 0.031009374 | D54: =IFERROR(D53/D49,0) -> 0.11259825 | E54: =IFERROR(E53/E49,0) -> 0.16701127 | F54: =IFERROR(F53/F49,0) -> 0.20789854 | G54: =IFERROR(G53/G49,0) -> 0.2297795
A55: Interest income (on opening cash) | C55: =Historicals!F43+C80*Inputs!$B$20/2 -> 2756.6375 | D55: =MAX(0,D80-D81)*Inputs!$B$20 -> 3507.9478 | E55: =MAX(0,E80-E81)*Inputs!$B$20 -> 3992.4566 | F55: =MAX(0,F80-F81)*Inputs!$B$20 -> 4788.2407 | G55: =MAX(0,G80-G81)*Inputs!$B$20 -> 6004.226
A56: Other taxable income adjustments | C56: =Inputs!B$56 -> 0 | D56: =Inputs!C$56 -> 0 | E56: =Inputs!D$56 -> 0 | F56: =Inputs!E$56 -> 0 | G56: =Inputs!F$56 -> 0
A57: IPO RSU tax deduction | C57: =IF(Inputs!$B$51=2026,Inputs!$B$50,0) -> 0 | D57: =IF(Inputs!$B$51=2027,Inputs!$B$50,0) -> 0 | E57: =IF(Inputs!$B$51=2028,Inputs!$B$50,0) -> 0 | F57: =IF(Inputs!$B$51=2029,Inputs!$B$50,0) -> 0 | G57: =IF(Inputs!$B$51=2030,Inputs!$B$50,0) -> 0
A58: Taxable income proxy | C58: =C53+C55+C56-C57 -> 4438.2138 | D58: =D53+D55+D56-D57 -> 15719.904 | E58: =E53+E55+E56-E57 -> 32068.186 | F58: =F53+F55+F56-F57 -> 51969.605 | G58: =G53+G55+G56-G57 -> 71188.125
A59: State taxable base (apportioned) | C59: =C58*Inputs!$B$46 -> 3195.514 | D59: =D58*Inputs!$B$46 -> 11318.331 | E59: =E58*Inputs!$B$46 -> 23089.094 | F59: =F58*Inputs!$B$46 -> 37418.116 | G59: =G58*Inputs!$B$46 -> 51255.45
A60: State NOL, opening | C60: =Inputs!$B$48 -> 4200 | D60: =C62 -> 4200 | E60: =D62 -> 0 | F60: =E62 -> 0 | G60: =F62 -> 0
A61: State NOL used | C61: =IF(AND(2026=2026,Inputs!$B$49=1),0,MIN(C60,MAX(0,C59))) -> 0 | D61: =IF(AND(2027=2026,Inputs!$B$49=1),0,MIN(D60,MAX(0,D59))) -> 4200 | E61: =IF(AND(2028=2026,Inputs!$B$49=1),0,MIN(E60,MAX(0,E59))) -> 0 | F61: =IF(AND(2029=2026,Inputs!$B$49=1),0,MIN(F60,MAX(0,F59))) -> 0 | G61: =IF(AND(2030=2026,Inputs!$B$49=1),0,MIN(G60,MAX(0,G59))) -> 0
A62: State NOL, closing | C62: =C60-C61+MAX(0,-C59) -> 4200 | D62: =D60-D61+MAX(0,-D59) -> 0 | E62: =E60-E61+MAX(0,-E59) -> 0 | F62: =F60-F61+MAX(0,-F59) -> 0 | G62: =G60-G61+MAX(0,-G59) -> 0
A63: State tax | C63: =MAX(0,C59-C61)*Inputs!$B$47 -> 191.73084 | D63: =MAX(0,D59-D61)*Inputs!$B$47 -> 427.09984 | E63: =MAX(0,E59-E61)*Inputs!$B$47 -> 1385.3457 | F63: =MAX(0,F59-F61)*Inputs!$B$47 -> 2245.087 | G63: =MAX(0,G59-G61)*Inputs!$B$47 -> 3075.327
A64: Federal taxable income before NOL (after state tax) | C64: =C58-C63 -> 4246.483 | D64: =D58-D63 -> 15292.804 | E64: =E58-E63 -> 30682.841 | F64: =F58-F63 -> 49724.519 | G64: =G58-G63 -> 68112.798
A65: Federal NOL, opening | C65: =Inputs!$B$44 -> 8200 | D65: =C67 -> 4802.8136 | E65: =D67 -> 0 | F65: =E67 -> 0 | G65: =F67 -> 0
A66: Federal NOL used (80% limit) | C66: =MIN(C65,Inputs!$B$45*MAX(0,C64)) -> 3397.1864 | D66: =MIN(D65,Inputs!$B$45*MAX(0,D64)) -> 4802.8136 | E66: =MIN(E65,Inputs!$B$45*MAX(0,E64)) -> 0 | F66: =MIN(F65,Inputs!$B$45*MAX(0,F64)) -> 0 | G66: =MIN(G65,Inputs!$B$45*MAX(0,G64)) -> 0
A67: Federal NOL, closing | C67: =C65-C66+MAX(0,-C64) -> 4802.8136 | D67: =D65-D66+MAX(0,-D64) -> 0 | E67: =E65-E66+MAX(0,-E64) -> 0 | F67: =F65-F66+MAX(0,-F64) -> 0 | G67: =G65-G66+MAX(0,-G64) -> 0
A68: Federal tax | C68: =MAX(0,C64-C66)*Inputs!$B$43 -> 178.35229 | D68: =MAX(0,D64-D66)*Inputs!$B$43 -> 2202.898 | E68: =MAX(0,E64-E66)*Inputs!$B$43 -> 6443.3966 | F68: =MAX(0,F64-F66)*Inputs!$B$43 -> 10442.149 | G68: =MAX(0,G64-G66)*Inputs!$B$43 -> 14303.688
A69: Cash taxes (selected method) | C69: =IF(Inputs!$H$90=0,MAX(0,C53+C55)*Inputs!B$54,IF(Inputs!$H$90=2,MAX(0,C58)*Inputs!$H$91,C63+C68)) -> 370.08312 | D69: =IF(Inputs!$H$90=0,MAX(0,D53+D55)*Inputs!C$54,IF(Inputs!$H$90=2,MAX(0,D58)*Inputs!$H$91,D63+D68)) -> 2629.9978 | E69: =IF(Inputs!$H$90=0,MAX(0,E53+E55)*Inputs!D$54,IF(Inputs!$H$90=2,MAX(0,E58)*Inputs!$H$91,E63+E68)) -> 7828.7422 | F69: =IF(Inputs!$H$90=0,MAX(0,F53+F55)*Inputs!E$54,IF(Inputs!$H$90=2,MAX(0,F58)*Inputs!$H$91,F63+F68)) -> 12687.236 | G69: =IF(Inputs!$H$90=0,MAX(0,G53+G55)*Inputs!F$54,IF(Inputs!$H$90=2,MAX(0,G58)*Inputs!$H$91,G63+G68)) -> 17379.015
A70: Effective tax rate on taxable income | C70: =IF(C58>0,MIN(1,C69/C58),0) -> 0.0833856 | D70: =IF(D58>0,MIN(1,D69/D58),0) -> 0.16730368 | E70: =IF(E58>0,MIN(1,E69/E58),0) -> 0.244128 | F70: =IF(F58>0,MIN(1,F69/F58),0) -> 0.244128 | G70: =IF(G58>0,MIN(1,G69/G58),0) -> 0.244128
A71: Net income excl. non-cash fair value items | C71: =C53+C55-C69 -> 4068.1307 | D71: =D53+D55-D69 -> 13089.906 | E71: =E53+E55-E69 -> 24239.444 | F71: =F53+F55-F69 -> 39282.37 | G71: =G53+G55-G69 -> 53809.111
A72: Non-cash stock comp & donation charges (added back for liquidity) | C72: =C12+C20 -> 8451.6198 | D72: =D12+D20 -> 9761.04 | E72: =E12+E20 -> 13448.544 | F72: =F12+F20 -> 15886.093 | G72: =G12+G20 -> 17020.814
A73: Working capital | C73: 0 | D73: =-(D5-C5)*Inputs!$B$33 -> 0 | E73: =-(E5-D5)*Inputs!$B$33 -> 0 | F73: =-(F5-E5)*Inputs!$B$33 -> 0 | G73: =-(G5-F5)*Inputs!$B$33 -> 0
A74: Compute prepayment timing (non-recurring; excluded from exit value) | C74: =-C$42+C$45 -> 0 | D74: =-D$42+D$45 -> 0 | E74: =-E$42+E$45 -> 0 | F74: =-F$42+F$45 -> 0 | G74: =-G$42+G$45 -> 0
A75: Actual cash flow (liquidity basis) | C75: =C53+C72+C52+C55-C69-C51+C73+C74 -> 10892.911 | D75: =D53+D72+D52+D55-D69-D51+D73+D74 -> 19380.354 | E75: =E53+E72+E52+E55-E69-E51+E73+E74 -> 31831.364 | F75: =F53+F72+F52+F55-F69-F51+F73+F74 -> 48639.411 | G75: =G53+G72+G52+G55-G69-G51+G73+G74 -> 64300.873
A76: Economic operating cash flow (valuation basis: after stock comp, excl. interest) | C76: =C53+C52-(C69-C55*C70)-C51+C73+C74 -> -85.482921 | D76: =D53+D52-(D69-D55*D70)-D51+D73+D74 -> 6698.2588 | E76: =E53+E52-(E69-E55*E70)-E51+E73+E74 -> 15365.034 | F76: =F53+F52-(F69-F55*F70)-F51+F73+F74 -> 29134.021 | G76: =G53+G52-(G69-G55*G70)-G51+G73+G74 -> 42741.633
A77: Economic cash flow margin | C77: =IFERROR(C76/C49,0) -> -0.0015763613 | D77: =IFERROR(D76/D49,0) -> 0.06176015 | E77: =IFERROR(E76/E49,0) -> 0.091400431 | F77: =IFERROR(F76/F49,0) -> 0.12837527 | G77: =IFERROR(G76/G49,0) -> 0.15066836
A79: Cash roll-forward | C79: H2 2026 | D79: 2027E | E79: 2028E | F79: 2029E | G79: 2030E
A80: Opening cash | C80: =Inputs!$B$6 -> 131651 | D80: =C85 -> 140317.91 | E80: =D85 -> 159698.26 | F80: =E85 -> 191529.63 | G80: =F85 -> 240169.04
A81: of which paid at start of year (prepayment) | C81: =C$42 -> 0 | D81: =D$42 -> 0 | E81: =E$42 -> 0 | F81: =F$42 -> 0 | G81: =G$42 -> 0
A82: Cash flow in period (H2 only for 2026) | B82: 2026: full-year cash flow less H1 actual on the same basis | C82: =C75-Historicals!$B$79 -> 8666.9105 | D82: =D75 -> 19380.354 | E82: =E75 -> 31831.364 | F82: =F75 -> 48639.411 | G82: =G75 -> 64300.873
A83: RSU tax withholding paid | C83: =-Inputs!$B$17 -> 0 | D83: 0 | E83: 0 | F83: 0 | G83: 0
A84: Primary IPO proceeds | C84: =Inputs!$B$15 -> 0 | D84: 0 | E84: 0 | F84: 0 | G84: 0
A85: Closing cash | C85: =C80+C82+C83+C84 -> 140317.91 | D85: =D80+D82+D83+D84 -> 159698.26 | E85: =E80+E82+E83+E84 -> 191529.63 | F85: =F80+F82+F83+F84 -> 240169.04 | G85: =G80+G82+G83+G84 -> 304469.91
A86: Lowest cash in the year (start-of-year payments or year end) | C86: =MIN(C80-C81,C85) -> 131651 | D86: =MIN(D80-D81,D85) -> 140317.91 | E86: =MIN(E80-E81,E85) -> 159698.26 | F86: =MIN(F80-F81,F85) -> 191529.63 | G86: =MIN(G80-G81,G85) -> 240169.04
A87: Lowest cash above the shortfall threshold | C87: =C86-Inputs!$B$29 -> 126651 | D87: =D86-Inputs!$B$29 -> 135317.91 | E87: =E86-Inputs!$B$29 -> 154698.26 | F87: =F86-Inputs!$B$29 -> 186529.63 | G87: =G86-Inputs!$B$29 -> 235169.04
A88: Year-end cash vs $5B covenant (cash proxy) | C88: =IF(C85<Inputs!$B$38,"Below","OK") -> OK | D88: =IF(D85<Inputs!$B$38,"Below","OK") -> OK | E88: =IF(E85<Inputs!$B$38,"Below","OK") -> OK | F88: =IF(F85<Inputs!$B$38,"Below","OK") -> OK | G88: =IF(G85<Inputs!$B$38,"Below","OK") -> OK
A89: Funding status | C89: =IF(C87<0,"Shortfall","OK") -> OK | D89: =IF(D87<0,"Shortfall","OK") -> OK | E89: =IF(E87<0,"Shortfall","OK") -> OK | F89: =IF(F87<0,"Shortfall","OK") -> OK | G89: =IF(G87<0,"Shortfall","OK") -> OK
A90: Peak funding need (intra-year) | G90: =MAX(0,-MIN(C87:G87)) -> 0
A91: Sensitivity: peak funding need with a $0 buffer | G91: =MAX(0,-MIN(C86:G86)) -> 0
A92: Funded cash path (illustrative equity raise) | C92: H2 2026 | D92: 2027E | E92: 2028E | F92: 2029E | G92: 2030E
A93: Financing year (start of the first shortfall year; proceeds arrive with the payment) | G93: =IF(G90=0,"none",IFERROR(2025+MATCH(1,INDEX(--(C87:G87<0),0),0),"none")) -> none
A94: Net proceeds needed (covers peak need) | G94: =G90 -> 0
A95: Issuance fees | G95: =G94/(1-Inputs!$B$31)*Inputs!$B$31 -> 0
A96: Gross amount raised | G96: =G94+G95 -> 0
A97: Net proceeds received in year | C97: =IF(AND(ISNUMBER($G$93),$G$93=2026),$G$94,0) -> 0 | D97: =IF(AND(ISNUMBER($G$93),$G$93=2027),$G$94,0) -> 0 | E97: =IF(AND(ISNUMBER($G$93),$G$93=2028),$G$94,0) -> 0 | F97: =IF(AND(ISNUMBER($G$93),$G$93=2029),$G$94,0) -> 0 | G97: =IF(AND(ISNUMBER($G$93),$G$93=2030),$G$94,0) -> 0
A98: Interest change vs. unfunded path (funded balance after start-of-year payments) | C98: =C97*Inputs!$B$20/2 -> 0 | D98: =MAX(0,C100-D81+D97)*Inputs!$B$20-D55 -> 0 | E98: =MAX(0,D100-E81+E97)*Inputs!$B$20-E55 -> 0 | F98: =MAX(0,E100-F81+F97)*Inputs!$B$20-F55 -> 0 | G98: =MAX(0,F100-G81+G97)*Inputs!$B$20-G55 -> 0
A99: Extra tax on that interest | C99: =C98*C70 -> 0 | D99: =D98*D70 -> 0 | E99: =E98*E70 -> 0 | F99: =F98*F70 -> 0 | G99: =G98*G70 -> 0
A100: Closing cash — funded | C100: =C85+SUM($C97:C97)+SUM($C98:C98)-SUM($C99:C99) -> 140317.91 | D100: =D85+SUM($C97:D97)+SUM($C98:D98)-SUM($C99:D99) -> 159698.26 | E100: =E85+SUM($C97:E97)+SUM($C98:E98)-SUM($C99:E99) -> 191529.63 | F100: =F85+SUM($C97:F97)+SUM($C98:F98)-SUM($C99:F99) -> 240169.04 | G100: =G85+SUM($C97:G97)+SUM($C98:G98)-SUM($C99:G99) -> 304469.91
A101: Lowest cash in the year — funded | C101: =MIN(C80-C81+0+C97,C100) -> 131651 | D101: =MIN(D80-D81+SUM($C97:C97)+SUM($C98:C98)-SUM($C99:C99)+D97,D100) -> 140317.91 | E101: =MIN(E80-E81+SUM($C97:D97)+SUM($C98:D98)-SUM($C99:D99)+E97,E100) -> 159698.26 | F101: =MIN(F80-F81+SUM($C97:E97)+SUM($C98:E98)-SUM($C99:E99)+F97,F100) -> 191529.63 | G101: =MIN(G80-G81+SUM($C97:F97)+SUM($C98:F98)-SUM($C99:F99)+G97,G100) -> 240169.04
A102: Funded path stays above threshold? | C102: =IF(C101-Inputs!$B$29<-0.5,"No","Yes") -> Yes | D102: =IF(D101-Inputs!$B$29<-0.5,"No","Yes") -> Yes | E102: =IF(E101-Inputs!$B$29<-0.5,"No","Yes") -> Yes | F102: =IF(F101-Inputs!$B$29<-0.5,"No","Yes") -> Yes | G102: =IF(G101-Inputs!$B$29<-0.5,"No","Yes") -> Yes
A104: Hybrid company (core + value-share): earnings, taxes, cash
A105: Revenue | C105: =C5+C31 -> 54228 | D105: =D5+D31 -> 110408.21 | E105: =E5+E31 -> 175671.61 | F105: =F5+F31 -> 247369.16 | G105: =G5+G31 -> 321977.06
A106: Operating income before depreciation of new owned capacity | C106: =C17+C35 -> 1681.5763 | D106: =D17+D35 -> 13860.487 | E106: =E17+E35 -> 33650.368 | F106: =F17+F35 -> 60169.513 | G106: =G17+G35 -> 88157.591
A107: Capital spending | C107: =C51+C37 -> 1626.84 | D107: =D51+D37 -> 4416.3283 | E107: =E51+E37 -> 8783.5803 | F107: =F51+F37 -> 12368.458 | G107: =G51+G37 -> 16098.853
...

Sheet S3
A1: S3 Half growth — projections, cash and valuation ($ millions except per share)
A2: 2026E = H1 2026 actual + Q3 2026 implied + assumed Q4. Compute is forecast as cash spending (hosting, leases and owned capacity all treated as paid when expensed); the S-1 gives no payment schedule.
A4: Core business: income statement | B4: 2025A | C4: 2026E | D4: 2027E | E4: 2028E | F4: 2029E | G4: 2030E
A5: Revenue | B5: =Historicals!D35 -> 4585 | C5: =Historicals!F35+(Inputs!$B$5+Inputs!$I$60) -> 54228 | D5: =C5*(1+Inputs!$I$62) -> 81342 | E5: =D5*(1+Inputs!$I$63) -> 103711.05 | F5: =E5*(1+Inputs!$I$64) -> 121860.48 | G5: =F5*(1+Inputs!$I$65) -> 137093.04
A6: Growth | C6: =IFERROR(C5/B5-1,0) -> 10.827263 | D6: =IFERROR(D5/C5-1,0) -> 0.5 | E6: =IFERROR(E5/D5-1,0) -> 0.275 | F6: =IFERROR(F5/E5-1,0) -> 0.175 | G6: =IFERROR(G5/F5-1,0) -> 0.125
A7: Subscription revenue | B7: =Historicals!D51 -> 789 | C7: =Historicals!F51+(Inputs!$B$5+Inputs!$I$60)*Historicals!F51/Historicals!F35 -> 10728.393 | D7: =D5*Inputs!$I$61 -> 16268.4 | E7: =E5*Inputs!$I$61 -> 20742.21 | F7: =F5*Inputs!$I$61 -> 24372.097 | G7: =G5*Inputs!$I$61 -> 27418.609
A8: Consumption revenue | B8: =B5-B7 -> 3796 | C8: =C5-C7 -> 43499.607 | D8: =D5-D7 -> 65073.6 | E8: =E5-E7 -> 82968.84 | F8: =F5-F7 -> 97488.387 | G8: =G5-G7 -> 109674.44
A10: Compute and infrastructure | B10: =Historicals!D36 -> 7326 | C10: =Historicals!F36+(Inputs!$B$5+Inputs!$I$60)*Inputs!$I$66 -> 26018.9 | D10: =C10*(1+Inputs!$I$67) -> 44232.13 | E10: =D10*(1+Inputs!$I$68) -> 64136.588 | F10: =E10*(1+Inputs!$I$69) -> 83377.565 | G10: =F10*(1+Inputs!$I$70) -> 100053.08
A11: Personnel (incl. stock comp) | B11: =Historicals!D37 -> 1839 | C11: =Historicals!F37+(Inputs!$B$5+Inputs!$I$60)*Historicals!G24 -> 9249.6455 | D11: =D5*Inputs!$I$71 -> 11387.88 | E11: =E5*Inputs!$I$72 -> 13482.436 | F11: =F5*Inputs!$I$73 -> 14623.258 | G11: =G5*Inputs!$I$74 -> 15080.235
A12: of which stock comp | B12: =Historicals!D49 -> 1158 | C12: =Historicals!F49+(Inputs!$B$5+Inputs!$I$60)*Historicals!G29 -> 6325.6198 | D12: =D5*Inputs!$I$75 -> 7320.78 | E12: =E5*Inputs!$I$76 -> 8296.884 | F12: =F5*Inputs!$I$77 -> 8530.2339 | G12: =G5*Inputs!$I$78 -> 8225.5827
A13: Sales, marketing & partner fees | B13: =Historicals!D39 -> 568 | C13: =Historicals!F39+(Inputs!$B$5+Inputs!$I$60)*Historicals!G25 -> 10178.486 | D13: =D5*Inputs!$I$79 -> 13828.14 | E13: =E5*Inputs!$I$80 -> 16593.768 | F13: =F5*Inputs!$I$81 -> 18279.073 | G13: =G5*Inputs!$I$82 -> 20563.957
A14: Other operating & administrative | B14: =Historicals!D40 -> 1412 | C14: =Historicals!F40+(Inputs!$B$5+Inputs!$I$60)*Historicals!G26 -> 5099.3918 | D14: =D5*Inputs!$I$83 -> 6507.36 | E14: =E5*Inputs!$I$84 -> 7259.7735 | F14: =F5*Inputs!$I$85 -> 7311.629 | G14: =G5*Inputs!$I$86 -> 8225.5827
A15: One-time items (2025 Bartz settlement; 2026 Q3 donation-matching charge) | B15: =Historicals!D38 -> 1500 | C15: =Inputs!$B$37 -> 2000 | D15: 0 | E15: 0 | F15: 0 | G15: 0
A16: Total operating expenses | B16: =B10+B11+B13+B14+B15 -> 12645 | C16: =C10+C11+C13+C14+C15 -> 52546.424 | D16: =D10+D11+D13+D14+D15 -> 75955.51 | E16: =E10+E11+E13+E14+E15 -> 101472.57 | F16: =F10+F11+F13+F14+F15 -> 123591.52 | G16: =G10+G11+G13+G14+G15 -> 143922.85
A17: Operating income before depreciation of new owned capacity | B17: =B5-B16 -> -8060 | C17: =C5-C16 -> 1681.5763 | D17: =D5-D16 -> 5386.49 | E17: =E5-E16 -> 2238.4835 | F17: =F5-F16 -> -1731.0409 | G17: =G5-G16 -> -6829.808
A18: Margin | B18: =IFERROR(B17/B5,0) -> -1.7579062 | C18: =IFERROR(C17/C5,0) -> 0.031009374 | D18: =IFERROR(D17/D5,0) -> 0.06622028 | E18: =IFERROR(E17/E5,0) -> 0.021583848 | F18: =IFERROR(F17/F5,0) -> -0.014205105 | G18: =IFERROR(G17/G5,0) -> -0.049818778
A19: Compute % of revenue | B19: =IFERROR(B10/B5,0) -> 1.597819 | C19: =IFERROR(C10/C5,0) -> 0.47980564 | D19: =IFERROR(D10/D5,0) -> 0.54377972 | E19: =IFERROR(E10/E5,0) -> 0.61841615 | F19: =IFERROR(F10/F5,0) -> 0.6842051 | G19: =IFERROR(G10/G5,0) -> 0.72981878
A20: Non-cash donation-matching charges (incl. in costs above) | C20: =Historicals!$B$78+Inputs!$B$37 -> 2126 | D20: 0 | E20: 0 | F20: 0 | G20: 0
A21: Discount factor to end 2026 | D21: =1/(1+Inputs!$B$19+Inputs!$I$89)^1 -> 0.89285714 | E21: =1/(1+Inputs!$B$19+Inputs!$I$89)^2 -> 0.79719388 | F21: =1/(1+Inputs!$B$19+Inputs!$I$89)^3 -> 0.71178025 | G21: =1/(1+Inputs!$B$19+Inputs!$I$89)^4 -> 0.63551808
A23: Third business line: value-share partnerships (hypothetical)
A24: Share of core revenue base under value-share | C24: 0 | D24: =Inputs!$C$97 -> 0.02 | E24: =Inputs!$C$98 -> 0.05 | F24: =Inputs!$C$99 -> 0.1 | G24: =Inputs!$C$100 -> 0.15
A25: Revenue base moved to value-share | C25: =C5*C24 -> 0 | D25: =D5*D24 -> 1626.84 | E25: =E5*E24 -> 5185.5525 | F25: =F5*F24 -> 12186.048 | G25: =G5*G24 -> 20563.957
A26: Value created per $1 of Claude spend | C26: =Inputs!$C$101 -> 8 | D26: =Inputs!$C$101 -> 8 | E26: =Inputs!$C$101 -> 8 | F26: =Inputs!$C$101 -> 8 | G26: =Inputs!$C$101 -> 8
A27: Economic value created for partners | C27: =C25*C26 -> 0 | D27: =D25*D26 -> 13014.72 | E27: =E25*E26 -> 41484.42 | F27: =F25*F26 -> 97488.387 | G27: =G25*G26 -> 164511.65
A28: Anthropic's cut | C28: =Inputs!$C$102 -> 0.15 | D28: =Inputs!$C$102 -> 0.15 | E28: =Inputs!$C$102 -> 0.15 | F28: =Inputs!$C$102 -> 0.15 | G28: =Inputs!$C$102 -> 0.15
A29: Value-share revenue (gross) | C29: =C27*C28 -> 0 | D29: =D27*D28 -> 1952.208 | E29: =E27*E28 -> 6222.663 | F29: =F27*F28 -> 14623.258 | G29: =G27*G28 -> 24676.748
A30: Token revenue given up | C30: =C25*Inputs!$C$103 -> 0 | D30: =D25*Inputs!$C$103 -> 488.052 | E30: =E25*Inputs!$C$103 -> 1555.6657 | F30: =F25*Inputs!$C$103 -> 3655.8145 | G30: =G25*Inputs!$C$103 -> 6169.187
A31: Net new revenue | C31: =C29-C30 -> 0 | D31: =D29-D30 -> 1464.156 | E31: =E29-E30 -> 4666.9973 | F31: =F29-F30 -> 10967.444 | G31: =G29-G30 -> 18507.561
A32: Delivery cost | C32: =C29*Inputs!$C$104 -> 0 | D32: =D29*Inputs!$C$104 -> 390.4416 | E32: =E29*Inputs!$C$104 -> 1244.5326 | F32: =F29*Inputs!$C$104 -> 2924.6516 | G32: =G29*Inputs!$C$104 -> 4935.3496
A33: Extra compute | C33: =C29*Inputs!$C$105 -> 0 | D33: =D29*Inputs!$C$105 -> 292.8312 | E33: =E29*Inputs!$C$105 -> 933.39945 | F33: =F29*Inputs!$C$105 -> 2193.4887 | G33: =G29*Inputs!$C$105 -> 3701.5122
A34: Selling, partner fees & overhead | C34: =C29*Inputs!$C$106 -> 0 | D34: =D29*Inputs!$C$106 -> 195.2208 | E34: =E29*Inputs!$C$106 -> 622.2663 | F34: =F29*Inputs!$C$106 -> 1462.3258 | G34: =G29*Inputs!$C$106 -> 2467.6748
A35: Value-share operating contribution | C35: =C29-C30-C32-C33-C34 -> 0 | D35: =D29-D30-D32-D33-D34 -> 585.6624 | E35: =E29-E30-E32-E33-E34 -> 1866.7989 | F35: =F29-F30-F32-F33-F34 -> 4386.9774 | G35: =G29-G30-G32-G33-G34 -> 7403.0244
A36: Value created as % of $40T knowledge-work pool | C36: =IFERROR(C27/Inputs!$B$27,0) -> 0 | D36: =IFERROR(D27/Inputs!$B$27,0) -> 0.000325368 | E36: =IFERROR(E27/Inputs!$B$27,0) -> 0.0010371105 | F36: =IFERROR(F27/Inputs!$B$27,0) -> 0.0024372097 | G36: =IFERROR(G27/Inputs!$B$27,0) -> 0.0041127913
A37: Value-share capital spending (per selected basis) | C37: =CHOOSE(Inputs!$B$35,C31*Inputs!B$55,C29*Inputs!$B$36,0) -> 0 | D37: =CHOOSE(Inputs!$B$35,D31*Inputs!C$55,D29*Inputs!$B$36,0) -> 58.56624 | E37: =CHOOSE(Inputs!$B$35,E31*Inputs!D$55,E29*Inputs!$B$36,0) -> 233.34986 | F37: =CHOOSE(Inputs!$B$35,F31*Inputs!E$55,F29*Inputs!$B$36,0) -> 548.37218 | G37: =CHOOSE(Inputs!$B$35,G31*Inputs!F$55,G29*Inputs!$B$36,0) -> 925.37805
A38: Value-share collection timing (working capital) | C38: 0 | D38: =-(D29-C29)*Inputs!$B$34/365 -> 0 | E38: =-(E29-D29)*Inputs!$B$34/365 -> 0 | F38: =-(F29-E29)*Inputs!$B$34/365 -> 0 | G38: =-(G29-F29)*Inputs!$B$34/365 -> 0
A40: Prepaid compute roll-forward (cash paid ahead of use)
A41: Prepaid balance, opening | C41: 0 | D41: =C46 -> 0 | E41: =D46 -> 0 | F41: =E46 -> 0 | G41: =F46 -> 0
A42: Prepayment paid (start of year) | C42: 0 | D42: =Inputs!$I$92 -> 0 | E42: 0 | F42: 0 | G42: 0
A43: Scheduled credits available (cumulative scheduled less used) | C43: =MAX(0,0) -> 0 | D43: =MAX(0,0) -> 0 | E43: =MAX(0,$D$42/Inputs!$B$40*MIN(1,Inputs!$B$40)-SUM($C45:D45)) -> 0 | F43: =MAX(0,$D$42/Inputs!$B$40*MIN(2,Inputs!$B$40)-SUM($C45:E45)) -> 0 | G43: =MAX(0,$D$42/Inputs!$B$40*MIN(3,Inputs!$B$40)-SUM($C45:F45)) -> 0
A44: Eligible compute charges this year | C44: =C10*Inputs!$B$39 -> 26018.9 | D44: =D10*Inputs!$B$39 -> 44232.13 | E44: =E10*Inputs!$B$39 -> 64136.588 | F44: =F10*Inputs!$B$39 -> 83377.565 | G44: =G10*Inputs!$B$39 -> 100053.08
A45: Credits used (capped by balance, schedule and eligible charges) | C45: =MAX(0,MIN(C41+C42,C43,C44)) -> 0 | D45: =MAX(0,MIN(D41+D42,D43,D44)) -> 0 | E45: =MAX(0,MIN(E41+E42,E43,E44)) -> 0 | F45: =MAX(0,MIN(F41+F42,F43,F44)) -> 0 | G45: =MAX(0,MIN(G41+G42,G43,G44)) -> 0
A46: Prepaid balance, closing | C46: =C41+C42-C45 -> 0 | D46: =D41+D42-D45 -> 0 | E46: =E41+E42-E45 -> 0 | F46: =F41+F42-F45 -> 0 | G46: =G41+G42-G45 -> 0
A48: Core business (tokens + subscriptions): earnings, taxes, cash
A49: Revenue | C49: =C5 -> 54228 | D49: =D5 -> 81342 | E49: =E5 -> 103711.05 | F49: =F5 -> 121860.48 | G49: =G5 -> 137093.04
A50: Operating income before depreciation of new owned capacity | C50: =C17 -> 1681.5763 | D50: =D17 -> 5386.49 | E50: =E17 -> 2238.4835 | F50: =F17 -> -1731.0409 | G50: =G17 -> -6829.808
A51: Capital spending | C51: =C5*Inputs!B$55 -> 1626.84 | D51: =D5*Inputs!C$55 -> 3253.68 | E51: =E5*Inputs!D$55 -> 5185.5525 | F51: =F5*Inputs!E$55 -> 6093.0242 | G51: =G5*Inputs!F$55 -> 6854.6522
A52: Depreciation of owned capacity bought from 2027 | C52: 0 | D52: =SUMPRODUCT($D51:D51,--((4-COLUMN($D51:D51))<Inputs!$B$32))/Inputs!$B$32 -> 650.736 | E52: =SUMPRODUCT($D51:E51,--((5-COLUMN($D51:E51))<Inputs!$B$32))/Inputs!$B$32 -> 1687.8465 | F52: =SUMPRODUCT($D51:F51,--((6-COLUMN($D51:F51))<Inputs!$B$32))/Inputs!$B$32 -> 2906.4513 | G52: =SUMPRODUCT($D51:G51,--((7-COLUMN($D51:G51))<Inputs!$B$32))/Inputs!$B$32 -> 4277.3818
A53: Operating income (earnings basis, after stock comp) | C53: =C50-C52 -> 1681.5763 | D53: =D50-D52 -> 4735.754 | E53: =E50-E52 -> 550.637 | F53: =F50-F52 -> -4637.4923 | G53: =G50-G52 -> -11107.19
A54: Operating margin | C54: =IFERROR(C53/C49,0) -> 0.031009374 | D54: =IFERROR(D53/D49,0) -> 0.05822028 | E54: =IFERROR(E53/E49,0) -> 0.0053093378 | F54: =IFERROR(F53/F49,0) -> -0.038055751 | G54: =IFERROR(G53/G49,0) -> -0.081019353
A55: Interest income (on opening cash) | C55: =Historicals!F43+C80*Inputs!$B$20/2 -> 2756.6375 | D55: =MAX(0,D80-D81)*Inputs!$B$20 -> 3507.9478 | E55: =MAX(0,E80-E81)*Inputs!$B$20 -> 3811.865 | F55: =MAX(0,F80-F81)*Inputs!$B$20 -> 4014.2818 | G55: =MAX(0,G80-G81)*Inputs!$B$20 -> 4132.2931
A56: Other taxable income adjustments | C56: =Inputs!B$56 -> 0 | D56: =Inputs!C$56 -> 0 | E56: =Inputs!D$56 -> 0 | F56: =Inputs!E$56 -> 0 | G56: =Inputs!F$56 -> 0
A57: IPO RSU tax deduction | C57: =IF(Inputs!$B$51=2026,Inputs!$B$50,0) -> 0 | D57: =IF(Inputs!$B$51=2027,Inputs!$B$50,0) -> 0 | E57: =IF(Inputs!$B$51=2028,Inputs!$B$50,0) -> 0 | F57: =IF(Inputs!$B$51=2029,Inputs!$B$50,0) -> 0 | G57: =IF(Inputs!$B$51=2030,Inputs!$B$50,0) -> 0
A58: Taxable income proxy | C58: =C53+C55+C56-C57 -> 4438.2138 | D58: =D53+D55+D56-D57 -> 8243.7018 | E58: =E53+E55+E56-E57 -> 4362.502 | F58: =F53+F55+F56-F57 -> -623.21048 | G58: =G53+G55+G56-G57 -> -6974.8967
A59: State taxable base (apportioned) | C59: =C58*Inputs!$B$46 -> 3195.514 | D59: =D58*Inputs!$B$46 -> 5935.4653 | E59: =E58*Inputs!$B$46 -> 3141.0015 | F59: =F58*Inputs!$B$46 -> -448.71154 | G59: =G58*Inputs!$B$46 -> -5021.9256
A60: State NOL, opening | C60: =Inputs!$B$48 -> 4200 | D60: =C62 -> 4200 | E60: =D62 -> 0 | F60: =E62 -> 0 | G60: =F62 -> 448.71154
A61: State NOL used | C61: =IF(AND(2026=2026,Inputs!$B$49=1),0,MIN(C60,MAX(0,C59))) -> 0 | D61: =IF(AND(2027=2026,Inputs!$B$49=1),0,MIN(D60,MAX(0,D59))) -> 4200 | E61: =IF(AND(2028=2026,Inputs!$B$49=1),0,MIN(E60,MAX(0,E59))) -> 0 | F61: =IF(AND(2029=2026,Inputs!$B$49=1),0,MIN(F60,MAX(0,F59))) -> 0 | G61: =IF(AND(2030=2026,Inputs!$B$49=1),0,MIN(G60,MAX(0,G59))) -> 0
A62: State NOL, closing | C62: =C60-C61+MAX(0,-C59) -> 4200 | D62: =D60-D61+MAX(0,-D59) -> 0 | E62: =E60-E61+MAX(0,-E59) -> 0 | F62: =F60-F61+MAX(0,-F59) -> 448.71154 | G62: =G60-G61+MAX(0,-G59) -> 5470.6372
A63: State tax | C63: =MAX(0,C59-C61)*Inputs!$B$47 -> 191.73084 | D63: =MAX(0,D59-D61)*Inputs!$B$47 -> 104.12792 | E63: =MAX(0,E59-E61)*Inputs!$B$47 -> 188.46009 | F63: =MAX(0,F59-F61)*Inputs!$B$47 -> 0 | G63: =MAX(0,G59-G61)*Inputs!$B$47 -> 0
A64: Federal taxable income before NOL (after state tax) | C64: =C58-C63 -> 4246.483 | D64: =D58-D63 -> 8139.5738 | E64: =E58-E63 -> 4174.0419 | F64: =F58-F63 -> -623.21048 | G64: =G58-G63 -> -6974.8967
A65: Federal NOL, opening | C65: =Inputs!$B$44 -> 8200 | D65: =C67 -> 4802.8136 | E65: =D67 -> 0 | F65: =E67 -> 0 | G65: =F67 -> 623.21048
A66: Federal NOL used (80% limit) | C66: =MIN(C65,Inputs!$B$45*MAX(0,C64)) -> 3397.1864 | D66: =MIN(D65,Inputs!$B$45*MAX(0,D64)) -> 4802.8136 | E66: =MIN(E65,Inputs!$B$45*MAX(0,E64)) -> 0 | F66: =MIN(F65,Inputs!$B$45*MAX(0,F64)) -> 0 | G66: =MIN(G65,Inputs!$B$45*MAX(0,G64)) -> 0
A67: Federal NOL, closing | C67: =C65-C66+MAX(0,-C64) -> 4802.8136 | D67: =D65-D66+MAX(0,-D64) -> 0 | E67: =E65-E66+MAX(0,-E64) -> 0 | F67: =F65-F66+MAX(0,-F64) -> 623.21048 | G67: =G65-G66+MAX(0,-G64) -> 7598.1072
A68: Federal tax | C68: =MAX(0,C64-C66)*Inputs!$B$43 -> 178.35229 | D68: =MAX(0,D64-D66)*Inputs!$B$43 -> 700.71965 | E68: =MAX(0,E64-E66)*Inputs!$B$43 -> 876.54881 | F68: =MAX(0,F64-F66)*Inputs!$B$43 -> 0 | G68: =MAX(0,G64-G66)*Inputs!$B$43 -> 0
A69: Cash taxes (selected method) | C69: =IF(Inputs!$I$90=0,MAX(0,C53+C55)*Inputs!B$54,IF(Inputs!$I$90=2,MAX(0,C58)*Inputs!$I$91,C63+C68)) -> 370.08312 | D69: =IF(Inputs!$I$90=0,MAX(0,D53+D55)*Inputs!C$54,IF(Inputs!$I$90=2,MAX(0,D58)*Inputs!$I$91,D63+D68)) -> 804.84757 | E69: =IF(Inputs!$I$90=0,MAX(0,E53+E55)*Inputs!D$54,IF(Inputs!$I$90=2,MAX(0,E58)*Inputs!$I$91,E63+E68)) -> 1065.0089 | F69: =IF(Inputs!$I$90=0,MAX(0,F53+F55)*Inputs!E$54,IF(Inputs!$I$90=2,MAX(0,F58)*Inputs!$I$91,F63+F68)) -> 0 | G69: =IF(Inputs!$I$90=0,MAX(0,G53+G55)*Inputs!F$54,IF(Inputs!$I$90=2,MAX(0,G58)*Inputs!$I$91,G63+G68)) -> 0
A70: Effective tax rate on taxable income | C70: =IF(C58>0,MIN(1,C69/C58),0) -> 0.0833856 | D70: =IF(D58>0,MIN(1,D69/D58),0) -> 0.097631815 | E70: =IF(E58>0,MIN(1,E69/E58),0) -> 0.244128 | F70: =IF(F58>0,MIN(1,F69/F58),0) -> 0 | G70: =IF(G58>0,MIN(1,G69/G58),0) -> 0
A71: Net income excl. non-cash fair value items | C71: =C53+C55-C69 -> 4068.1307 | D71: =D53+D55-D69 -> 7438.8542 | E71: =E53+E55-E69 -> 3297.4931 | F71: =F53+F55-F69 -> -623.21048 | G71: =G53+G55-G69 -> -6974.8967
A72: Non-cash stock comp & donation charges (added back for liquidity) | C72: =C12+C20 -> 8451.6198 | D72: =D12+D20 -> 7320.78 | E72: =E12+E20 -> 8296.884 | F72: =F12+F20 -> 8530.2339 | G72: =G12+G20 -> 8225.5827
A73: Working capital | C73: 0 | D73: =-(D5-C5)*Inputs!$B$33 -> 0 | E73: =-(E5-D5)*Inputs!$B$33 -> 0 | F73: =-(F5-E5)*Inputs!$B$33 -> 0 | G73: =-(G5-F5)*Inputs!$B$33 -> 0
A74: Compute prepayment timing (non-recurring; excluded from exit value) | C74: =-C$42+C$45 -> 0 | D74: =-D$42+D$45 -> 0 | E74: =-E$42+E$45 -> 0 | F74: =-F$42+F$45 -> 0 | G74: =-G$42+G$45 -> 0
A75: Actual cash flow (liquidity basis) | C75: =C53+C72+C52+C55-C69-C51+C73+C74 -> 10892.911 | D75: =D53+D72+D52+D55-D69-D51+D73+D74 -> 12156.69 | E75: =E53+E72+E52+E55-E69-E51+E73+E74 -> 8096.6711 | F75: =F53+F72+F52+F55-F69-F51+F73+F74 -> 4720.4505 | G75: =G53+G72+G52+G55-G69-G51+G73+G74 -> -1326.5845
A76: Economic operating cash flow (valuation basis: after stock comp, excl. interest) | C76: =C53+C52-(C69-C55*C70)-C51+C73+C74 -> -85.482921 | D76: =D53+D52-(D69-D55*D70)-D51+D73+D74 -> 1670.4497 | E76: =E53+E52-(E69-E55*E70)-E51+E73+E74 -> -3081.4949 | F76: =F53+F52-(F69-F55*F70)-F51+F73+F74 -> -7824.0651 | G76: =G53+G52-(G69-G55*G70)-G51+G73+G74 -> -13684.46
A77: Economic cash flow margin | C77: =IFERROR(C76/C49,0) -> -0.0015763613 | D77: =IFERROR(D76/D49,0) -> 0.020536128 | E77: =IFERROR(E76/E49,0) -> -0.02971231 | F77: =IFERROR(F76/F49,0) -> -0.064205105 | G77: =IFERROR(G76/G49,0) -> -0.099818778
A79: Cash roll-forward | C79: H2 2026 | D79: 2027E | E79: 2028E | F79: 2029E | G79: 2030E
A80: Opening cash | C80: =Inputs!$B$6 -> 131651 | D80: =C85 -> 140317.91 | E80: =D85 -> 152474.6 | F80: =E85 -> 160571.27 | G80: =F85 -> 165291.72
A81: of which paid at start of year (prepayment) | C81: =C$42 -> 0 | D81: =D$42 -> 0 | E81: =E$42 -> 0 | F81: =F$42 -> 0 | G81: =G$42 -> 0
A82: Cash flow in period (H2 only for 2026) | B82: 2026: full-year cash flow less H1 actual on the same basis | C82: =C75-Historicals!$B$79 -> 8666.9105 | D82: =D75 -> 12156.69 | E82: =E75 -> 8096.6711 | F82: =F75 -> 4720.4505 | G82: =G75 -> -1326.5845
A83: RSU tax withholding paid | C83: =-Inputs!$B$17 -> 0 | D83: 0 | E83: 0 | F83: 0 | G83: 0
A84: Primary IPO proceeds | C84: =Inputs!$B$15 -> 0 | D84: 0 | E84: 0 | F84: 0 | G84: 0
A85: Closing cash | C85: =C80+C82+C83+C84 -> 140317.91 | D85: =D80+D82+D83+D84 -> 152474.6 | E85: =E80+E82+E83+E84 -> 160571.27 | F85: =F80+F82+F83+F84 -> 165291.72 | G85: =G80+G82+G83+G84 -> 163965.14
A86: Lowest cash in the year (start-of-year payments or year end) | C86: =MIN(C80-C81,C85) -> 131651 | D86: =MIN(D80-D81,D85) -> 140317.91 | E86: =MIN(E80-E81,E85) -> 152474.6 | F86: =MIN(F80-F81,F85) -> 160571.27 | G86: =MIN(G80-G81,G85) -> 163965.14
A87: Lowest cash above the shortfall threshold | C87: =C86-Inputs!$B$29 -> 126651 | D87: =D86-Inputs!$B$29 -> 135317.91 | E87: =E86-Inputs!$B$29 -> 147474.6 | F87: =F86-Inputs!$B$29 -> 155571.27 | G87: =G86-Inputs!$B$29 -> 158965.14
A88: Year-end cash vs $5B covenant (cash proxy) | C88: =IF(C85<Inputs!$B$38,"Below","OK") -> OK | D88: =IF(D85<Inputs!$B$38,"Below","OK") -> OK | E88: =IF(E85<Inputs!$B$38,"Below","OK") -> OK | F88: =IF(F85<Inputs!$B$38,"Below","OK") -> OK | G88: =IF(G85<Inputs!$B$38,"Below","OK") -> OK
A89: Funding status | C89: =IF(C87<0,"Shortfall","OK") -> OK | D89: =IF(D87<0,"Shortfall","OK") -> OK | E89: =IF(E87<0,"Shortfall","OK") -> OK | F89: =IF(F87<0,"Shortfall","OK") -> OK | G89: =IF(G87<0,"Shortfall","OK") -> OK
A90: Peak funding need (intra-year) | G90: =MAX(0,-MIN(C87:G87)) -> 0
A91: Sensitivity: peak funding need with a $0 buffer | G91: =MAX(0,-MIN(C86:G86)) -> 0
A92: Funded cash path (illustrative equity raise) | C92: H2 2026 | D92: 2027E | E92: 2028E | F92: 2029E | G92: 2030E
A93: Financing year (start of the first shortfall year; proceeds arrive with the payment) | G93: =IF(G90=0,"none",IFERROR(2025+MATCH(1,INDEX(--(C87:G87<0),0),0),"none")) -> none
A94: Net proceeds needed (covers peak need) | G94: =G90 -> 0
A95: Issuance fees | G95: =G94/(1-Inputs!$B$31)*Inputs!$B$31 -> 0
A96: Gross amount raised | G96: =G94+G95 -> 0
A97: Net proceeds received in year | C97: =IF(AND(ISNUMBER($G$93),$G$93=2026),$G$94,0) -> 0 | D97: =IF(AND(ISNUMBER($G$93),$G$93=2027),$G$94,0) -> 0 | E97: =IF(AND(ISNUMBER($G$93),$G$93=2028),$G$94,0) -> 0 | F97: =IF(AND(ISNUMBER($G$93),$G$93=2029),$G$94,0) -> 0 | G97: =IF(AND(ISNUMBER($G$93),$G$93=2030),$G$94,0) -> 0
A98: Interest change vs. unfunded path (funded balance after start-of-year payments) | C98: =C97*Inputs!$B$20/2 -> 0 | D98: =MAX(0,C100-D81+D97)*Inputs!$B$20-D55 -> 0 | E98: =MAX(0,D100-E81+E97)*Inputs!$B$20-E55 -> 0 | F98: =MAX(0,E100-F81+F97)*Inputs!$B$20-F55 -> 0 | G98: =MAX(0,F100-G81+G97)*Inputs!$B$20-G55 -> 0
A99: Extra tax on that interest | C99: =C98*C70 -> 0 | D99: =D98*D70 -> 0 | E99: =E98*E70 -> 0 | F99: =F98*F70 -> 0 | G99: =G98*G70 -> 0
A100: Closing cash — funded | C100: =C85+SUM($C97:C97)+SUM($C98:C98)-SUM($C99:C99) -> 140317.91 | D100: =D85+SUM($C97:D97)+SUM($C98:D98)-SUM($C99:D99) -> 152474.6 | E100: =E85+SUM($C97:E97)+SUM($C98:E98)-SUM($C99:E99) -> 160571.27 | F100: =F85+SUM($C97:F97)+SUM($C98:F98)-SUM($C99:F99) -> 165291.72 | G100: =G85+SUM($C97:G97)+SUM($C98:G98)-SUM($C99:G99) -> 163965.14
A101: Lowest cash in the year — funded | C101: =MIN(C80-C81+0+C97,C100) -> 131651 | D101: =MIN(D80-D81+SUM($C97:C97)+SUM($C98:C98)-SUM($C99:C99)+D97,D100) -> 140317.91 | E101: =MIN(E80-E81+SUM($C97:D97)+SUM($C98:D98)-SUM($C99:D99)+E97,E100) -> 152474.6 | F101: =MIN(F80-F81+SUM($C97:E97)+SUM($C98:E98)-SUM($C99:E99)+F97,F100) -> 160571.27 | G101: =MIN(G80-G81+SUM($C97:F97)+SUM($C98:F98)-SUM($C99:F99)+G97,G100) -> 163965.14
A102: Funded path stays above threshold? | C102: =IF(C101-Inputs!$B$29<-0.5,"No","Yes") -> Yes | D102: =IF(D101-Inputs!$B$29<-0.5,"No","Yes") -> Yes | E102: =IF(E101-Inputs!$B$29<-0.5,"No","Yes") -> Yes | F102: =IF(F101-Inputs!$B$29<-0.5,"No","Yes") -> Yes | G102: =IF(G101-Inputs!$B$29<-0.5,"No","Yes") -> Yes
A104: Hybrid company (core + value-share): earnings, taxes, cash
A105: Revenue | C105: =C5+C31 -> 54228 | D105: =D5+D31 -> 82806.156 | E105: =E5+E31 -> 108378.05 | F105: =F5+F31 -> 132827.93 | G105: =G5+G31 -> 155600.61
A106: Operating income before depreciation of new owned capacity | C106: =C17+C35 -> 1681.5763 | D106: =D17+D35 -> 5972.1524 | E106: =E17+E35 -> 4105.2824 | F106: =F17+F35 -> 2655.9365 | G106: =G17+G35 -> 573.2164
A107: Capital spending | C107: =C51+C37 -> 1626.84 | D107: =D51+D37 -> 3312.2462 | E107: =E51+E37 -> 5418.9024 | F107: =F51+F37 -> 6641.3964 | G107: =G51+G37 -> 7780.0303
...

Sheet S4
A1: S4 Lower multiples — projections, cash and valuation ($ millions except per share)
A2: 2026E = H1 2026 actual + Q3 2026 implied + assumed Q4. Compute is forecast as cash spending (hosting, leases and owned capacity all treated as paid when expensed); the S-1 gives no payment schedule.
A4: Core business: income statement | B4: 2025A | C4: 2026E | D4: 2027E | E4: 2028E | F4: 2029E | G4: 2030E
A5: Revenue | B5: =Historicals!D35 -> 4585 | C5: =Historicals!F35+(Inputs!$B$5+Inputs!$J$60) -> 54228 | D5: =C5*(1+Inputs!$J$62) -> 108456 | E5: =D5*(1+Inputs!$J$63) -> 168106.8 | F5: =E5*(1+Inputs!$J$64) -> 226944.18 | G5: =F5*(1+Inputs!$J$65) -> 283680.22
A6: Growth | C6: =IFERROR(C5/B5-1,0) -> 10.827263 | D6: =IFERROR(D5/C5-1,0) -> 1 | E6: =IFERROR(E5/D5-1,0) -> 0.55 | F6: =IFERROR(F5/E5-1,0) -> 0.35 | G6: =IFERROR(G5/F5-1,0) -> 0.25
A7: Subscription revenue | B7: =Historicals!D51 -> 789 | C7: =Historicals!F51+(Inputs!$B$5+Inputs!$J$60)*Historicals!F51/Historicals!F35 -> 10728.393 | D7: =D5*Inputs!$J$61 -> 21691.2 | E7: =E5*Inputs!$J$61 -> 33621.36 | F7: =F5*Inputs!$J$61 -> 45388.836 | G7: =G5*Inputs!$J$61 -> 56736.045
A8: Consumption revenue | B8: =B5-B7 -> 3796 | C8: =C5-C7 -> 43499.607 | D8: =D5-D7 -> 86764.8 | E8: =E5-E7 -> 134485.44 | F8: =F5-F7 -> 181555.34 | G8: =G5-G7 -> 226944.18
A10: Compute and infrastructure | B10: =Historicals!D36 -> 7326 | C10: =Historicals!F36+(Inputs!$B$5+Inputs!$J$60)*Inputs!$J$66 -> 26018.9 | D10: =C10*(1+Inputs!$J$67) -> 44232.13 | E10: =D10*(1+Inputs!$J$68) -> 64136.588 | F10: =E10*(1+Inputs!$J$69) -> 83377.565 | G10: =F10*(1+Inputs!$J$70) -> 100053.08
A11: Personnel (incl. stock comp) | B11: =Historicals!D37 -> 1839 | C11: =Historicals!F37+(Inputs!$B$5+Inputs!$J$60)*Historicals!G24 -> 9249.6455 | D11: =D5*Inputs!$J$71 -> 15183.84 | E11: =E5*Inputs!$J$72 -> 21853.884 | F11: =F5*Inputs!$J$73 -> 27233.302 | G11: =G5*Inputs!$J$74 -> 31204.825
A12: of which stock comp | B12: =Historicals!D49 -> 1158 | C12: =Historicals!F49+(Inputs!$B$5+Inputs!$J$60)*Historicals!G29 -> 6325.6198 | D12: =D5*Inputs!$J$75 -> 9761.04 | E12: =E5*Inputs!$J$76 -> 13448.544 | F12: =F5*Inputs!$J$77 -> 15886.093 | G12: =G5*Inputs!$J$78 -> 17020.814
A13: Sales, marketing & partner fees | B13: =Historicals!D39 -> 568 | C13: =Historicals!F39+(Inputs!$B$5+Inputs!$J$60)*Historicals!G25 -> 10178.486 | D13: =D5*Inputs!$J$79 -> 18437.52 | E13: =E5*Inputs!$J$80 -> 26897.088 | F13: =F5*Inputs!$J$81 -> 34041.627 | G13: =G5*Inputs!$J$82 -> 42552.034
A14: Other operating & administrative | B14: =Historicals!D40 -> 1412 | C14: =Historicals!F40+(Inputs!$B$5+Inputs!$J$60)*Historicals!G26 -> 5099.3918 | D14: =D5*Inputs!$J$83 -> 8676.48 | E14: =E5*Inputs!$J$84 -> 11767.476 | F14: =F5*Inputs!$J$85 -> 13616.651 | G14: =G5*Inputs!$J$86 -> 17020.814
A15: One-time items (2025 Bartz settlement; 2026 Q3 donation-matching charge) | B15: =Historicals!D38 -> 1500 | C15: =Inputs!$B$37 -> 2000 | D15: 0 | E15: 0 | F15: 0 | G15: 0
A16: Total operating expenses | B16: =B10+B11+B13+B14+B15 -> 12645 | C16: =C10+C11+C13+C14+C15 -> 52546.424 | D16: =D10+D11+D13+D14+D15 -> 86529.97 | E16: =E10+E11+E13+E14+E15 -> 124655.04 | F16: =F10+F11+F13+F14+F15 -> 158269.14 | G16: =G10+G11+G13+G14+G15 -> 190830.75
A17: Operating income before depreciation of new owned capacity | B17: =B5-B16 -> -8060 | C17: =C5-C16 -> 1681.5763 | D17: =D5-D16 -> 21926.03 | E17: =E5-E16 -> 43451.764 | F17: =F5-F16 -> 68675.036 | G17: =G5-G16 -> 92849.475
A18: Margin | B18: =IFERROR(B17/B5,0) -> -1.7579062 | C18: =IFERROR(C17/C5,0) -> 0.031009374 | D18: =IFERROR(D17/D5,0) -> 0.20216521 | E18: =IFERROR(E17/E5,0) -> 0.25847713 | F18: =IFERROR(F17/F5,0) -> 0.30260761 | G18: =IFERROR(G17/G5,0) -> 0.3273033
A19: Compute % of revenue | B19: =IFERROR(B10/B5,0) -> 1.597819 | C19: =IFERROR(C10/C5,0) -> 0.47980564 | D19: =IFERROR(D10/D5,0) -> 0.40783479 | E19: =IFERROR(E10/E5,0) -> 0.38152287 | F19: =IFERROR(F10/F5,0) -> 0.36739239 | G19: =IFERROR(G10/G5,0) -> 0.3526967
A20: Non-cash donation-matching charges (incl. in costs above) | C20: =Historicals!$B$78+Inputs!$B$37 -> 2126 | D20: 0 | E20: 0 | F20: 0 | G20: 0
A21: Discount factor to end 2026 | D21: =1/(1+Inputs!$B$19+Inputs!$J$89)^1 -> 0.89285714 | E21: =1/(1+Inputs!$B$19+Inputs!$J$89)^2 -> 0.79719388 | F21: =1/(1+Inputs!$B$19+Inputs!$J$89)^3 -> 0.71178025 | G21: =1/(1+Inputs!$B$19+Inputs!$J$89)^4 -> 0.63551808
A23: Third business line: value-share partnerships (hypothetical)
A24: Share of core revenue base under value-share | C24: 0 | D24: =Inputs!$C$97 -> 0.02 | E24: =Inputs!$C$98 -> 0.05 | F24: =Inputs!$C$99 -> 0.1 | G24: =Inputs!$C$100 -> 0.15
A25: Revenue base moved to value-share | C25: =C5*C24 -> 0 | D25: =D5*D24 -> 2169.12 | E25: =E5*E24 -> 8405.34 | F25: =F5*F24 -> 22694.418 | G25: =G5*G24 -> 42552.034
A26: Value created per $1 of Claude spend | C26: =Inputs!$C$101 -> 8 | D26: =Inputs!$C$101 -> 8 | E26: =Inputs!$C$101 -> 8 | F26: =Inputs!$C$101 -> 8 | G26: =Inputs!$C$101 -> 8
A27: Economic value created for partners | C27: =C25*C26 -> 0 | D27: =D25*D26 -> 17352.96 | E27: =E25*E26 -> 67242.72 | F27: =F25*F26 -> 181555.34 | G27: =G25*G26 -> 340416.27
A28: Anthropic's cut | C28: =Inputs!$C$102 -> 0.15 | D28: =Inputs!$C$102 -> 0.15 | E28: =Inputs!$C$102 -> 0.15 | F28: =Inputs!$C$102 -> 0.15 | G28: =Inputs!$C$102 -> 0.15
A29: Value-share revenue (gross) | C29: =C27*C28 -> 0 | D29: =D27*D28 -> 2602.944 | E29: =E27*E28 -> 10086.408 | F29: =F27*F28 -> 27233.302 | G29: =G27*G28 -> 51062.44
A30: Token revenue given up | C30: =C25*Inputs!$C$103 -> 0 | D30: =D25*Inputs!$C$103 -> 650.736 | E30: =E25*Inputs!$C$103 -> 2521.602 | F30: =F25*Inputs!$C$103 -> 6808.3254 | G30: =G25*Inputs!$C$103 -> 12765.61
A31: Net new revenue | C31: =C29-C30 -> 0 | D31: =D29-D30 -> 1952.208 | E31: =E29-E30 -> 7564.806 | F31: =F29-F30 -> 20424.976 | G31: =G29-G30 -> 38296.83
A32: Delivery cost | C32: =C29*Inputs!$C$104 -> 0 | D32: =D29*Inputs!$C$104 -> 520.5888 | E32: =E29*Inputs!$C$104 -> 2017.2816 | F32: =F29*Inputs!$C$104 -> 5446.6603 | G32: =G29*Inputs!$C$104 -> 10212.488
A33: Extra compute | C33: =C29*Inputs!$C$105 -> 0 | D33: =D29*Inputs!$C$105 -> 390.4416 | E33: =E29*Inputs!$C$105 -> 1512.9612 | F33: =F29*Inputs!$C$105 -> 4084.9952 | G33: =G29*Inputs!$C$105 -> 7659.3661
A34: Selling, partner fees & overhead | C34: =C29*Inputs!$C$106 -> 0 | D34: =D29*Inputs!$C$106 -> 260.2944 | E34: =E29*Inputs!$C$106 -> 1008.6408 | F34: =F29*Inputs!$C$106 -> 2723.3302 | G34: =G29*Inputs!$C$106 -> 5106.2441
A35: Value-share operating contribution | C35: =C29-C30-C32-C33-C34 -> 0 | D35: =D29-D30-D32-D33-D34 -> 780.8832 | E35: =E29-E30-E32-E33-E34 -> 3025.9224 | F35: =F29-F30-F32-F33-F34 -> 8169.9905 | G35: =G29-G30-G32-G33-G34 -> 15318.732
A36: Value created as % of $40T knowledge-work pool | C36: =IFERROR(C27/Inputs!$B$27,0) -> 0 | D36: =IFERROR(D27/Inputs!$B$27,0) -> 0.000433824 | E36: =IFERROR(E27/Inputs!$B$27,0) -> 0.001681068 | F36: =IFERROR(F27/Inputs!$B$27,0) -> 0.0045388836 | G36: =IFERROR(G27/Inputs!$B$27,0) -> 0.0085104067
A37: Value-share capital spending (per selected basis) | C37: =CHOOSE(Inputs!$B$35,C31*Inputs!B$55,C29*Inputs!$B$36,0) -> 0 | D37: =CHOOSE(Inputs!$B$35,D31*Inputs!C$55,D29*Inputs!$B$36,0) -> 78.08832 | E37: =CHOOSE(Inputs!$B$35,E31*Inputs!D$55,E29*Inputs!$B$36,0) -> 378.2403 | F37: =CHOOSE(Inputs!$B$35,F31*Inputs!E$55,F29*Inputs!$B$36,0) -> 1021.2488 | G37: =CHOOSE(Inputs!$B$35,G31*Inputs!F$55,G29*Inputs!$B$36,0) -> 1914.8415
A38: Value-share collection timing (working capital) | C38: 0 | D38: =-(D29-C29)*Inputs!$B$34/365 -> 0 | E38: =-(E29-D29)*Inputs!$B$34/365 -> 0 | F38: =-(F29-E29)*Inputs!$B$34/365 -> 0 | G38: =-(G29-F29)*Inputs!$B$34/365 -> 0
A40: Prepaid compute roll-forward (cash paid ahead of use)
A41: Prepaid balance, opening | C41: 0 | D41: =C46 -> 0 | E41: =D46 -> 0 | F41: =E46 -> 0 | G41: =F46 -> 0
A42: Prepayment paid (start of year) | C42: 0 | D42: =Inputs!$J$92 -> 0 | E42: 0 | F42: 0 | G42: 0
A43: Scheduled credits available (cumulative scheduled less used) | C43: =MAX(0,0) -> 0 | D43: =MAX(0,0) -> 0 | E43: =MAX(0,$D$42/Inputs!$B$40*MIN(1,Inputs!$B$40)-SUM($C45:D45)) -> 0 | F43: =MAX(0,$D$42/Inputs!$B$40*MIN(2,Inputs!$B$40)-SUM($C45:E45)) -> 0 | G43: =MAX(0,$D$42/Inputs!$B$40*MIN(3,Inputs!$B$40)-SUM($C45:F45)) -> 0
A44: Eligible compute charges this year | C44: =C10*Inputs!$B$39 -> 26018.9 | D44: =D10*Inputs!$B$39 -> 44232.13 | E44: =E10*Inputs!$B$39 -> 64136.588 | F44: =F10*Inputs!$B$39 -> 83377.565 | G44: =G10*Inputs!$B$39 -> 100053.08
A45: Credits used (capped by balance, schedule and eligible charges) | C45: =MAX(0,MIN(C41+C42,C43,C44)) -> 0 | D45: =MAX(0,MIN(D41+D42,D43,D44)) -> 0 | E45: =MAX(0,MIN(E41+E42,E43,E44)) -> 0 | F45: =MAX(0,MIN(F41+F42,F43,F44)) -> 0 | G45: =MAX(0,MIN(G41+G42,G43,G44)) -> 0
A46: Prepaid balance, closing | C46: =C41+C42-C45 -> 0 | D46: =D41+D42-D45 -> 0 | E46: =E41+E42-E45 -> 0 | F46: =F41+F42-F45 -> 0 | G46: =G41+G42-G45 -> 0
A48: Core business (tokens + subscriptions): earnings, taxes, cash
A49: Revenue | C49: =C5 -> 54228 | D49: =D5 -> 108456 | E49: =E5 -> 168106.8 | F49: =F5 -> 226944.18 | G49: =G5 -> 283680.22
A50: Operating income before depreciation of new owned capacity | C50: =C17 -> 1681.5763 | D50: =D17 -> 21926.03 | E50: =E17 -> 43451.764 | F50: =F17 -> 68675.036 | G50: =G17 -> 92849.475
A51: Capital spending | C51: =C5*Inputs!B$55 -> 1626.84 | D51: =D5*Inputs!C$55 -> 4338.24 | E51: =E5*Inputs!D$55 -> 8405.34 | F51: =F5*Inputs!E$55 -> 11347.209 | G51: =G5*Inputs!F$55 -> 14184.011
A52: Depreciation of owned capacity bought from 2027 | C52: 0 | D52: =SUMPRODUCT($D51:D51,--((4-COLUMN($D51:D51))<Inputs!$B$32))/Inputs!$B$32 -> 867.648 | E52: =SUMPRODUCT($D51:E51,--((5-COLUMN($D51:E51))<Inputs!$B$32))/Inputs!$B$32 -> 2548.716 | F52: =SUMPRODUCT($D51:F51,--((6-COLUMN($D51:F51))<Inputs!$B$32))/Inputs!$B$32 -> 4818.1578 | G52: =SUMPRODUCT($D51:G51,--((7-COLUMN($D51:G51))<Inputs!$B$32))/Inputs!$B$32 -> 7654.96
A53: Operating income (earnings basis, after stock comp) | C53: =C50-C52 -> 1681.5763 | D53: =D50-D52 -> 21058.382 | E53: =E50-E52 -> 40903.048 | F53: =F50-F52 -> 63856.878 | G53: =G50-G52 -> 85194.515
A54: Operating margin | C54: =IFERROR(C53/C49,0) -> 0.031009374 | D54: =IFERROR(D53/D49,0) -> 0.19416521 | E54: =IFERROR(E53/E49,0) -> 0.24331584 | F54: =IFERROR(F53/F49,0) -> 0.28137702 | G54: =IFERROR(G53/G49,0) -> 0.30031884
A55: Interest income (on opening cash) | C55: =Historicals!F43+C80*Inputs!$B$20/2 -> 2756.6375 | D55: =MAX(0,D80-D81)*Inputs!$B$20 -> 3507.9478 | E55: =MAX(0,E80-E81)*Inputs!$B$20 -> 4159.6258 | F55: =MAX(0,F80-F81)*Inputs!$B$20 -> 5200.9641 | G55: =MAX(0,G80-G81)*Inputs!$B$20 -> 6739.8623
A56: Other taxable income adjustments | C56: =Inputs!B$56 -> 0 | D56: =Inputs!C$56 -> 0 | E56: =Inputs!D$56 -> 0 | F56: =Inputs!E$56 -> 0 | G56: =Inputs!F$56 -> 0
A57: IPO RSU tax deduction | C57: =IF(Inputs!$B$51=2026,Inputs!$B$50,0) -> 0 | D57: =IF(Inputs!$B$51=2027,Inputs!$B$50,0) -> 0 | E57: =IF(Inputs!$B$51=2028,Inputs!$B$50,0) -> 0 | F57: =IF(Inputs!$B$51=2029,Inputs!$B$50,0) -> 0 | G57: =IF(Inputs!$B$51=2030,Inputs!$B$50,0) -> 0
A58: Taxable income proxy | C58: =C53+C55+C56-C57 -> 4438.2138 | D58: =D53+D55+D56-D57 -> 24566.33 | E58: =E53+E55+E56-E57 -> 45062.673 | F58: =F53+F55+F56-F57 -> 69057.842 | G58: =G53+G55+G56-G57 -> 91934.377
A59: State taxable base (apportioned) | C59: =C58*Inputs!$B$46 -> 3195.514 | D59: =D58*Inputs!$B$46 -> 17687.757 | E59: =E58*Inputs!$B$46 -> 32445.125 | F59: =F58*Inputs!$B$46 -> 49721.646 | G59: =G58*Inputs!$B$46 -> 66192.752
A60: State NOL, opening | C60: =Inputs!$B$48 -> 4200 | D60: =C62 -> 4200 | E60: =D62 -> 0 | F60: =E62 -> 0 | G60: =F62 -> 0
A61: State NOL used | C61: =IF(AND(2026=2026,Inputs!$B$49=1),0,MIN(C60,MAX(0,C59))) -> 0 | D61: =IF(AND(2027=2026,Inputs!$B$49=1),0,MIN(D60,MAX(0,D59))) -> 4200 | E61: =IF(AND(2028=2026,Inputs!$B$49=1),0,MIN(E60,MAX(0,E59))) -> 0 | F61: =IF(AND(2029=2026,Inputs!$B$49=1),0,MIN(F60,MAX(0,F59))) -> 0 | G61: =IF(AND(2030=2026,Inputs!$B$49=1),0,MIN(G60,MAX(0,G59))) -> 0
A62: State NOL, closing | C62: =C60-C61+MAX(0,-C59) -> 4200 | D62: =D60-D61+MAX(0,-D59) -> 0 | E62: =E60-E61+MAX(0,-E59) -> 0 | F62: =F60-F61+MAX(0,-F59) -> 0 | G62: =G60-G61+MAX(0,-G59) -> 0
A63: State tax | C63: =MAX(0,C59-C61)*Inputs!$B$47 -> 191.73084 | D63: =MAX(0,D59-D61)*Inputs!$B$47 -> 809.26545 | E63: =MAX(0,E59-E61)*Inputs!$B$47 -> 1946.7075 | F63: =MAX(0,F59-F61)*Inputs!$B$47 -> 2983.2988 | G63: =MAX(0,G59-G61)*Inputs!$B$47 -> 3971.5651
A64: Federal taxable income before NOL (after state tax) | C64: =C58-C63 -> 4246.483 | D64: =D58-D63 -> 23757.064 | E64: =E58-E63 -> 43115.966 | F64: =F58-F63 -> 66074.543 | G64: =G58-G63 -> 87962.812
A65: Federal NOL, opening | C65: =Inputs!$B$44 -> 8200 | D65: =C67 -> 4802.8136 | E65: =D67 -> 0 | F65: =E67 -> 0 | G65: =F67 -> 0
A66: Federal NOL used (80% limit) | C66: =MIN(C65,Inputs!$B$45*MAX(0,C64)) -> 3397.1864 | D66: =MIN(D65,Inputs!$B$45*MAX(0,D64)) -> 4802.8136 | E66: =MIN(E65,Inputs!$B$45*MAX(0,E64)) -> 0 | F66: =MIN(F65,Inputs!$B$45*MAX(0,F64)) -> 0 | G66: =MIN(G65,Inputs!$B$45*MAX(0,G64)) -> 0
A67: Federal NOL, closing | C67: =C65-C66+MAX(0,-C64) -> 4802.8136 | D67: =D65-D66+MAX(0,-D64) -> 0 | E67: =E65-E66+MAX(0,-E64) -> 0 | F67: =F65-F66+MAX(0,-F64) -> 0 | G67: =G65-G66+MAX(0,-G64) -> 0
A68: Federal tax | C68: =MAX(0,C64-C66)*Inputs!$B$43 -> 178.35229 | D68: =MAX(0,D64-D66)*Inputs!$B$43 -> 3980.3926 | E68: =MAX(0,E64-E66)*Inputs!$B$43 -> 9054.3528 | F68: =MAX(0,F64-F66)*Inputs!$B$43 -> 13875.654 | G68: =MAX(0,G64-G66)*Inputs!$B$43 -> 18472.191
A69: Cash taxes (selected method) | C69: =IF(Inputs!$J$90=0,MAX(0,C53+C55)*Inputs!B$54,IF(Inputs!$J$90=2,MAX(0,C58)*Inputs!$J$91,C63+C68)) -> 370.08312 | D69: =IF(Inputs!$J$90=0,MAX(0,D53+D55)*Inputs!C$54,IF(Inputs!$J$90=2,MAX(0,D58)*Inputs!$J$91,D63+D68)) -> 4789.6581 | E69: =IF(Inputs!$J$90=0,MAX(0,E53+E55)*Inputs!D$54,IF(Inputs!$J$90=2,MAX(0,E58)*Inputs!$J$91,E63+E68)) -> 11001.06 | F69: =IF(Inputs!$J$90=0,MAX(0,F53+F55)*Inputs!E$54,IF(Inputs!$J$90=2,MAX(0,F58)*Inputs!$J$91,F63+F68)) -> 16858.953 | G69: =IF(Inputs!$J$90=0,MAX(0,G53+G55)*Inputs!F$54,IF(Inputs!$J$90=2,MAX(0,G58)*Inputs!$J$91,G63+G68)) -> 22443.756
A70: Effective tax rate on taxable income | C70: =IF(C58>0,MIN(1,C69/C58),0) -> 0.0833856 | D70: =IF(D58>0,MIN(1,D69/D58),0) -> 0.1949684 | E70: =IF(E58>0,MIN(1,E69/E58),0) -> 0.244128 | F70: =IF(F58>0,MIN(1,F69/F58),0) -> 0.244128 | G70: =IF(G58>0,MIN(1,G69/G58),0) -> 0.244128
A71: Net income excl. non-cash fair value items | C71: =C53+C55-C69 -> 4068.1307 | D71: =D53+D55-D69 -> 19776.672 | E71: =E53+E55-E69 -> 34061.613 | F71: =F53+F55-F69 -> 52198.889 | G71: =G53+G55-G69 -> 69490.622
A72: Non-cash stock comp & donation charges (added back for liquidity) | C72: =C12+C20 -> 8451.6198 | D72: =D12+D20 -> 9761.04 | E72: =E12+E20 -> 13448.544 | F72: =F12+F20 -> 15886.093 | G72: =G12+G20 -> 17020.814
A73: Working capital | C73: 0 | D73: =-(D5-C5)*Inputs!$B$33 -> 0 | E73: =-(E5-D5)*Inputs!$B$33 -> 0 | F73: =-(F5-E5)*Inputs!$B$33 -> 0 | G73: =-(G5-F5)*Inputs!$B$33 -> 0
A74: Compute prepayment timing (non-recurring; excluded from exit value) | C74: =-C$42+C$45 -> 0 | D74: =-D$42+D$45 -> 0 | E74: =-E$42+E$45 -> 0 | F74: =-F$42+F$45 -> 0 | G74: =-G$42+G$45 -> 0
A75: Actual cash flow (liquidity basis) | C75: =C53+C72+C52+C55-C69-C51+C73+C74 -> 10892.911 | D75: =D53+D72+D52+D55-D69-D51+D73+D74 -> 26067.12 | E75: =E53+E72+E52+E55-E69-E51+E73+E74 -> 41653.533 | F75: =F53+F72+F52+F55-F69-F51+F73+F74 -> 61555.93 | G75: =G53+G72+G52+G55-G69-G51+G73+G74 -> 79982.384
A76: Economic operating cash flow (valuation basis: after stock comp, excl. interest) | C76: =C53+C52-(C69-C55*C70)-C51+C73+C74 -> -85.482921 | D76: =D53+D52-(D69-D55*D70)-D51+D73+D74 -> 13482.071 | E76: =E53+E52-(E69-E55*E70)-E51+E73+E74 -> 25060.844 | F76: =F53+F52-(F69-F55*F70)-F51+F73+F74 -> 41738.575 | G76: =G53+G52-(G69-G55*G70)-G51+G73+G74 -> 57867.097
A77: Economic cash flow margin | C77: =IFERROR(C76/C49,0) -> -0.0015763613 | D77: =IFERROR(D76/D49,0) -> 0.12430913 | E77: =IFERROR(E76/E49,0) -> 0.14907692 | F77: =IFERROR(F76/F49,0) -> 0.1839156 | G77: =IFERROR(G76/G49,0) -> 0.20398707
A79: Cash roll-forward | C79: H2 2026 | D79: 2027E | E79: 2028E | F79: 2029E | G79: 2030E
A80: Opening cash | C80: =Inputs!$B$6 -> 131651 | D80: =C85 -> 140317.91 | E80: =D85 -> 166385.03 | F80: =E85 -> 208038.56 | G80: =F85 -> 269594.49
A81: of which paid at start of year (prepayment) | C81: =C$42 -> 0 | D81: =D$42 -> 0 | E81: =E$42 -> 0 | F81: =F$42 -> 0 | G81: =G$42 -> 0
A82: Cash flow in period (H2 only for 2026) | B82: 2026: full-year cash flow less H1 actual on the same basis | C82: =C75-Historicals!$B$79 -> 8666.9105 | D82: =D75 -> 26067.12 | E82: =E75 -> 41653.533 | F82: =F75 -> 61555.93 | G82: =G75 -> 79982.384
A83: RSU tax withholding paid | C83: =-Inputs!$B$17 -> 0 | D83: 0 | E83: 0 | F83: 0 | G83: 0
A84: Primary IPO proceeds | C84: =Inputs!$B$15 -> 0 | D84: 0 | E84: 0 | F84: 0 | G84: 0
A85: Closing cash | C85: =C80+C82+C83+C84 -> 140317.91 | D85: =D80+D82+D83+D84 -> 166385.03 | E85: =E80+E82+E83+E84 -> 208038.56 | F85: =F80+F82+F83+F84 -> 269594.49 | G85: =G80+G82+G83+G84 -> 349576.88
A86: Lowest cash in the year (start-of-year payments or year end) | C86: =MIN(C80-C81,C85) -> 131651 | D86: =MIN(D80-D81,D85) -> 140317.91 | E86: =MIN(E80-E81,E85) -> 166385.03 | F86: =MIN(F80-F81,F85) -> 208038.56 | G86: =MIN(G80-G81,G85) -> 269594.49
A87: Lowest cash above the shortfall threshold | C87: =C86-Inputs!$B$29 -> 126651 | D87: =D86-Inputs!$B$29 -> 135317.91 | E87: =E86-Inputs!$B$29 -> 161385.03 | F87: =F86-Inputs!$B$29 -> 203038.56 | G87: =G86-Inputs!$B$29 -> 264594.49
A88: Year-end cash vs $5B covenant (cash proxy) | C88: =IF(C85<Inputs!$B$38,"Below","OK") -> OK | D88: =IF(D85<Inputs!$B$38,"Below","OK") -> OK | E88: =IF(E85<Inputs!$B$38,"Below","OK") -> OK | F88: =IF(F85<Inputs!$B$38,"Below","OK") -> OK | G88: =IF(G85<Inputs!$B$38,"Below","OK") -> OK
A89: Funding status | C89: =IF(C87<0,"Shortfall","OK") -> OK | D89: =IF(D87<0,"Shortfall","OK") -> OK | E89: =IF(E87<0,"Shortfall","OK") -> OK | F89: =IF(F87<0,"Shortfall","OK") -> OK | G89: =IF(G87<0,"Shortfall","OK") -> OK
A90: Peak funding need (intra-year) | G90: =MAX(0,-MIN(C87:G87)) -> 0
A91: Sensitivity: peak funding need with a $0 buffer | G91: =MAX(0,-MIN(C86:G86)) -> 0
A92: Funded cash path (illustrative equity raise) | C92: H2 2026 | D92: 2027E | E92: 2028E | F92: 2029E | G92: 2030E
A93: Financing year (start of the first shortfall year; proceeds arrive with the payment) | G93: =IF(G90=0,"none",IFERROR(2025+MATCH(1,INDEX(--(C87:G87<0),0),0),"none")) -> none
A94: Net proceeds needed (covers peak need) | G94: =G90 -> 0
A95: Issuance fees | G95: =G94/(1-Inputs!$B$31)*Inputs!$B$31 -> 0
A96: Gross amount raised | G96: =G94+G95 -> 0
A97: Net proceeds received in year | C97: =IF(AND(ISNUMBER($G$93),$G$93=2026),$G$94,0) -> 0 | D97: =IF(AND(ISNUMBER($G$93),$G$93=2027),$G$94,0) -> 0 | E97: =IF(AND(ISNUMBER($G$93),$G$93=2028),$G$94,0) -> 0 | F97: =IF(AND(ISNUMBER($G$93),$G$93=2029),$G$94,0) -> 0 | G97: =IF(AND(ISNUMBER($G$93),$G$93=2030),$G$94,0) -> 0
A98: Interest change vs. unfunded path (funded balance after start-of-year payments) | C98: =C97*Inputs!$B$20/2 -> 0 | D98: =MAX(0,C100-D81+D97)*Inputs!$B$20-D55 -> 0 | E98: =MAX(0,D100-E81+E97)*Inputs!$B$20-E55 -> 0 | F98: =MAX(0,E100-F81+F97)*Inputs!$B$20-F55 -> 0 | G98: =MAX(0,F100-G81+G97)*Inputs!$B$20-G55 -> 0
A99: Extra tax on that interest | C99: =C98*C70 -> 0 | D99: =D98*D70 -> 0 | E99: =E98*E70 -> 0 | F99: =F98*F70 -> 0 | G99: =G98*G70 -> 0
A100: Closing cash — funded | C100: =C85+SUM($C97:C97)+SUM($C98:C98)-SUM($C99:C99) -> 140317.91 | D100: =D85+SUM($C97:D97)+SUM($C98:D98)-SUM($C99:D99) -> 166385.03 | E100: =E85+SUM($C97:E97)+SUM($C98:E98)-SUM($C99:E99) -> 208038.56 | F100: =F85+SUM($C97:F97)+SUM($C98:F98)-SUM($C99:F99) -> 269594.49 | G100: =G85+SUM($C97:G97)+SUM($C98:G98)-SUM($C99:G99) -> 349576.88
A101: Lowest cash in the year — funded | C101: =MIN(C80-C81+0+C97,C100) -> 131651 | D101: =MIN(D80-D81+SUM($C97:C97)+SUM($C98:C98)-SUM($C99:C99)+D97,D100) -> 140317.91 | E101: =MIN(E80-E81+SUM($C97:D97)+SUM($C98:D98)-SUM($C99:D99)+E97,E100) -> 166385.03 | F101: =MIN(F80-F81+SUM($C97:E97)+SUM($C98:E98)-SUM($C99:E99)+F97,F100) -> 208038.56 | G101: =MIN(G80-G81+SUM($C97:F97)+SUM($C98:F98)-SUM($C99:F99)+G97,G100) -> 269594.49
A102: Funded path stays above threshold? | C102: =IF(C101-Inputs!$B$29<-0.5,"No","Yes") -> Yes | D102: =IF(D101-Inputs!$B$29<-0.5,"No","Yes") -> Yes | E102: =IF(E101-Inputs!$B$29<-0.5,"No","Yes") -> Yes | F102: =IF(F101-Inputs!$B$29<-0.5,"No","Yes") -> Yes | G102: =IF(G101-Inputs!$B$29<-0.5,"No","Yes") -> Yes
A104: Hybrid company (core + value-share): earnings, taxes, cash
A105: Revenue | C105: =C5+C31 -> 54228 | D105: =D5+D31 -> 110408.21 | E105: =E5+E31 -> 175671.61 | F105: =F5+F31 -> 247369.16 | G105: =G5+G31 -> 321977.06
A106: Operating income before depreciation of new owned capacity | C106: =C17+C35 -> 1681.5763 | D106: =D17+D35 -> 22706.913 | E106: =E17+E35 -> 46477.686 | F106: =F17+F35 -> 76845.026 | G106: =G17+G35 -> 108168.21
A107: Capital spending | C107: =C51+C37 -> 1626.84 | D107: =D51+D37 -> 4416.3283 | E107: =E51+E37 -> 8783.5803 | F107: =F51+F37 -> 12368.458 | G107: =G51+G37 -> 16098.853
...

Sheet S5
A1: S5 Discount +2pts — projections, cash and valuation ($ millions except per share)
A2: 2026E = H1 2026 actual + Q3 2026 implied + assumed Q4. Compute is forecast as cash spending (hosting, leases and owned capacity all treated as paid when expensed); the S-1 gives no payment schedule.
A4: Core business: income statement | B4: 2025A | C4: 2026E | D4: 2027E | E4: 2028E | F4: 2029E | G4: 2030E
A5: Revenue | B5: =Historicals!D35 -> 4585 | C5: =Historicals!F35+(Inputs!$B$5+Inputs!$K$60) -> 54228 | D5: =C5*(1+Inputs!$K$62) -> 108456 | E5: =D5*(1+Inputs!$K$63) -> 168106.8 | F5: =E5*(1+Inputs!$K$64) -> 226944.18 | G5: =F5*(1+Inputs!$K$65) -> 283680.22
A6: Growth | C6: =IFERROR(C5/B5-1,0) -> 10.827263 | D6: =IFERROR(D5/C5-1,0) -> 1 | E6: =IFERROR(E5/D5-1,0) -> 0.55 | F6: =IFERROR(F5/E5-1,0) -> 0.35 | G6: =IFERROR(G5/F5-1,0) -> 0.25
A7: Subscription revenue | B7: =Historicals!D51 -> 789 | C7: =Historicals!F51+(Inputs!$B$5+Inputs!$K$60)*Historicals!F51/Historicals!F35 -> 10728.393 | D7: =D5*Inputs!$K$61 -> 21691.2 | E7: =E5*Inputs!$K$61 -> 33621.36 | F7: =F5*Inputs!$K$61 -> 45388.836 | G7: =G5*Inputs!$K$61 -> 56736.045
A8: Consumption revenue | B8: =B5-B7 -> 3796 | C8: =C5-C7 -> 43499.607 | D8: =D5-D7 -> 86764.8 | E8: =E5-E7 -> 134485.44 | F8: =F5-F7 -> 181555.34 | G8: =G5-G7 -> 226944.18
